Workbook
Name Acq_Fee_Pct: Overview!$F$32
Name Acquisition_Price: Overview!$C$14
Name Addl_Income: Overview!$C$28
Name AM_Fee_Pct: Overview!$F$33
Name Amort1_Years: Overview!$F$16
Name Assessed_Value: Overview!$C$26
Name Close_Date: Overview!$C$6
Name Closing_Cost_Pct: Overview!$C$15
Name Credit_Loss_Pct: Overview!$C$21
Name Default_Downtime: Overview!$F$8
Name Default_Renewal_Prob: Overview!$F$9
Name Exit_Cap: Overview!$C$18
Name Exit_Month: Overview!$C$19
Name IO1_Months: Overview!$F$15
Name LC_New: Overview!$F$6
Name LC_Renewal: Overview!$F$7
Name Legal_Monthly: Overview!$F$34
Name Loan1_Amount: Overview!$F$13
Name Mgmt_Fee_Pct: Overview!$C$27
Name Millage_Rate: Overview!$C$24
Name Monthly_OpEx: 'OM OpEx'!$G$21
Name NRA: Overview!$C$7
Name opex_annual_growth: Overview!$C$25
Name opex_no_pm: 'OM OpEx'!$G$21
Name Orig_Fee1: Overview!$F$18
Name Rate1: Overview!$F$14
Name Refi_Amort: Overview!$F$27
Name Refi_IO: Overview!$F$26
Name Refi_Loan_Amt: Overview!$F$24
Name Refi_LTV: Overview!$F$23
Name Refi_Month: Overview!$F$22
Name Refi_Orig_Fee: Overview!$F$29
Name Refi_Rate: Overview!$F$25
Name Refi_Term: Overview!$F$28
Name Refi_Toggle: Overview!$F$21
Name Rent_Growth: Overview!$C$23
Name Repl_Reserve_PSF: Overview!$C$22
Name Selling_Cost_Pct: Overview!$C$20
Name Term1_Months: Overview!$F$17
Name TI_New: Overview!$F$4
Name TI_Renewal: Overview!$F$5

Sheet Monthly CF
A1: MONTHLY CASH FLOW
B2: Month | C2: 1 | D2: 2 | E2: 3 | F2: 4 | G2: 5 | H2: 6 | I2: 7 | J2: 8 | K2: 9 | L2: 10 | M2: 11 | N2: 12 | O2: 13 | P2: 14 | Q2: 15 | R2: 16 | S2: 17 | T2: 18 | U2: 19 | V2: 20 | W2: 21 | X2: 22 | Y2: 23 | Z2: 24 | AA2: 25 | AB2: 26 | AC2: 27 | AD2: 28 | AE2: 29 | AF2: 30 | AG2: 31 | AH2: 32 | AI2: 33 | AJ2: 34 | AK2: 35 | AL2: 36 | AM2: 37 | AN2: 38 | AO2: 39 | AP2: 40 | AQ2: 41 | AR2: 42 | AS2: 43 | AT2: 44 | AU2: 45 | AV2: 46 | AW2: 47 | AX2: 48 | AY2: 49 | AZ2: 50 | BA2: 51 | BB2: 52 | BC2: 53 | BD2: 54 | BE2: 55 | BF2: 56 | BG2: 57 | BH2: 58 | BI2: 59 | BJ2: 60
B3: Year | C3: =INT((C2-1)/12)+1 -> 1 | D3: =INT((D2-1)/12)+1 -> 1 | E3: =INT((E2-1)/12)+1 -> 1 | F3: =INT((F2-1)/12)+1 -> 1 | G3: =INT((G2-1)/12)+1 -> 1 | H3: =INT((H2-1)/12)+1 -> 1 | I3: =INT((I2-1)/12)+1 -> 1 | J3: =INT((J2-1)/12)+1 -> 1 | ... BJ3: =INT((BJ2-1)/12)+1 -> 5
B4: Date | C4: =EDATE(Close_Date,C2-1) -> 46143 | D4: =EDATE(Close_Date,D2-1) -> 46174 | E4: =EDATE(Close_Date,E2-1) -> 46204 | F4: =EDATE(Close_Date,F2-1) -> 46235 | G4: =EDATE(Close_Date,G2-1) -> 46266 | H4: =EDATE(Close_Date,H2-1) -> 46296 | I4: =EDATE(Close_Date,I2-1) -> 46327 | J4: =EDATE(Close_Date,J2-1) -> 46357 | ... BJ4: =EDATE(Close_Date,BJ2-1) -> 47939
B6: INCOME
B7: Total Collected Rent | C7: ='Rent Roll'!V44 -> 14111.5 | D7: ='Rent Roll'!W44 -> 14111.5 | E7: ='Rent Roll'!X44 -> 14111.5 | F7: ='Rent Roll'!Y44 -> 14111.5 | G7: ='Rent Roll'!Z44 -> 14111.5 | H7: ='Rent Roll'!AA44 -> 16371.5 | I7: ='Rent Roll'!AB44 -> 19014 | J7: ='Rent Roll'!AC44 -> 19014 | ... BJ7: ='Rent Roll'!CC44 -> 20124.098
B8: Additional Income | C8: =Addl_Income -> 1376.0833 | D8: =Addl_Income -> 1376.0833 | E8: =Addl_Income -> 1376.0833 | F8: =Addl_Income -> 1376.0833 | G8: =Addl_Income -> 1376.0833 | H8: =Addl_Income -> 1376.0833 | I8: =Addl_Income -> 1376.0833 | J8: =Addl_Income -> 1376.0833 | ... BJ8: =Addl_Income -> 1376.0833
B9: Gross Income | C9: =SUM(C7:C8) -> 15487.583 | D9: =SUM(D7:D8) -> 15487.583 | E9: =SUM(E7:E8) -> 15487.583 | F9: =SUM(F7:F8) -> 15487.583 | G9: =SUM(G7:G8) -> 15487.583 | H9: =SUM(H7:H8) -> 17747.583 | I9: =SUM(I7:I8) -> 20390.083 | J9: =SUM(J7:J8) -> 20390.083 | ... BJ9: =SUM(BJ7:BJ8) -> 21500.181
B10: Credit Loss | C10: =-Credit_Loss_Pct*C9 -> -774.37917 | D10: =-Credit_Loss_Pct*D9 -> -774.37917 | E10: =-Credit_Loss_Pct*E9 -> -774.37917 | F10: =-Credit_Loss_Pct*F9 -> -774.37917 | G10: =-Credit_Loss_Pct*G9 -> -774.37917 | H10: =-Credit_Loss_Pct*H9 -> -887.37917 | I10: =-Credit_Loss_Pct*I9 -> -1019.5042 | J10: =-Credit_Loss_Pct*J9 -> -1019.5042 | ... BJ10: =-Credit_Loss_Pct*BJ9 -> -1075.009
B11: Effective Gross Income (EGI) | C11: =C9+C10 -> 14713.204 | D11: =D9+D10 -> 14713.204 | E11: =E9+E10 -> 14713.204 | F11: =F9+F10 -> 14713.204 | G11: =G9+G10 -> 14713.204 | H11: =H9+H10 -> 16860.204 | I11: =I9+I10 -> 19370.579 | J11: =J9+J10 -> 19370.579 | ... BJ11: =BJ9+BJ10 -> 20425.172
B13: Reimbursement Income | C13: ='Rent Roll'!V45 -> 10950.016 | D13: ='Rent Roll'!W45 -> 10967.422 | E13: ='Rent Roll'!X45 -> 10984.857 | F13: ='Rent Roll'!Y45 -> 11002.32 | G13: ='Rent Roll'!Z45 -> 11019.813 | H13: ='Rent Roll'!AA45 -> 13106.104 | I13: ='Rent Roll'!AB45 -> 16018.2 | J13: ='Rent Roll'!AC45 -> 16043.376 | ... BJ13: ='Rent Roll'!CC45 -> 17453.634
B15: EGI + REIMBURSEMEBNTS | C15: =C13 + C11 -> 25663.22 | D15: =D13 + D11 -> 25680.626 | E15: =E13 + E11 -> 25698.061 | F15: =F13 + F11 -> 25715.525 | G15: =G13 + G11 -> 25733.017 | H15: =H13 + H11 -> 29966.308 | I15: =I13 + I11 -> 35388.78 | J15: =J13 + J11 -> 35413.955 | ... BJ15: =BJ13 + BJ11 -> 37878.806
B17: OPERATING EXPENSES
B18: Total Operating Expenses | C18: =Monthly_OpEx -> 15093.193 | D18: =C18*(1 + Overview!$C$25)^(1/12) -> 15118.12 | E18: =D18*(1 + Overview!$C$25)^(1/12) -> 15143.089 | F18: =E18*(1 + Overview!$C$25)^(1/12) -> 15168.099 | G18: =F18*(1 + Overview!$C$25)^(1/12) -> 15193.15 | H18: =G18*(1 + Overview!$C$25)^(1/12) -> 15218.243 | I18: =H18*(1 + Overview!$C$25)^(1/12) -> 15243.377 | J18: =I18*(1 + Overview!$C$25)^(1/12) -> 15268.553 | K18: =J18*(1 + Overview!$C$25)^(1/12) -> 15293.77 | ... BJ18: =BI18*(1 + Overview!$C$25)^(1/12) -> 16636.627
B19: Property Management Fee | C19: =Mgmt_Fee_Pct*C11 -> 588.52817 | D19: =Mgmt_Fee_Pct*D11 -> 588.52817 | E19: =Mgmt_Fee_Pct*E11 -> 588.52817 | F19: =Mgmt_Fee_Pct*F11 -> 588.52817 | G19: =Mgmt_Fee_Pct*G11 -> 588.52817 | H19: =Mgmt_Fee_Pct*H11 -> 674.40817 | I19: =Mgmt_Fee_Pct*I11 -> 774.82317 | J19: =Mgmt_Fee_Pct*J11 -> 774.82317 | ... BJ19: =Mgmt_Fee_Pct*BJ11 -> 817.00687
B20: Total Expenses | C20: =C18+C19 -> 15681.721 | D20: =D18+D19 -> 15706.648 | E20: =E18+E19 -> 15731.617 | F20: =F18+F19 -> 15756.627 | G20: =G18+G19 -> 15781.678 | H20: =H18+H19 -> 15892.651 | I20: =I18+I19 -> 16018.2 | J20: =J18+J19 -> 16043.376 | ... BJ20: =BJ18+BJ19 -> 17453.634
B22: NET OPERATING INCOME (NOI) | C22: =C15-C20 -> 9981.4993 | D22: =D15-D20 -> 9973.9778 | E22: =E15-E20 -> 9966.4439 | F22: =F15-F20 -> 9958.8975 | G22: =G15-G20 -> 9951.3386 | H22: =H15-H20 -> 14073.657 | I22: =I15-I20 -> 19370.579 | J22: =J15-J20 -> 19370.579 | ... BJ22: =BJ15-BJ20 -> 20425.172
B24: BELOW-THE-LINE
B25: CapEx | C25: =-'CapEx & TI-LC'!H13 -> -25000 | D25: =-'CapEx & TI-LC'!I13 -> -25000 | E25: =-'CapEx & TI-LC'!J13 -> -25000 | F25: =-'CapEx & TI-LC'!K13 -> -25000 | G25: =-'CapEx & TI-LC'!L13 -> -25000 | H25: =-'CapEx & TI-LC'!M13 -> -25000 | I25: =-'CapEx & TI-LC'!N13 -> 0 | J25: =-'CapEx & TI-LC'!O13 -> 0 | ... BJ25: =-'CapEx & TI-LC'!BO13 -> 0
B26: Tenant Improvements | C26: =-'CapEx & TI-LC'!H30 -> 0 | D26: =-'CapEx & TI-LC'!I30 -> 0 | E26: =-'CapEx & TI-LC'!J30 -> 0 | F26: =-'CapEx & TI-LC'!K30 -> 0 | G26: =-'CapEx & TI-LC'!L30 -> 0 | H26: =-'CapEx & TI-LC'!M30 -> -56500 | I26: =-'CapEx & TI-LC'!N30 -> -98100 | J26: =-'CapEx & TI-LC'!O30 -> 0 | ... BJ26: =-'CapEx & TI-LC'!BO30 -> -36200
B27: Leasing Commissions | C27: =-'CapEx & TI-LC'!H46 -> 0 | D27: =-'CapEx & TI-LC'!I46 -> 0 | E27: =-'CapEx & TI-LC'!J46 -> 0 | F27: =-'CapEx & TI-LC'!K46 -> 0 | G27: =-'CapEx & TI-LC'!L46 -> 0 | H27: =-'CapEx & TI-LC'!M46 -> -8136 | I27: =-'CapEx & TI-LC'!N46 -> -18387 | J27: =-'CapEx & TI-LC'!O46 -> 0 | ... BJ27: =-'CapEx & TI-LC'!BO46 -> -9167.2693
B28: Total Capex, LI, LC | C28: =SUM(C25:C27) -> -25000 | D28: =SUM(D25:D27) -> -25000 | E28: =SUM(E25:E27) -> -25000 | F28: =SUM(F25:F27) -> -25000 | G28: =SUM(G25:G27) -> -25000 | H28: =SUM(H25:H27) -> -89636 | I28: =SUM(I25:I27) -> -116487 | J28: =SUM(J25:J27) -> 0 | ... BJ28: =SUM(BJ25:BJ27) -> -45367.269
B29: Cash Flow Before Debt Service | C29: =C22+C25+C26+C27 -> -15018.501 | D29: =D22+D25+D26+D27 -> -15026.022 | E29: =E22+E25+E26+E27 -> -15033.556 | F29: =F22+F25+F26+F27 -> -15041.103 | G29: =G22+G25+G26+G27 -> -15048.661 | H29: =H22+H25+H26+H27 -> -75562.343 | I29: =I22+I25+I26+I27 -> -97116.421 | J29: =J22+J25+J26+J27 -> 19370.579 | ... BJ29: =BJ22+BJ25+BJ26+BJ27 -> -24942.097
B31: DEBT SERVICE & OTHER
B32: Total Debt Service | C32: =-Debt!C23 -> -11666.667 | D32: =-Debt!D23 -> -11666.667 | E32: =-Debt!E23 -> -11666.667 | F32: =-Debt!F23 -> -11666.667 | G32: =-Debt!G23 -> -11666.667 | H32: =-Debt!H23 -> -11666.667 | I32: =-Debt!I23 -> -11666.667 | J32: =-Debt!J23 -> -11666.667 | ... BJ32: =-Debt!BJ23 -> -14701.247
B33: Replacement Reserve | C33: =-Repl_Reserve_PSF*NRA/12 -> -745 | D33: =-Repl_Reserve_PSF*NRA/12 -> -745 | E33: =-Repl_Reserve_PSF*NRA/12 -> -745 | F33: =-Repl_Reserve_PSF*NRA/12 -> -745 | G33: =-Repl_Reserve_PSF*NRA/12 -> -745 | H33: =-Repl_Reserve_PSF*NRA/12 -> -745 | I33: =-Repl_Reserve_PSF*NRA/12 -> -745 | J33: =-Repl_Reserve_PSF*NRA/12 -> -745 | ... BJ33: =-Repl_Reserve_PSF*NRA/12 -> -745
B34: Acquisition Fee | C34: 0 | D34: 0 | E34: 0 | F34: 0 | G34: 0 | H34: 0 | I34: 0 | J34: 0 | K34: 0 | L34: 0 | M34: 0 | N34: 0 | O34: 0 | P34: 0 | Q34: 0 | R34: 0 | S34: 0 | T34: 0 | U34: 0 | V34: 0 | W34: 0 | X34: 0 | Y34: 0 | Z34: 0 | AA34: 0 | AB34: 0 | AC34: 0 | AD34: 0 | AE34: 0 | AF34: 0 | AG34: 0 | AH34: 0 | AI34: 0 | AJ34: 0 | AK34: 0 | AL34: 0 | AM34: 0 | AN34: 0 | AO34: 0 | AP34: 0 | AQ34: 0 | AR34: 0 | AS34: 0 | AT34: 0 | AU34: 0 | AV34: 0 | AW34: 0 | AX34: 0 | AY34: 0 | AZ34: 0 | BA34: 0 | BB34: 0 | BC34: 0 | BD34: 0 | BE34: 0 | BF34: 0 | BG34: 0 | BH34: 0 | BI34: 0 | BJ34: 0
B35: Asset Management Fee | C35: =-AM_Fee_Pct*Overview!$L$10 / 12 -> -823.33333 | D35: =-AM_Fee_Pct*Overview!$L$10 / 12 -> -823.33333 | E35: =-AM_Fee_Pct*Overview!$L$10 / 12 -> -823.33333 | F35: =-AM_Fee_Pct*Overview!$L$10 / 12 -> -823.33333 | G35: =-AM_Fee_Pct*Overview!$L$10 / 12 -> -823.33333 | H35: =-AM_Fee_Pct*Overview!$L$10 / 12 -> -823.33333 | I35: =-AM_Fee_Pct*Overview!$L$10 / 12 -> -823.33333 | J35: =-AM_Fee_Pct*Overview!$L$10 / 12 -> -823.33333 | ... BJ35: =-AM_Fee_Pct*Overview!$L$10 / 12 -> -823.33333
B36: Legal/Acct/Banking | C36: =-Legal_Monthly -> -500 | D36: =-Legal_Monthly -> -500 | E36: =-Legal_Monthly -> -500 | F36: =-Legal_Monthly -> -500 | G36: =-Legal_Monthly -> -500 | H36: =-Legal_Monthly -> -500 | I36: =-Legal_Monthly -> -500 | J36: =-Legal_Monthly -> -500 | ... BJ36: =-Legal_Monthly -> -500
B38: CASH AVAILABLE FOR DISTRIBUTION | C38: =C29+C32+C33+C34+C35+C36 -> -28753.501 | D38: =D29+D32+D33+D34+D35+D36 -> -28761.022 | E38: =E29+E32+E33+E34+E35+E36 -> -28768.556 | F38: =F29+F32+F33+F34+F35+F36 -> -28776.103 | G38: =G29+G32+G33+G34+G35+G36 -> -28783.661 | H38: =H29+H32+H33+H34+H35+H36 -> -89297.343 | I38: =I29+I32+I33+I34+I35+I36 -> -110851.42 | J38: =J29+J32+J33+J34+J35+J36 -> 5635.5792 | ... BJ38: =BJ29+BJ32+BJ33+BJ34+BJ35+BJ36 -> -41711.678
B40: Net Refi Proceeds | C40: =Debt!C24 -> 0 | D40: =Debt!D24 -> 0 | E40: =Debt!E24 -> 0 | F40: =Debt!F24 -> 0 | G40: =Debt!G24 -> 0 | H40: =Debt!H24 -> 0 | I40: =Debt!I24 -> 0 | J40: =Debt!J24 -> 0 | ... BJ40: =Debt!BJ24 -> 0
B42: SALE / DISPOSITION
B43: T12 NOI (at exit) | C43: =IF(C2=Exit_Month,C22*12,0) -> 0 | D43: =IF(D2=Exit_Month,D22*12,0) -> 0 | E43: =IF(E2=Exit_Month,E22*12,0) -> 0 | F43: =IF(F2=Exit_Month,F22*12,0) -> 0 | G43: =IF(G2=Exit_Month,G22*12,0) -> 0 | H43: =IF(H2=Exit_Month,H22*12,0) -> 0 | I43: =IF(I2=Exit_Month,I22*12,0) -> 0 | J43: =IF(J2=Exit_Month,J22*12,0) -> 0 | ... BJ43: =IF(BJ2=Exit_Month,BJ22*12,0) -> 245102.06
B44: Gross Sale Price | C44: =IF(C2=Exit_Month,C43/Exit_Cap,0) -> 0 | D44: =IF(D2=Exit_Month,D43/Exit_Cap,0) -> 0 | E44: =IF(E2=Exit_Month,E43/Exit_Cap,0) -> 0 | F44: =IF(F2=Exit_Month,F43/Exit_Cap,0) -> 0 | G44: =IF(G2=Exit_Month,G43/Exit_Cap,0) -> 0 | H44: =IF(H2=Exit_Month,H43/Exit_Cap,0) -> 0 | I44: =IF(I2=Exit_Month,I43/Exit_Cap,0) -> 0 | J44: =IF(J2=Exit_Month,J43/Exit_Cap,0) -> 0 | ... BJ44: =IF(BJ2=Exit_Month,BJ43/Exit_Cap,0) -> 3063775.8
B45: Less: Selling Costs | C45: =IF(C2=Exit_Month,-Selling_Cost_Pct*C44,0) -> 0 | D45: =IF(D2=Exit_Month,-Selling_Cost_Pct*D44,0) -> 0 | E45: =IF(E2=Exit_Month,-Selling_Cost_Pct*E44,0) -> 0 | F45: =IF(F2=Exit_Month,-Selling_Cost_Pct*F44,0) -> 0 | G45: =IF(G2=Exit_Month,-Selling_Cost_Pct*G44,0) -> 0 | H45: =IF(H2=Exit_Month,-Selling_Cost_Pct*H44,0) -> 0 | I45: =IF(I2=Exit_Month,-Selling_Cost_Pct*I44,0) -> 0 | J45: =IF(J2=Exit_Month,-Selling_Cost_Pct*J44,0) -> 0 | ... BJ45: =IF(BJ2=Exit_Month,-Selling_Cost_Pct*BJ44,0) -> -61275.515
B46: Less: Loan Payoff | C46: =-Debt!C25 -> 0 | D46: =-Debt!D25 -> 0 | E46: =-Debt!E25 -> 0 | F46: =-Debt!F25 -> 0 | G46: =-Debt!G25 -> 0 | H46: =-Debt!H25 -> 0 | I46: =-Debt!I25 -> 0 | J46: =-Debt!J25 -> 0 | ... BJ46: =-Debt!BJ25 -> -1896785.5
B47: Net Sale Proceeds to Equity | C47: =C44+C45+C46 -> 0 | D47: =D44+D45+D46 -> 0 | E47: =E44+E45+E46 -> 0 | F47: =F44+F45+F46 -> 0 | G47: =G44+G45+G46 -> 0 | H47: =H44+H45+H46 -> 0 | I47: =I44+I45+I46 -> 0 | J47: =J44+J45+J46 -> 0 | ... BJ47: =BJ44+BJ45+BJ46 -> 1105714.8
B49: RETURN CALCULATIONS
B50: Equity Investment | C50: =IF(C2=1,-(Overview!I20-Overview!I6),0) -> -988000 | D50: =IF(D2=1,-(Overview!J20-Overview!J6),0) -> 0 | E50: =IF(E2=1,-(Overview!K20-Overview!K6),0) -> 0 | F50: =IF(F2=1,-(Overview!L20-Overview!L6),0) -> 0 | G50: =IF(G2=1,-(Overview!M20-Overview!M6),0) -> 0 | H50: =IF(H2=1,-(Overview!N20-Overview!N6),0) -> 0 | I50: =IF(I2=1,-(Overview!O20-Overview!O6),0) -> 0 | J50: =IF(J2=1,-(Overview!P20-Overview!P6),0) -> 0 | ... BJ50: =IF(BJ2=1,-(Overview!BP20-Overview!BP6),0) -> 0
B51: Levered Net CF (for IRR) | C51: =C50+C38+C40+C47 -> -1016753.5 | D51: =D50+D38+D40+D47 -> -28761.022 | E51: =E50+E38+E40+E47 -> -28768.556 | F51: =F50+F38+F40+F47 -> -28776.103 | G51: =G50+G38+G40+G47 -> -28783.661 | H51: =H50+H38+H40+H47 -> -89297.343 | I51: =I50+I38+I40+I47 -> -110851.42 | J51: =J50+J38+J40+J47 -> 5635.5792 | ... BJ51: =BJ50+BJ38+BJ40+BJ47 -> 1064003.1
B52: Unlevered Net CF (for IRR) | C52: =-Overview!I20+C22+C25+C26+C27 + Overview!I15 -> -2375018.5 | D52: =D22+D25+D26+D27+D44+D45 -> -15026.022 | E52: =E22+E25+E26+E27+E44+E45 -> -15033.556 | F52: =F22+F25+F26+F27+F44+F45 -> -15041.103 | G52: =G22+G25+G26+G27+G44+G45 -> -15048.661 | H52: =H22+H25+H26+H27+H44+H45 -> -75562.343 | I52: =I22+I25+I26+I27+I44+I45 -> -97116.421 | J52: =J22+J25+J26+J27+J44+J45 -> 19370.579 | K52: =K22+K25+K26+K27+K44+K45 -> 19370.579 | ... BJ52: =BJ22+BJ25+BJ26+BJ27+BJ44+BJ45 -> 2977558.2
B54: RETURN METRICS
B55: Levered IRR | C55: =IFERROR(XIRR(C51:BJ51, $C$4:$BJ$4, 0.1),"N/A") -> 0.09347612
B56: Unlevered IRR | C56: =IFERROR(XIRR(C52:BJ52, $C$4:$BJ$4, 0.1),"N/A") -> 0.10299947
B57: Equity Multiple | C57: =IFERROR(1+SUM(C51:BJ51)/(-C50),"N/A") -> 1.4402914
B58: Cash-on-Cash (Year 2) | C58: {=IFERROR(SUMPRODUCT(($C$3:$BJ$3=2)*$C$38:$BJ$38)/(-C50),"N/A")} -> 0.037251037
B59: Total Cash Flow | C59: =SUM(C51:BJ51) -> 435007.9

Sheet Overview
A1: RETAIL ACQUISITION MODEL v1 - Keegan Tingey
B2: last updated: 4/5/26
B3: PROPERTY INFO | D3: NOTES | E3: CAPITAL & LEASING ASSUMPTIONS | H3: SOURCES & USES | K3: RETURN METRICS
B4: Property Name | C4: Marconi & Walnut | E4: TI $/SF (New Leases) | F4: 25 | K4: Levered IRR | L4: =IFERROR('Monthly CF'!C55,"--") -> 0.09347612
B5: Property Address | C5: 4949 Marconi Ave, Carmichael CA | E5: TI $/SF (Renewals) | F5: 5 | H5: SOURCES | I5: Amount ($) | K5: Unlevered IRR | L5: =IFERROR('Monthly CF'!C56,"--") -> 0.10299947
B6: Close Date (Model Start) | C6: 46143 | E6: LC % of Total Rent (New) | F6: 0.06 | H6: Loan 1 Proceeds | I6: =F13 -> 1400000 | K6: Equity Multiple | L6: =IFERROR('Monthly CF'!C57,"--") -> 1.4402914
B7: Total NRA (SF) | C7: 17880 | E7: LC % of Total Rent (Renewal) | F7: 0.03 | H7: LP Equity | I7: =I20-I6-I8-I9 -> 988000 | K7: Cash-on-Cash (Yr 2) | L7: =IFERROR('Monthly CF'!C58,"--") -> 0.037251037
B8: Lot Size (acres) | C8: 1.57 | E8: Downtime Between Tenants (mo) | F8: 6 | H8: GP Equity (Co-Invest) | I8: 0 | K8: Going-In Cap Rate | L8: =C17 -> 0.059888996
B9: Year Built | C9: 1984 | E9: Default Renewal Probability | F9: 0.75 | H9: Other Sources | I9: 0 | K9: Exit Cap Rate | L9: =C18 -> 0.08
B10: Parking Spaces | C10: 65 | H10: Total Sources | I10: =SUM(I6:I9) -> 2388000 | K10: Total Equity | L10: =I20-I6 -> 988000
B11: Number of Buildings | C11: 2 | E11: DEBT — LOAN 1 (ACQUISITION) | K11: Total Cash Flow | L11: =IFERROR('Monthly CF'!C59,"--") -> 435007.9
E12: LTV (%) | F12: 0.7 | H12: USES | I12: Amount ($)
B13: KEY ASSUMPTIONS | E13: Loan Amount | F13: =F12*C14 -> 1400000 | H13: Purchase Price | I13: =C14 -> 2000000
B14: Acquisition Price | C14: 2000000 | E14: Int Rate | F14: 0.1 | H14: Closing Costs | I14: =C14*C15 -> 20000
B15: Closing Costs (% of Price) | C15: 0.01 | E15: IO Period | F15: 12 | G15: mos | H15: Loan Origination Fees | I15: =F13*F18 -> 28000
B16: Total Basis | C16: =C14+C14*C15+I18+I19+F13*F18 -> 2298000 | E16: Amo Period | F16: 25 | G16: mos | H16: Acquisition Fee | I16: =C14*F32 -> 40000
B17: Going-In Cap Rate | C17: =IFERROR('Monthly CF'!C22*12/C14,"--") -> 0.059888996 | E17: Loan Term | F17: 60 | G17: mos | H17: Working Capital Reserve | I17: 50000 | J17: need logic on these 3
B18: Exit Cap Rate | C18: 0.08 | D18: also drives refi amnt | E18: Origination Fee (%) | F18: 0.02 | H18: Upfront CapEx Reserve | I18: =SUM('CapEx & TI-LC'!H13:S13) -> 150000
B19: Exit Month | C19: 60 | H19: Upfront TI/LC Reserve | I19: 100000
B20: Selling Costs at Exit (%) | C20: 0.02 | E20: DEBT — LOAN 2 (REFINANCE) | H20: Total Uses | I20: =SUM(I13:I19) -> 2388000
B21: Credit Loss (% of EGI) | C21: 0.05 | E21: Refinance Toggle | F21: ON | H21: Sources - Uses | I21: =I10-I20 -> 0
B22: Replacement Reserve ($/SF/yr) | C22: 0.5 | E22: Refi Month | F22: =IO1_Months -> 12 | H22: Balance Check | I22: =IF(ROUND(I21,0)=0,"✓ BALANCED","✗ ERROR") -> ✓ BALANCED
B23: Annual Rent Growth Rate | C23: 0.03 | E23: Refi LTV (% of Stabilized Value) | F23: 0.7
B24: Property Tax Millage Rate | C24: 0.011742 | E24: Refi Loan Amount | F24: =IFERROR(F23*INDEX('Monthly CF'!C22:BJ22,MATCH(Refi_Month,'Monthly CF'!C2:BJ2,0))* 12/C18,"--") -> 2033910.8
B25: OpEx Annual Growth | C25: 0.02 | D25: driving monthly opex rn | E25: Int Rate | F25: 0.0725
B26: Assessed Value for Taxes | C26: 2000000 | E26: IO Period | F26: 0 | G26: mos
B27: Property Management Fee (% of EGI) | C27: 0.04 | E27: Amo Period | F27: 25 | G27: mos
B28: Additional Income ($/month) | C28: =16513 / 12 -> 1376.0833 | D28: check om: reimb and fireworks | E28: Loan Term | F28: 60 | G28: mos
E29: Origination Fee (%) | F29: 0.02
E31: ENTITY-LEVEL EXPENSES
E32: Acquisition Fee (% of Price) | F32: 0.02
E33: Asset Mgmt Fee (% of Equity) | F33: 0.01
E34: Legal/Acct/Banking ($/month) | F34: 500

Sheet CapEx & TI-LC
A1: CAPITAL EXPENDITURES & TI / LEASING COMMISSIONS
A3: CAPITAL EXPENDITURES
A4: # | B4: Description | C4: Category | D4: Vendor/Notes | E4: Total Cost ($) | F4: Start Month | G4: Spread (mo) | H4: 1 | I4: 2 | J4: 3 | K4: 4 | L4: 5 | M4: 6 | N4: 7 | O4: 8 | P4: 9 | Q4: 10 | R4: 11 | S4: 12 | T4: 13 | U4: 14 | V4: 15 | W4: 16 | X4: 17 | Y4: 18 | Z4: 19 | AA4: 20 | AB4: 21 | AC4: 22 | AD4: 23 | AE4: 24 | AF4: 25 | AG4: 26 | AH4: 27 | AI4: 28 | AJ4: 29 | AK4: 30 | AL4: 31 | AM4: 32 | AN4: 33 | AO4: 34 | AP4: 35 | AQ4: 36 | AR4: 37 | AS4: 38 | AT4: 39 | AU4: 40 | AV4: 41 | AW4: 42 | AX4: 43 | AY4: 44 | AZ4: 45 | BA4: 46 | BB4: 47 | BC4: 48 | BD4: 49 | BE4: 50 | BF4: 51 | BG4: 52 | BH4: 53 | BI4: 54 | BJ4: 55 | BK4: 56 | BL4: 57 | BM4: 58 | BN4: 59 | BO4: 60
A5: 1 | B5: Misc Repairs | C5: Misc | E5: 150000 | F5: 1 | G5: 6 | H5: =IF(AND(1>=$F$5,1<$F$5+$G$5),$E$5/$G$5,0) -> 25000 | I5: =IF(AND(2>=$F$5,2<$F$5+$G$5),$E$5/$G$5,0) -> 25000 | J5: =IF(AND(3>=$F$5,3<$F$5+$G$5),$E$5/$G$5,0) -> 25000 | K5: =IF(AND(4>=$F$5,4<$F$5+$G$5),$E$5/$G$5,0) -> 25000 | L5: =IF(AND(5>=$F$5,5<$F$5+$G$5),$E$5/$G$5,0) -> 25000 | M5: =IF(AND(6>=$F$5,6<$F$5+$G$5),$E$5/$G$5,0) -> 25000 | N5: =IF(AND(7>=$F$5,7<$F$5+$G$5),$E$5/$G$5,0) -> 0 | O5: =IF(AND(8>=$F$5,8<$F$5+$G$5),$E$5/$G$5,0) -> 0 | P5: =IF(AND(9>=$F$5,9<$F$5+$G$5),$E$5/$G$5,0) -> 0 | Q5: =IF(AND(10>=$F$5,10<$F$5+$G$5),$E$5/$G$5,0) -> 0 | R5: =IF(AND(11>=$F$5,11<$F$5+$G$5),$E$5/$G$5,0) -> 0 | S5: =IF(AND(12>=$F$5,12<$F$5+$G$5),$E$5/$G$5,0) -> 0 | T5: =IF(AND(13>=$F$5,13<$F$5+$G$5),$E$5/$G$5,0) -> 0 | U5: =IF(AND(14>=$F$5,14<$F$5+$G$5),$E$5/$G$5,0) -> 0 | V5: =IF(AND(15>=$F$5,15<$F$5+$G$5),$E$5/$G$5,0) -> 0 | W5: =IF(AND(16>=$F$5,16<$F$5+$G$5),$E$5/$G$5,0) -> 0 | X5: =IF(AND(17>=$F$5,17<$F$5+$G$5),$E$5/$G$5,0) -> 0 | Y5: =IF(AND(18>=$F$5,18<$F$5+$G$5),$E$5/$G$5,0) -> 0 | Z5: =IF(AND(19>=$F$5,19<$F$5+$G$5),$E$5/$G$5,0) -> 0 | AA5: =IF(AND(20>=$F$5,20<$F$5+$G$5),$E$5/$G$5,0) -> 0 | AB5: =IF(AND(21>=$F$5,21<$F$5+$G$5),$E$5/$G$5,0) -> 0 | AC5: =IF(AND(22>=$F$5,22<$F$5+$G$5),$E$5/$G$5,0) -> 0 | AD5: =IF(AND(23>=$F$5,23<$F$5+$G$5),$E$5/$G$5,0) -> 0 | AE5: =IF(AND(24>=$F$5,24<$F$5+$G$5),$E$5/$G$5,0) -> 0 | AF5: =IF(AND(25>=$F$5,25<$F$5+$G$5),$E$5/$G$5,0) -> 0 | AG5: =IF(AND(26>=$F$5,26<$F$5+$G$5),$E$5/$G$5,0) -> 0 | AH5: =IF(AND(27>=$F$5,27<$F$5+$G$5),$E$5/$G$5,0) -> 0 | AI5: =IF(AND(28>=$F$5,28<$F$5+$G$5),$E$5/$G$5,0) -> 0 | AJ5: =IF(AND(29>=$F$5,29<$F$5+$G$5),$E$5/$G$5,0) -> 0 | AK5: =IF(AND(30>=$F$5,30<$F$5+$G$5),$E$5/$G$5,0) -> 0 | AL5: =IF(AND(31>=$F$5,31<$F$5+$G$5),$E$5/$G$5,0) -> 0 | AM5: =IF(AND(32>=$F$5,32<$F$5+$G$5),$E$5/$G$5,0) -> 0 | AN5: =IF(AND(33>=$F$5,33<$F$5+$G$5),$E$5/$G$5,0) -> 0 | AO5: =IF(AND(34>=$F$5,34<$F$5+$G$5),$E$5/$G$5,0) -> 0 | AP5: =IF(AND(35>=$F$5,35<$F$5+$G$5),$E$5/$G$5,0) -> 0 | AQ5: =IF(AND(36>=$F$5,36<$F$5+$G$5),$E$5/$G$5,0) -> 0 | AR5: =IF(AND(37>=$F$5,37<$F$5+$G$5),$E$5/$G$5,0) -> 0 | AS5: =IF(AND(38>=$F$5,38<$F$5+$G$5),$E$5/$G$5,0) -> 0 | AT5: =IF(AND(39>=$F$5,39<$F$5+$G$5),$E$5/$G$5,0) -> 0 | AU5: =IF(AND(40>=$F$5,40<$F$5+$G$5),$E$5/$G$5,0) -> 0 | AV5: =IF(AND(41>=$F$5,41<$F$5+$G$5),$E$5/$G$5,0) -> 0 | AW5: =IF(AND(42>=$F$5,42<$F$5+$G$5),$E$5/$G$5,0) -> 0 | AX5: =IF(AND(43>=$F$5,43<$F$5+$G$5),$E$5/$G$5,0) -> 0 | AY5: =IF(AND(44>=$F$5,44<$F$5+$G$5),$E$5/$G$5,0) -> 0 | AZ5: =IF(AND(45>=$F$5,45<$F$5+$G$5),$E$5/$G$5,0) -> 0 | BA5: =IF(AND(46>=$F$5,46<$F$5+$G$5),$E$5/$G$5,0) -> 0 | BB5: =IF(AND(47>=$F$5,47<$F$5+$G$5),$E$5/$G$5,0) -> 0 | BC5: =IF(AND(48>=$F$5,48<$F$5+$G$5),$E$5/$G$5,0) -> 0 | BD5: =IF(AND(49>=$F$5,49<$F$5+$G$5),$E$5/$G$5,0) -> 0 | BE5: =IF(AND(50>=$F$5,50<$F$5+$G$5),$E$5/$G$5,0) -> 0 | BF5: =IF(AND(51>=$F$5,51<$F$5+$G$5),$E$5/$G$5,0) -> 0 | BG5: =IF(AND(52>=$F$5,52<$F$5+$G$5),$E$5/$G$5,0) -> 0 | BH5: =IF(AND(53>=$F$5,53<$F$5+$G$5),$E$5/$G$5,0) -> 0 | BI5: =IF(AND(54>=$F$5,54<$F$5+$G$5),$E$5/$G$5,0) -> 0 | BJ5: =IF(AND(55>=$F$5,55<$F$5+$G$5),$E$5/$G$5,0) -> 0 | BK5: =IF(AND(56>=$F$5,56<$F$5+$G$5),$E$5/$G$5,0) -> 0 | BL5: =IF(AND(57>=$F$5,57<$F$5+$G$5),$E$5/$G$5,0) -> 0 | BM5: =IF(AND(58>=$F$5,58<$F$5+$G$5),$E$5/$G$5,0) -> 0 | BN5: =IF(AND(59>=$F$5,59<$F$5+$G$5),$E$5/$G$5,0) -> 0 | BO5: =IF(AND(60>=$F$5,60<$F$5+$G$5),$E$5/$G$5,0) -> 0
A6: 2 | B6: Asphalt Resurfacing | C6: Site | E6: 0 | F6: 4 | G6: 2 | H6: =IF(AND(1>=$F$6,1<$F$6+$G$6),$E$6/$G$6,0) -> 0 | I6: =IF(AND(2>=$F$6,2<$F$6+$G$6),$E$6/$G$6,0) -> 0 | J6: =IF(AND(3>=$F$6,3<$F$6+$G$6),$E$6/$G$6,0) -> 0 | K6: =IF(AND(4>=$F$6,4<$F$6+$G$6),$E$6/$G$6,0) -> 0 | L6: =IF(AND(5>=$F$6,5<$F$6+$G$6),$E$6/$G$6,0) -> 0 | M6: =IF(AND(6>=$F$6,6<$F$6+$G$6),$E$6/$G$6,0) -> 0 | N6: =IF(AND(7>=$F$6,7<$F$6+$G$6),$E$6/$G$6,0) -> 0 | O6: =IF(AND(8>=$F$6,8<$F$6+$G$6),$E$6/$G$6,0) -> 0 | P6: =IF(AND(9>=$F$6,9<$F$6+$G$6),$E$6/$G$6,0) -> 0 | Q6: =IF(AND(10>=$F$6,10<$F$6+$G$6),$E$6/$G$6,0) -> 0 | R6: =IF(AND(11>=$F$6,11<$F$6+$G$6),$E$6/$G$6,0) -> 0 | S6: =IF(AND(12>=$F$6,12<$F$6+$G$6),$E$6/$G$6,0) -> 0 | T6: =IF(AND(13>=$F$6,13<$F$6+$G$6),$E$6/$G$6,0) -> 0 | U6: =IF(AND(14>=$F$6,14<$F$6+$G$6),$E$6/$G$6,0) -> 0 | V6: =IF(AND(15>=$F$6,15<$F$6+$G$6),$E$6/$G$6,0) -> 0 | W6: =IF(AND(16>=$F$6,16<$F$6+$G$6),$E$6/$G$6,0) -> 0 | X6: =IF(AND(17>=$F$6,17<$F$6+$G$6),$E$6/$G$6,0) -> 0 | Y6: =IF(AND(18>=$F$6,18<$F$6+$G$6),$E$6/$G$6,0) -> 0 | Z6: =IF(AND(19>=$F$6,19<$F$6+$G$6),$E$6/$G$6,0) -> 0 | AA6: =IF(AND(20>=$F$6,20<$F$6+$G$6),$E$6/$G$6,0) -> 0 | AB6: =IF(AND(21>=$F$6,21<$F$6+$G$6),$E$6/$G$6,0) -> 0 | AC6: =IF(AND(22>=$F$6,22<$F$6+$G$6),$E$6/$G$6,0) -> 0 | AD6: =IF(AND(23>=$F$6,23<$F$6+$G$6),$E$6/$G$6,0) -> 0 | AE6: =IF(AND(24>=$F$6,24<$F$6+$G$6),$E$6/$G$6,0) -> 0 | AF6: =IF(AND(25>=$F$6,25<$F$6+$G$6),$E$6/$G$6,0) -> 0 | AG6: =IF(AND(26>=$F$6,26<$F$6+$G$6),$E$6/$G$6,0) -> 0 | AH6: =IF(AND(27>=$F$6,27<$F$6+$G$6),$E$6/$G$6,0) -> 0 | AI6: =IF(AND(28>=$F$6,28<$F$6+$G$6),$E$6/$G$6,0) -> 0 | AJ6: =IF(AND(29>=$F$6,29<$F$6+$G$6),$E$6/$G$6,0) -> 0 | AK6: =IF(AND(30>=$F$6,30<$F$6+$G$6),$E$6/$G$6,0) -> 0 | AL6: =IF(AND(31>=$F$6,31<$F$6+$G$6),$E$6/$G$6,0) -> 0 | AM6: =IF(AND(32>=$F$6,32<$F$6+$G$6),$E$6/$G$6,0) -> 0 | AN6: =IF(AND(33>=$F$6,33<$F$6+$G$6),$E$6/$G$6,0) -> 0 | AO6: =IF(AND(34>=$F$6,34<$F$6+$G$6),$E$6/$G$6,0) -> 0 | AP6: =IF(AND(35>=$F$6,35<$F$6+$G$6),$E$6/$G$6,0) -> 0 | AQ6: =IF(AND(36>=$F$6,36<$F$6+$G$6),$E$6/$G$6,0) -> 0 | AR6: =IF(AND(37>=$F$6,37<$F$6+$G$6),$E$6/$G$6,0) -> 0 | AS6: =IF(AND(38>=$F$6,38<$F$6+$G$6),$E$6/$G$6,0) -> 0 | AT6: =IF(AND(39>=$F$6,39<$F$6+$G$6),$E$6/$G$6,0) -> 0 | AU6: =IF(AND(40>=$F$6,40<$F$6+$G$6),$E$6/$G$6,0) -> 0 | AV6: =IF(AND(41>=$F$6,41<$F$6+$G$6),$E$6/$G$6,0) -> 0 | AW6: =IF(AND(42>=$F$6,42<$F$6+$G$6),$E$6/$G$6,0) -> 0 | AX6: =IF(AND(43>=$F$6,43<$F$6+$G$6),$E$6/$G$6,0) -> 0 | AY6: =IF(AND(44>=$F$6,44<$F$6+$G$6),$E$6/$G$6,0) -> 0 | AZ6: =IF(AND(45>=$F$6,45<$F$6+$G$6),$E$6/$G$6,0) -> 0 | BA6: =IF(AND(46>=$F$6,46<$F$6+$G$6),$E$6/$G$6,0) -> 0 | BB6: =IF(AND(47>=$F$6,47<$F$6+$G$6),$E$6/$G$6,0) -> 0 | BC6: =IF(AND(48>=$F$6,48<$F$6+$G$6),$E$6/$G$6,0) -> 0 | BD6: =IF(AND(49>=$F$6,49<$F$6+$G$6),$E$6/$G$6,0) -> 0 | BE6: =IF(AND(50>=$F$6,50<$F$6+$G$6),$E$6/$G$6,0) -> 0 | BF6: =IF(AND(51>=$F$6,51<$F$6+$G$6),$E$6/$G$6,0) -> 0 | BG6: =IF(AND(52>=$F$6,52<$F$6+$G$6),$E$6/$G$6,0) -> 0 | BH6: =IF(AND(53>=$F$6,53<$F$6+$G$6),$E$6/$G$6,0) -> 0 | BI6: =IF(AND(54>=$F$6,54<$F$6+$G$6),$E$6/$G$6,0) -> 0 | BJ6: =IF(AND(55>=$F$6,55<$F$6+$G$6),$E$6/$G$6,0) -> 0 | BK6: =IF(AND(56>=$F$6,56<$F$6+$G$6),$E$6/$G$6,0) -> 0 | BL6: =IF(AND(57>=$F$6,57<$F$6+$G$6),$E$6/$G$6,0) -> 0 | BM6: =IF(AND(58>=$F$6,58<$F$6+$G$6),$E$6/$G$6,0) -> 0 | BN6: =IF(AND(59>=$F$6,59<$F$6+$G$6),$E$6/$G$6,0) -> 0 | BO6: =IF(AND(60>=$F$6,60<$F$6+$G$6),$E$6/$G$6,0) -> 0
A7: 3 | B7: Dry Rot Repairs | C7: Structural | E7: 0 | F7: 3 | G7: 1 | H7: =IF(AND(1>=$F$7,1<$F$7+$G$7),$E$7/$G$7,0) -> 0 | I7: =IF(AND(2>=$F$7,2<$F$7+$G$7),$E$7/$G$7,0) -> 0 | J7: =IF(AND(3>=$F$7,3<$F$7+$G$7),$E$7/$G$7,0) -> 0 | K7: =IF(AND(4>=$F$7,4<$F$7+$G$7),$E$7/$G$7,0) -> 0 | L7: =IF(AND(5>=$F$7,5<$F$7+$G$7),$E$7/$G$7,0) -> 0 | M7: =IF(AND(6>=$F$7,6<$F$7+$G$7),$E$7/$G$7,0) -> 0 | N7: =IF(AND(7>=$F$7,7<$F$7+$G$7),$E$7/$G$7,0) -> 0 | O7: =IF(AND(8>=$F$7,8<$F$7+$G$7),$E$7/$G$7,0) -> 0 | P7: =IF(AND(9>=$F$7,9<$F$7+$G$7),$E$7/$G$7,0) -> 0 | Q7: =IF(AND(10>=$F$7,10<$F$7+$G$7),$E$7/$G$7,0) -> 0 | R7: =IF(AND(11>=$F$7,11<$F$7+$G$7),$E$7/$G$7,0) -> 0 | S7: =IF(AND(12>=$F$7,12<$F$7+$G$7),$E$7/$G$7,0) -> 0 | T7: =IF(AND(13>=$F$7,13<$F$7+$G$7),$E$7/$G$7,0) -> 0 | U7: =IF(AND(14>=$F$7,14<$F$7+$G$7),$E$7/$G$7,0) -> 0 | V7: =IF(AND(15>=$F$7,15<$F$7+$G$7),$E$7/$G$7,0) -> 0 | W7: =IF(AND(16>=$F$7,16<$F$7+$G$7),$E$7/$G$7,0) -> 0 | X7: =IF(AND(17>=$F$7,17<$F$7+$G$7),$E$7/$G$7,0) -> 0 | Y7: =IF(AND(18>=$F$7,18<$F$7+$G$7),$E$7/$G$7,0) -> 0 | Z7: =IF(AND(19>=$F$7,19<$F$7+$G$7),$E$7/$G$7,0) -> 0 | AA7: =IF(AND(20>=$F$7,20<$F$7+$G$7),$E$7/$G$7,0) -> 0 | AB7: =IF(AND(21>=$F$7,21<$F$7+$G$7),$E$7/$G$7,0) -> 0 | AC7: =IF(AND(22>=$F$7,22<$F$7+$G$7),$E$7/$G$7,0) -> 0 | AD7: =IF(AND(23>=$F$7,23<$F$7+$G$7),$E$7/$G$7,0) -> 0 | AE7: =IF(AND(24>=$F$7,24<$F$7+$G$7),$E$7/$G$7,0) -> 0 | AF7: =IF(AND(25>=$F$7,25<$F$7+$G$7),$E$7/$G$7,0) -> 0 | AG7: =IF(AND(26>=$F$7,26<$F$7+$G$7),$E$7/$G$7,0) -> 0 | AH7: =IF(AND(27>=$F$7,27<$F$7+$G$7),$E$7/$G$7,0) -> 0 | AI7: =IF(AND(28>=$F$7,28<$F$7+$G$7),$E$7/$G$7,0) -> 0 | AJ7: =IF(AND(29>=$F$7,29<$F$7+$G$7),$E$7/$G$7,0) -> 0 | AK7: =IF(AND(30>=$F$7,30<$F$7+$G$7),$E$7/$G$7,0) -> 0 | AL7: =IF(AND(31>=$F$7,31<$F$7+$G$7),$E$7/$G$7,0) -> 0 | AM7: =IF(AND(32>=$F$7,32<$F$7+$G$7),$E$7/$G$7,0) -> 0 | AN7: =IF(AND(33>=$F$7,33<$F$7+$G$7),$E$7/$G$7,0) -> 0 | AO7: =IF(AND(34>=$F$7,34<$F$7+$G$7),$E$7/$G$7,0) -> 0 | AP7: =IF(AND(35>=$F$7,35<$F$7+$G$7),$E$7/$G$7,0) -> 0 | AQ7: =IF(AND(36>=$F$7,36<$F$7+$G$7),$E$7/$G$7,0) -> 0 | AR7: =IF(AND(37>=$F$7,37<$F$7+$G$7),$E$7/$G$7,0) -> 0 | AS7: =IF(AND(38>=$F$7,38<$F$7+$G$7),$E$7/$G$7,0) -> 0 | AT7: =IF(AND(39>=$F$7,39<$F$7+$G$7),$E$7/$G$7,0) -> 0 | AU7: =IF(AND(40>=$F$7,40<$F$7+$G$7),$E$7/$G$7,0) -> 0 | AV7: =IF(AND(41>=$F$7,41<$F$7+$G$7),$E$7/$G$7,0) -> 0 | AW7: =IF(AND(42>=$F$7,42<$F$7+$G$7),$E$7/$G$7,0) -> 0 | AX7: =IF(AND(43>=$F$7,43<$F$7+$G$7),$E$7/$G$7,0) -> 0 | AY7: =IF(AND(44>=$F$7,44<$F$7+$G$7),$E$7/$G$7,0) -> 0 | AZ7: =IF(AND(45>=$F$7,45<$F$7+$G$7),$E$7/$G$7,0) -> 0 | BA7: =IF(AND(46>=$F$7,46<$F$7+$G$7),$E$7/$G$7,0) -> 0 | BB7: =IF(AND(47>=$F$7,47<$F$7+$G$7),$E$7/$G$7,0) -> 0 | BC7: =IF(AND(48>=$F$7,48<$F$7+$G$7),$E$7/$G$7,0) -> 0 | BD7: =IF(AND(49>=$F$7,49<$F$7+$G$7),$E$7/$G$7,0) -> 0 | BE7: =IF(AND(50>=$F$7,50<$F$7+$G$7),$E$7/$G$7,0) -> 0 | BF7: =IF(AND(51>=$F$7,51<$F$7+$G$7),$E$7/$G$7,0) -> 0 | BG7: =IF(AND(52>=$F$7,52<$F$7+$G$7),$E$7/$G$7,0) -> 0 | BH7: =IF(AND(53>=$F$7,53<$F$7+$G$7),$E$7/$G$7,0) -> 0 | BI7: =IF(AND(54>=$F$7,54<$F$7+$G$7),$E$7/$G$7,0) -> 0 | BJ7: =IF(AND(55>=$F$7,55<$F$7+$G$7),$E$7/$G$7,0) -> 0 | BK7: =IF(AND(56>=$F$7,56<$F$7+$G$7),$E$7/$G$7,0) -> 0 | BL7: =IF(AND(57>=$F$7,57<$F$7+$G$7),$E$7/$G$7,0) -> 0 | BM7: =IF(AND(58>=$F$7,58<$F$7+$G$7),$E$7/$G$7,0) -> 0 | BN7: =IF(AND(59>=$F$7,59<$F$7+$G$7),$E$7/$G$7,0) -> 0 | BO7: =IF(AND(60>=$F$7,60<$F$7+$G$7),$E$7/$G$7,0) -> 0
A8: 4 | B8: Gutter Repairs | C8: Structural | E8: 0 | F8: 6 | G8: 1 | H8: =IF(AND(1>=$F$8,1<$F$8+$G$8),$E$8/$G$8,0) -> 0 | I8: =IF(AND(2>=$F$8,2<$F$8+$G$8),$E$8/$G$8,0) -> 0 | J8: =IF(AND(3>=$F$8,3<$F$8+$G$8),$E$8/$G$8,0) -> 0 | K8: =IF(AND(4>=$F$8,4<$F$8+$G$8),$E$8/$G$8,0) -> 0 | L8: =IF(AND(5>=$F$8,5<$F$8+$G$8),$E$8/$G$8,0) -> 0 | M8: =IF(AND(6>=$F$8,6<$F$8+$G$8),$E$8/$G$8,0) -> 0 | N8: =IF(AND(7>=$F$8,7<$F$8+$G$8),$E$8/$G$8,0) -> 0 | O8: =IF(AND(8>=$F$8,8<$F$8+$G$8),$E$8/$G$8,0) -> 0 | P8: =IF(AND(9>=$F$8,9<$F$8+$G$8),$E$8/$G$8,0) -> 0 | Q8: =IF(AND(10>=$F$8,10<$F$8+$G$8),$E$8/$G$8,0) -> 0 | R8: =IF(AND(11>=$F$8,11<$F$8+$G$8),$E$8/$G$8,0) -> 0 | S8: =IF(AND(12>=$F$8,12<$F$8+$G$8),$E$8/$G$8,0) -> 0 | T8: =IF(AND(13>=$F$8,13<$F$8+$G$8),$E$8/$G$8,0) -> 0 | U8: =IF(AND(14>=$F$8,14<$F$8+$G$8),$E$8/$G$8,0) -> 0 | V8: =IF(AND(15>=$F$8,15<$F$8+$G$8),$E$8/$G$8,0) -> 0 | W8: =IF(AND(16>=$F$8,16<$F$8+$G$8),$E$8/$G$8,0) -> 0 | X8: =IF(AND(17>=$F$8,17<$F$8+$G$8),$E$8/$G$8,0) -> 0 | Y8: =IF(AND(18>=$F$8,18<$F$8+$G$8),$E$8/$G$8,0) -> 0 | Z8: =IF(AND(19>=$F$8,19<$F$8+$G$8),$E$8/$G$8,0) -> 0 | AA8: =IF(AND(20>=$F$8,20<$F$8+$G$8),$E$8/$G$8,0) -> 0 | AB8: =IF(AND(21>=$F$8,21<$F$8+$G$8),$E$8/$G$8,0) -> 0 | AC8: =IF(AND(22>=$F$8,22<$F$8+$G$8),$E$8/$G$8,0) -> 0 | AD8: =IF(AND(23>=$F$8,23<$F$8+$G$8),$E$8/$G$8,0) -> 0 | AE8: =IF(AND(24>=$F$8,24<$F$8+$G$8),$E$8/$G$8,0) -> 0 | AF8: =IF(AND(25>=$F$8,25<$F$8+$G$8),$E$8/$G$8,0) -> 0 | AG8: =IF(AND(26>=$F$8,26<$F$8+$G$8),$E$8/$G$8,0) -> 0 | AH8: =IF(AND(27>=$F$8,27<$F$8+$G$8),$E$8/$G$8,0) -> 0 | AI8: =IF(AND(28>=$F$8,28<$F$8+$G$8),$E$8/$G$8,0) -> 0 | AJ8: =IF(AND(29>=$F$8,29<$F$8+$G$8),$E$8/$G$8,0) -> 0 | AK8: =IF(AND(30>=$F$8,30<$F$8+$G$8),$E$8/$G$8,0) -> 0 | AL8: =IF(AND(31>=$F$8,31<$F$8+$G$8),$E$8/$G$8,0) -> 0 | AM8: =IF(AND(32>=$F$8,32<$F$8+$G$8),$E$8/$G$8,0) -> 0 | AN8: =IF(AND(33>=$F$8,33<$F$8+$G$8),$E$8/$G$8,0) -> 0 | AO8: =IF(AND(34>=$F$8,34<$F$8+$G$8),$E$8/$G$8,0) -> 0 | AP8: =IF(AND(35>=$F$8,35<$F$8+$G$8),$E$8/$G$8,0) -> 0 | AQ8: =IF(AND(36>=$F$8,36<$F$8+$G$8),$E$8/$G$8,0) -> 0 | AR8: =IF(AND(37>=$F$8,37<$F$8+$G$8),$E$8/$G$8,0) -> 0 | AS8: =IF(AND(38>=$F$8,38<$F$8+$G$8),$E$8/$G$8,0) -> 0 | AT8: =IF(AND(39>=$F$8,39<$F$8+$G$8),$E$8/$G$8,0) -> 0 | AU8: =IF(AND(40>=$F$8,40<$F$8+$G$8),$E$8/$G$8,0) -> 0 | AV8: =IF(AND(41>=$F$8,41<$F$8+$G$8),$E$8/$G$8,0) -> 0 | AW8: =IF(AND(42>=$F$8,42<$F$8+$G$8),$E$8/$G$8,0) -> 0 | AX8: =IF(AND(43>=$F$8,43<$F$8+$G$8),$E$8/$G$8,0) -> 0 | AY8: =IF(AND(44>=$F$8,44<$F$8+$G$8),$E$8/$G$8,0) -> 0 | AZ8: =IF(AND(45>=$F$8,45<$F$8+$G$8),$E$8/$G$8,0) -> 0 | BA8: =IF(AND(46>=$F$8,46<$F$8+$G$8),$E$8/$G$8,0) -> 0 | BB8: =IF(AND(47>=$F$8,47<$F$8+$G$8),$E$8/$G$8,0) -> 0 | BC8: =IF(AND(48>=$F$8,48<$F$8+$G$8),$E$8/$G$8,0) -> 0 | BD8: =IF(AND(49>=$F$8,49<$F$8+$G$8),$E$8/$G$8,0) -> 0 | BE8: =IF(AND(50>=$F$8,50<$F$8+$G$8),$E$8/$G$8,0) -> 0 | BF8: =IF(AND(51>=$F$8,51<$F$8+$G$8),$E$8/$G$8,0) -> 0 | BG8: =IF(AND(52>=$F$8,52<$F$8+$G$8),$E$8/$G$8,0) -> 0 | BH8: =IF(AND(53>=$F$8,53<$F$8+$G$8),$E$8/$G$8,0) -> 0 | BI8: =IF(AND(54>=$F$8,54<$F$8+$G$8),$E$8/$G$8,0) -> 0 | BJ8: =IF(AND(55>=$F$8,55<$F$8+$G$8),$E$8/$G$8,0) -> 0 | BK8: =IF(AND(56>=$F$8,56<$F$8+$G$8),$E$8/$G$8,0) -> 0 | BL8: =IF(AND(57>=$F$8,57<$F$8+$G$8),$E$8/$G$8,0) -> 0 | BM8: =IF(AND(58>=$F$8,58<$F$8+$G$8),$E$8/$G$8,0) -> 0 | BN8: =IF(AND(59>=$F$8,59<$F$8+$G$8),$E$8/$G$8,0) -> 0 | BO8: =IF(AND(60>=$F$8,60<$F$8+$G$8),$E$8/$G$8,0) -> 0
A9: 5 | B9: Exterior LED Lighting | C9: Electrical | E9: 0 | F9: 5 | G9: 1 | H9: =IF(AND(1>=$F$9,1<$F$9+$G$9),$E$9/$G$9,0) -> 0 | I9: =IF(AND(2>=$F$9,2<$F$9+$G$9),$E$9/$G$9,0) -> 0 | J9: =IF(AND(3>=$F$9,3<$F$9+$G$9),$E$9/$G$9,0) -> 0 | K9: =IF(AND(4>=$F$9,4<$F$9+$G$9),$E$9/$G$9,0) -> 0 | L9: =IF(AND(5>=$F$9,5<$F$9+$G$9),$E$9/$G$9,0) -> 0 | M9: =IF(AND(6>=$F$9,6<$F$9+$G$9),$E$9/$G$9,0) -> 0 | N9: =IF(AND(7>=$F$9,7<$F$9+$G$9),$E$9/$G$9,0) -> 0 | O9: =IF(AND(8>=$F$9,8<$F$9+$G$9),$E$9/$G$9,0) -> 0 | P9: =IF(AND(9>=$F$9,9<$F$9+$G$9),$E$9/$G$9,0) -> 0 | Q9: =IF(AND(10>=$F$9,10<$F$9+$G$9),$E$9/$G$9,0) -> 0 | R9: =IF(AND(11>=$F$9,11<$F$9+$G$9),$E$9/$G$9,0) -> 0 | S9: =IF(AND(12>=$F$9,12<$F$9+$G$9),$E$9/$G$9,0) -> 0 | T9: =IF(AND(13>=$F$9,13<$F$9+$G$9),$E$9/$G$9,0) -> 0 | U9: =IF(AND(14>=$F$9,14<$F$9+$G$9),$E$9/$G$9,0) -> 0 | V9: =IF(AND(15>=$F$9,15<$F$9+$G$9),$E$9/$G$9,0) -> 0 | W9: =IF(AND(16>=$F$9,16<$F$9+$G$9),$E$9/$G$9,0) -> 0 | X9: =IF(AND(17>=$F$9,17<$F$9+$G$9),$E$9/$G$9,0) -> 0 | Y9: =IF(AND(18>=$F$9,18<$F$9+$G$9),$E$9/$G$9,0) -> 0 | Z9: =IF(AND(19>=$F$9,19<$F$9+$G$9),$E$9/$G$9,0) -> 0 | AA9: =IF(AND(20>=$F$9,20<$F$9+$G$9),$E$9/$G$9,0) -> 0 | AB9: =IF(AND(21>=$F$9,21<$F$9+$G$9),$E$9/$G$9,0) -> 0 | AC9: =IF(AND(22>=$F$9,22<$F$9+$G$9),$E$9/$G$9,0) -> 0 | AD9: =IF(AND(23>=$F$9,23<$F$9+$G$9),$E$9/$G$9,0) -> 0 | AE9: =IF(AND(24>=$F$9,24<$F$9+$G$9),$E$9/$G$9,0) -> 0 | AF9: =IF(AND(25>=$F$9,25<$F$9+$G$9),$E$9/$G$9,0) -> 0 | AG9: =IF(AND(26>=$F$9,26<$F$9+$G$9),$E$9/$G$9,0) -> 0 | AH9: =IF(AND(27>=$F$9,27<$F$9+$G$9),$E$9/$G$9,0) -> 0 | AI9: =IF(AND(28>=$F$9,28<$F$9+$G$9),$E$9/$G$9,0) -> 0 | AJ9: =IF(AND(29>=$F$9,29<$F$9+$G$9),$E$9/$G$9,0) -> 0 | AK9: =IF(AND(30>=$F$9,30<$F$9+$G$9),$E$9/$G$9,0) -> 0 | AL9: =IF(AND(31>=$F$9,31<$F$9+$G$9),$E$9/$G$9,0) -> 0 | AM9: =IF(AND(32>=$F$9,32<$F$9+$G$9),$E$9/$G$9,0) -> 0 | AN9: =IF(AND(33>=$F$9,33<$F$9+$G$9),$E$9/$G$9,0) -> 0 | AO9: =IF(AND(34>=$F$9,34<$F$9+$G$9),$E$9/$G$9,0) -> 0 | AP9: =IF(AND(35>=$F$9,35<$F$9+$G$9),$E$9/$G$9,0) -> 0 | AQ9: =IF(AND(36>=$F$9,36<$F$9+$G$9),$E$9/$G$9,0) -> 0 | AR9: =IF(AND(37>=$F$9,37<$F$9+$G$9),$E$9/$G$9,0) -> 0 | AS9: =IF(AND(38>=$F$9,38<$F$9+$G$9),$E$9/$G$9,0) -> 0 | AT9: =IF(AND(39>=$F$9,39<$F$9+$G$9),$E$9/$G$9,0) -> 0 | AU9: =IF(AND(40>=$F$9,40<$F$9+$G$9),$E$9/$G$9,0) -> 0 | AV9: =IF(AND(41>=$F$9,41<$F$9+$G$9),$E$9/$G$9,0) -> 0 | AW9: =IF(AND(42>=$F$9,42<$F$9+$G$9),$E$9/$G$9,0) -> 0 | AX9: =IF(AND(43>=$F$9,43<$F$9+$G$9),$E$9/$G$9,0) -> 0 | AY9: =IF(AND(44>=$F$9,44<$F$9+$G$9),$E$9/$G$9,0) -> 0 | AZ9: =IF(AND(45>=$F$9,45<$F$9+$G$9),$E$9/$G$9,0) -> 0 | BA9: =IF(AND(46>=$F$9,46<$F$9+$G$9),$E$9/$G$9,0) -> 0 | BB9: =IF(AND(47>=$F$9,47<$F$9+$G$9),$E$9/$G$9,0) -> 0 | BC9: =IF(AND(48>=$F$9,48<$F$9+$G$9),$E$9/$G$9,0) -> 0 | BD9: =IF(AND(49>=$F$9,49<$F$9+$G$9),$E$9/$G$9,0) -> 0 | BE9: =IF(AND(50>=$F$9,50<$F$9+$G$9),$E$9/$G$9,0) -> 0 | BF9: =IF(AND(51>=$F$9,51<$F$9+$G$9),$E$9/$G$9,0) -> 0 | BG9: =IF(AND(52>=$F$9,52<$F$9+$G$9),$E$9/$G$9,0) -> 0 | BH9: =IF(AND(53>=$F$9,53<$F$9+$G$9),$E$9/$G$9,0) -> 0 | BI9: =IF(AND(54>=$F$9,54<$F$9+$G$9),$E$9/$G$9,0) -> 0 | BJ9: =IF(AND(55>=$F$9,55<$F$9+$G$9),$E$9/$G$9,0) -> 0 | BK9: =IF(AND(56>=$F$9,56<$F$9+$G$9),$E$9/$G$9,0) -> 0 | BL9: =IF(AND(57>=$F$9,57<$F$9+$G$9),$E$9/$G$9,0) -> 0 | BM9: =IF(AND(58>=$F$9,58<$F$9+$G$9),$E$9/$G$9,0) -> 0 | BN9: =IF(AND(59>=$F$9,59<$F$9+$G$9),$E$9/$G$9,0) -> 0 | BO9: =IF(AND(60>=$F$9,60<$F$9+$G$9),$E$9/$G$9,0) -> 0
A10: 6 | B10: Sewer Line Repair | C10: Mechanical | E10: 0 | F10: 6 | G10: 1 | H10: =IF(AND(1>=$F$10,1<$F$10+$G$10),$E$10/$G$10,0) -> 0 | I10: =IF(AND(2>=$F$10,2<$F$10+$G$10),$E$10/$G$10,0) -> 0 | J10: =IF(AND(3>=$F$10,3<$F$10+$G$10),$E$10/$G$10,0) -> 0 | K10: =IF(AND(4>=$F$10,4<$F$10+$G$10),$E$10/$G$10,0) -> 0 | L10: =IF(AND(5>=$F$10,5<$F$10+$G$10),$E$10/$G$10,0) -> 0 | M10: =IF(AND(6>=$F$10,6<$F$10+$G$10),$E$10/$G$10,0) -> 0 | N10: =IF(AND(7>=$F$10,7<$F$10+$G$10),$E$10/$G$10,0) -> 0 | O10: =IF(AND(8>=$F$10,8<$F$10+$G$10),$E$10/$G$10,0) -> 0 | P10: =IF(AND(9>=$F$10,9<$F$10+$G$10),$E$10/$G$10,0) -> 0 | Q10: =IF(AND(10>=$F$10,10<$F$10+$G$10),$E$10/$G$10,0) -> 0 | R10: =IF(AND(11>=$F$10,11<$F$10+$G$10),$E$10/$G$10,0) -> 0 | S10: =IF(AND(12>=$F$10,12<$F$10+$G$10),$E$10/$G$10,0) -> 0 | T10: =IF(AND(13>=$F$10,13<$F$10+$G$10),$E$10/$G$10,0) -> 0 | U10: =IF(AND(14>=$F$10,14<$F$10+$G$10),$E$10/$G$10,0) -> 0 | V10: =IF(AND(15>=$F$10,15<$F$10+$G$10),$E$10/$G$10,0) -> 0 | W10: =IF(AND(16>=$F$10,16<$F$10+$G$10),$E$10/$G$10,0) -> 0 | X10: =IF(AND(17>=$F$10,17<$F$10+$G$10),$E$10/$G$10,0) -> 0 | Y10: =IF(AND(18>=$F$10,18<$F$10+$G$10),$E$10/$G$10,0) -> 0 | Z10: =IF(AND(19>=$F$10,19<$F$10+$G$10),$E$10/$G$10,0) -> 0 | AA10: =IF(AND(20>=$F$10,20<$F$10+$G$10),$E$10/$G$10,0) -> 0 | AB10: =IF(AND(21>=$F$10,21<$F$10+$G$10),$E$10/$G$10,0) -> 0 | AC10: =IF(AND(22>=$F$10,22<$F$10+$G$10),$E$10/$G$10,0) -> 0 | AD10: =IF(AND(23>=$F$10,23<$F$10+$G$10),$E$10/$G$10,0) -> 0 | AE10: =IF(AND(24>=$F$10,24<$F$10+$G$10),$E$10/$G$10,0) -> 0 | AF10: =IF(AND(25>=$F$10,25<$F$10+$G$10),$E$10/$G$10,0) -> 0 | AG10: =IF(AND(26>=$F$10,26<$F$10+$G$10),$E$10/$G$10,0) -> 0 | AH10: =IF(AND(27>=$F$10,27<$F$10+$G$10),$E$10/$G$10,0) -> 0 | AI10: =IF(AND(28>=$F$10,28<$F$10+$G$10),$E$10/$G$10,0) -> 0 | AJ10: =IF(AND(29>=$F$10,29<$F$10+$G$10),$E$10/$G$10,0) -> 0 | AK10: =IF(AND(30>=$F$10,30<$F$10+$G$10),$E$10/$G$10,0) -> 0 | AL10: =IF(AND(31>=$F$10,31<$F$10+$G$10),$E$10/$G$10,0) -> 0 | AM10: =IF(AND(32>=$F$10,32<$F$10+$G$10),$E$10/$G$10,0) -> 0 | AN10: =IF(AND(33>=$F$10,33<$F$10+$G$10),$E$10/$G$10,0) -> 0 | AO10: =IF(AND(34>=$F$10,34<$F$10+$G$10),$E$10/$G$10,0) -> 0 | AP10: =IF(AND(35>=$F$10,35<$F$10+$G$10),$E$10/$G$10,0) -> 0 | AQ10: =IF(AND(36>=$F$10,36<$F$10+$G$10),$E$10/$G$10,0) -> 0 | AR10: =IF(AND(37>=$F$10,37<$F$10+$G$10),$E$10/$G$10,0) -> 0 | AS10: =IF(AND(38>=$F$10,38<$F$10+$G$10),$E$10/$G$10,0) -> 0 | AT10: =IF(AND(39>=$F$10,39<$F$10+$G$10),$E$10/$G$10,0) -> 0 | AU10: =IF(AND(40>=$F$10,40<$F$10+$G$10),$E$10/$G$10,0) -> 0 | AV10: =IF(AND(41>=$F$10,41<$F$10+$G$10),$E$10/$G$10,0) -> 0 | AW10: =IF(AND(42>=$F$10,42<$F$10+$G$10),$E$10/$G$10,0) -> 0 | AX10: =IF(AND(43>=$F$10,43<$F$10+$G$10),$E$10/$G$10,0) -> 0 | AY10: =IF(AND(44>=$F$10,44<$F$10+$G$10),$E$10/$G$10,0) -> 0 | AZ10: =IF(AND(45>=$F$10,45<$F$10+$G$10),$E$10/$G$10,0) -> 0 | BA10: =IF(AND(46>=$F$10,46<$F$10+$G$10),$E$10/$G$10,0) -> 0 | BB10: =IF(AND(47>=$F$10,47<$F$10+$G$10),$E$10/$G$10,0) -> 0 | BC10: =IF(AND(48>=$F$10,48<$F$10+$G$10),$E$10/$G$10,0) -> 0 | BD10: =IF(AND(49>=$F$10,49<$F$10+$G$10),$E$10/$G$10,0) -> 0 | BE10: =IF(AND(50>=$F$10,50<$F$10+$G$10),$E$10/$G$10,0) -> 0 | BF10: =IF(AND(51>=$F$10,51<$F$10+$G$10),$E$10/$G$10,0) -> 0 | BG10: =IF(AND(52>=$F$10,52<$F$10+$G$10),$E$10/$G$10,0) -> 0 | BH10: =IF(AND(53>=$F$10,53<$F$10+$G$10),$E$10/$G$10,0) -> 0 | BI10: =IF(AND(54>=$F$10,54<$F$10+$G$10),$E$10/$G$10,0) -> 0 | BJ10: =IF(AND(55>=$F$10,55<$F$10+$G$10),$E$10/$G$10,0) -> 0 | BK10: =IF(AND(56>=$F$10,56<$F$10+$G$10),$E$10/$G$10,0) -> 0 | BL10: =IF(AND(57>=$F$10,57<$F$10+$G$10),$E$10/$G$10,0) -> 0 | BM10: =IF(AND(58>=$F$10,58<$F$10+$G$10),$E$10/$G$10,0) -> 0 | BN10: =IF(AND(59>=$F$10,59<$F$10+$G$10),$E$10/$G$10,0) -> 0 | BO10: =IF(AND(60>=$F$10,60<$F$10+$G$10),$E$10/$G$10,0) -> 0
A11: 7 | B11: Tree Service | C11: Site | E11: 0 | F11: 2 | G11: 1 | H11: =IF(AND(1>=$F$11,1<$F$11+$G$11),$E$11/$G$11,0) -> 0 | I11: =IF(AND(2>=$F$11,2<$F$11+$G$11),$E$11/$G$11,0) -> 0 | J11: =IF(AND(3>=$F$11,3<$F$11+$G$11),$E$11/$G$11,0) -> 0 | K11: =IF(AND(4>=$F$11,4<$F$11+$G$11),$E$11/$G$11,0) -> 0 | L11: =IF(AND(5>=$F$11,5<$F$11+$G$11),$E$11/$G$11,0) -> 0 | M11: =IF(AND(6>=$F$11,6<$F$11+$G$11),$E$11/$G$11,0) -> 0 | N11: =IF(AND(7>=$F$11,7<$F$11+$G$11),$E$11/$G$11,0) -> 0 | O11: =IF(AND(8>=$F$11,8<$F$11+$G$11),$E$11/$G$11,0) -> 0 | P11: =IF(AND(9>=$F$11,9<$F$11+$G$11),$E$11/$G$11,0) -> 0 | Q11: =IF(AND(10>=$F$11,10<$F$11+$G$11),$E$11/$G$11,0) -> 0 | R11: =IF(AND(11>=$F$11,11<$F$11+$G$11),$E$11/$G$11,0) -> 0 | S11: =IF(AND(12>=$F$11,12<$F$11+$G$11),$E$11/$G$11,0) -> 0 | T11: =IF(AND(13>=$F$11,13<$F$11+$G$11),$E$11/$G$11,0) -> 0 | U11: =IF(AND(14>=$F$11,14<$F$11+$G$11),$E$11/$G$11,0) -> 0 | V11: =IF(AND(15>=$F$11,15<$F$11+$G$11),$E$11/$G$11,0) -> 0 | W11: =IF(AND(16>=$F$11,16<$F$11+$G$11),$E$11/$G$11,0) -> 0 | X11: =IF(AND(17>=$F$11,17<$F$11+$G$11),$E$11/$G$11,0) -> 0 | Y11: =IF(AND(18>=$F$11,18<$F$11+$G$11),$E$11/$G$11,0) -> 0 | Z11: =IF(AND(19>=$F$11,19<$F$11+$G$11),$E$11/$G$11,0) -> 0 | AA11: =IF(AND(20>=$F$11,20<$F$11+$G$11),$E$11/$G$11,0) -> 0 | AB11: =IF(AND(21>=$F$11,21<$F$11+$G$11),$E$11/$G$11,0) -> 0 | AC11: =IF(AND(22>=$F$11,22<$F$11+$G$11),$E$11/$G$11,0) -> 0 | AD11: =IF(AND(23>=$F$11,23<$F$11+$G$11),$E$11/$G$11,0) -> 0 | AE11: =IF(AND(24>=$F$11,24<$F$11+$G$11),$E$11/$G$11,0) -> 0 | AF11: =IF(AND(25>=$F$11,25<$F$11+$G$11),$E$11/$G$11,0) -> 0 | AG11: =IF(AND(26>=$F$11,26<$F$11+$G$11),$E$11/$G$11,0) -> 0 | AH11: =IF(AND(27>=$F$11,27<$F$11+$G$11),$E$11/$G$11,0) -> 0 | AI11: =IF(AND(28>=$F$11,28<$F$11+$G$11),$E$11/$G$11,0) -> 0 | AJ11: =IF(AND(29>=$F$11,29<$F$11+$G$11),$E$11/$G$11,0) -> 0 | AK11: =IF(AND(30>=$F$11,30<$F$11+$G$11),$E$11/$G$11,0) -> 0 | AL11: =IF(AND(31>=$F$11,31<$F$11+$G$11),$E$11/$G$11,0) -> 0 | AM11: =IF(AND(32>=$F$11,32<$F$11+$G$11),$E$11/$G$11,0) -> 0 | AN11: =IF(AND(33>=$F$11,33<$F$11+$G$11),$E$11/$G$11,0) -> 0 | AO11: =IF(AND(34>=$F$11,34<$F$11+$G$11),$E$11/$G$11,0) -> 0 | AP11: =IF(AND(35>=$F$11,35<$F$11+$G$11),$E$11/$G$11,0) -> 0 | AQ11: =IF(AND(36>=$F$11,36<$F$11+$G$11),$E$11/$G$11,0) -> 0 | AR11: =IF(AND(37>=$F$11,37<$F$11+$G$11),$E$11/$G$11,0) -> 0 | AS11: =IF(AND(38>=$F$11,38<$F$11+$G$11),$E$11/$G$11,0) -> 0 | AT11: =IF(AND(39>=$F$11,39<$F$11+$G$11),$E$11/$G$11,0) -> 0 | AU11: =IF(AND(40>=$F$11,40<$F$11+$G$11),$E$11/$G$11,0) -> 0 | AV11: =IF(AND(41>=$F$11,41<$F$11+$G$11),$E$11/$G$11,0) -> 0 | AW11: =IF(AND(42>=$F$11,42<$F$11+$G$11),$E$11/$G$11,0) -> 0 | AX11: =IF(AND(43>=$F$11,43<$F$11+$G$11),$E$11/$G$11,0) -> 0 | AY11: =IF(AND(44>=$F$11,44<$F$11+$G$11),$E$11/$G$11,0) -> 0 | AZ11: =IF(AND(45>=$F$11,45<$F$11+$G$11),$E$11/$G$11,0) -> 0 | BA11: =IF(AND(46>=$F$11,46<$F$11+$G$11),$E$11/$G$11,0) -> 0 | BB11: =IF(AND(47>=$F$11,47<$F$11+$G$11),$E$11/$G$11,0) -> 0 | BC11: =IF(AND(48>=$F$11,48<$F$11+$G$11),$E$11/$G$11,0) -> 0 | BD11: =IF(AND(49>=$F$11,49<$F$11+$G$11),$E$11/$G$11,0) -> 0 | BE11: =IF(AND(50>=$F$11,50<$F$11+$G$11),$E$11/$G$11,0) -> 0 | BF11: =IF(AND(51>=$F$11,51<$F$11+$G$11),$E$11/$G$11,0) -> 0 | BG11: =IF(AND(52>=$F$11,52<$F$11+$G$11),$E$11/$G$11,0) -> 0 | BH11: =IF(AND(53>=$F$11,53<$F$11+$G$11),$E$11/$G$11,0) -> 0 | BI11: =IF(AND(54>=$F$11,54<$F$11+$G$11),$E$11/$G$11,0) -> 0 | BJ11: =IF(AND(55>=$F$11,55<$F$11+$G$11),$E$11/$G$11,0) -> 0 | BK11: =IF(AND(56>=$F$11,56<$F$11+$G$11),$E$11/$G$11,0) -> 0 | BL11: =IF(AND(57>=$F$11,57<$F$11+$G$11),$E$11/$G$11,0) -> 0 | BM11: =IF(AND(58>=$F$11,58<$F$11+$G$11),$E$11/$G$11,0) -> 0 | BN11: =IF(AND(59>=$F$11,59<$F$11+$G$11),$E$11/$G$11,0) -> 0 | BO11: =IF(AND(60>=$F$11,60<$F$11+$G$11),$E$11/$G$11,0) -> 0
A12: 8 | B12: Misc Repairs | C12: Cosmetic | E12: 0 | F12: 3 | G12: 1 | H12: =IF(AND(1>=$F$12,1<$F$12+$G$12),$E$12/$G$12,0) -> 0 | I12: =IF(AND(2>=$F$12,2<$F$12+$G$12),$E$12/$G$12,0) -> 0 | J12: =IF(AND(3>=$F$12,3<$F$12+$G$12),$E$12/$G$12,0) -> 0 | K12: =IF(AND(4>=$F$12,4<$F$12+$G$12),$E$12/$G$12,0) -> 0 | L12: =IF(AND(5>=$F$12,5<$F$12+$G$12),$E$12/$G$12,0) -> 0 | M12: =IF(AND(6>=$F$12,6<$F$12+$G$12),$E$12/$G$12,0) -> 0 | N12: =IF(AND(7>=$F$12,7<$F$12+$G$12),$E$12/$G$12,0) -> 0 | O12: =IF(AND(8>=$F$12,8<$F$12+$G$12),$E$12/$G$12,0) -> 0 | P12: =IF(AND(9>=$F$12,9<$F$12+$G$12),$E$12/$G$12,0) -> 0 | Q12: =IF(AND(10>=$F$12,10<$F$12+$G$12),$E$12/$G$12,0) -> 0 | R12: =IF(AND(11>=$F$12,11<$F$12+$G$12),$E$12/$G$12,0) -> 0 | S12: =IF(AND(12>=$F$12,12<$F$12+$G$12),$E$12/$G$12,0) -> 0 | T12: =IF(AND(13>=$F$12,13<$F$12+$G$12),$E$12/$G$12,0) -> 0 | U12: =IF(AND(14>=$F$12,14<$F$12+$G$12),$E$12/$G$12,0) -> 0 | V12: =IF(AND(15>=$F$12,15<$F$12+$G$12),$E$12/$G$12,0) -> 0 | W12: =IF(AND(16>=$F$12,16<$F$12+$G$12),$E$12/$G$12,0) -> 0 | X12: =IF(AND(17>=$F$12,17<$F$12+$G$12),$E$12/$G$12,0) -> 0 | Y12: =IF(AND(18>=$F$12,18<$F$12+$G$12),$E$12/$G$12,0) -> 0 | Z12: =IF(AND(19>=$F$12,19<$F$12+$G$12),$E$12/$G$12,0) -> 0 | AA12: =IF(AND(20>=$F$12,20<$F$12+$G$12),$E$12/$G$12,0) -> 0 | AB12: =IF(AND(21>=$F$12,21<$F$12+$G$12),$E$12/$G$12,0) -> 0 | AC12: =IF(AND(22>=$F$12,22<$F$12+$G$12),$E$12/$G$12,0) -> 0 | AD12: =IF(AND(23>=$F$12,23<$F$12+$G$12),$E$12/$G$12,0) -> 0 | AE12: =IF(AND(24>=$F$12,24<$F$12+$G$12),$E$12/$G$12,0) -> 0 | AF12: =IF(AND(25>=$F$12,25<$F$12+$G$12),$E$12/$G$12,0) -> 0 | AG12: =IF(AND(26>=$F$12,26<$F$12+$G$12),$E$12/$G$12,0) -> 0 | AH12: =IF(AND(27>=$F$12,27<$F$12+$G$12),$E$12/$G$12,0) -> 0 | AI12: =IF(AND(28>=$F$12,28<$F$12+$G$12),$E$12/$G$12,0) -> 0 | AJ12: =IF(AND(29>=$F$12,29<$F$12+$G$12),$E$12/$G$12,0) -> 0 | AK12: =IF(AND(30>=$F$12,30<$F$12+$G$12),$E$12/$G$12,0) -> 0 | AL12: =IF(AND(31>=$F$12,31<$F$12+$G$12),$E$12/$G$12,0) -> 0 | AM12: =IF(AND(32>=$F$12,32<$F$12+$G$12),$E$12/$G$12,0) -> 0 | AN12: =IF(AND(33>=$F$12,33<$F$12+$G$12),$E$12/$G$12,0) -> 0 | AO12: =IF(AND(34>=$F$12,34<$F$12+$G$12),$E$12/$G$12,0) -> 0 | AP12: =IF(AND(35>=$F$12,35<$F$12+$G$12),$E$12/$G$12,0) -> 0 | AQ12: =IF(AND(36>=$F$12,36<$F$12+$G$12),$E$12/$G$12,0) -> 0 | AR12: =IF(AND(37>=$F$12,37<$F$12+$G$12),$E$12/$G$12,0) -> 0 | AS12: =IF(AND(38>=$F$12,38<$F$12+$G$12),$E$12/$G$12,0) -> 0 | AT12: =IF(AND(39>=$F$12,39<$F$12+$G$12),$E$12/$G$12,0) -> 0 | AU12: =IF(AND(40>=$F$12,40<$F$12+$G$12),$E$12/$G$12,0) -> 0 | AV12: =IF(AND(41>=$F$12,41<$F$12+$G$12),$E$12/$G$12,0) -> 0 | AW12: =IF(AND(42>=$F$12,42<$F$12+$G$12),$E$12/$G$12,0) -> 0 | AX12: =IF(AND(43>=$F$12,43<$F$12+$G$12),$E$12/$G$12,0) -> 0 | AY12: =IF(AND(44>=$F$12,44<$F$12+$G$12),$E$12/$G$12,0) -> 0 | AZ12: =IF(AND(45>=$F$12,45<$F$12+$G$12),$E$12/$G$12,0) -> 0 | BA12: =IF(AND(46>=$F$12,46<$F$12+$G$12),$E$12/$G$12,0) -> 0 | BB12: =IF(AND(47>=$F$12,47<$F$12+$G$12),$E$12/$G$12,0) -> 0 | BC12: =IF(AND(48>=$F$12,48<$F$12+$G$12),$E$12/$G$12,0) -> 0 | BD12: =IF(AND(49>=$F$12,49<$F$12+$G$12),$E$12/$G$12,0) -> 0 | BE12: =IF(AND(50>=$F$12,50<$F$12+$G$12),$E$12/$G$12,0) -> 0 | BF12: =IF(AND(51>=$F$12,51<$F$12+$G$12),$E$12/$G$12,0) -> 0 | BG12: =IF(AND(52>=$F$12,52<$F$12+$G$12),$E$12/$G$12,0) -> 0 | BH12: =IF(AND(53>=$F$12,53<$F$12+$G$12),$E$12/$G$12,0) -> 0 | BI12: =IF(AND(54>=$F$12,54<$F$12+$G$12),$E$12/$G$12,0) -> 0 | BJ12: =IF(AND(55>=$F$12,55<$F$12+$G$12),$E$12/$G$12,0) -> 0 | BK12: =IF(AND(56>=$F$12,56<$F$12+$G$12),$E$12/$G$12,0) -> 0 | BL12: =IF(AND(57>=$F$12,57<$F$12+$G$12),$E$12/$G$12,0) -> 0 | BM12: =IF(AND(58>=$F$12,58<$F$12+$G$12),$E$12/$G$12,0) -> 0 | BN12: =IF(AND(59>=$F$12,59<$F$12+$G$12),$E$12/$G$12,0) -> 0 | BO12: =IF(AND(60>=$F$12,60<$F$12+$G$12),$E$12/$G$12,0) -> 0
B13: TOTAL CAPEX | E13: =SUM(E5:E12) -> 150000 | H13: =SUM(H5:H12) -> 25000 | I13: =SUM(I5:I12) -> 25000 | J13: =SUM(J5:J12) -> 25000 | K13: =SUM(K5:K12) -> 25000 | L13: =SUM(L5:L12) -> 25000 | M13: =SUM(M5:M12) -> 25000 | N13: =SUM(N5:N12) -> 0 | O13: =SUM(O5:O12) -> 0 | ... BO13: =SUM(BO5:BO12) -> 0
A16: TENANT IMPROVEMENTS
A17: # | B17: Suite/Tenant | C17: SF | D17: Relet Month | E17: TI Cost ($) | H17: 1 | I17: 2 | J17: 3 | K17: 4 | L17: 5 | M17: 6 | N17: 7 | O17: 8 | P17: 9 | Q17: 10 | R17: 11 | S17: 12 | T17: 13 | U17: 14 | V17: 15 | W17: 16 | X17: 17 | Y17: 18 | Z17: 19 | AA17: 20 | AB17: 21 | AC17: 22 | AD17: 23 | AE17: 24 | AF17: 25 | AG17: 26 | AH17: 27 | AI17: 28 | AJ17: 29 | AK17: 30 | AL17: 31 | AM17: 32 | AN17: 33 | AO17: 34 | AP17: 35 | AQ17: 36 | AR17: 37 | AS17: 38 | AT17: 39 | AU17: 40 | AV17: 41 | AW17: 42 | AX17: 43 | AY17: 44 | AZ17: 45 | BA17: 46 | BB17: 47 | BC17: 48 | BD17: 49 | BE17: 50 | BF17: 51 | BG17: 52 | BH17: 53 | BI17: 54 | BJ17: 55 | BK17: 56 | BL17: 57 | BM17: 58 | BN17: 59 | BO17: 60
A18: ='Rent Roll'!A4 -> 4949 A1&A2 | B18: ='Rent Roll'!B4 -> Middle East Bakery | C18: ='Rent Roll'!C4 -> 2230 | D18: =IFERROR(MATCH("Relet", 'Rent Roll'!V4:CD4, 0), 0) -> 48 | E18: =('Rent Roll'!N4*'Rent Roll'!Q4+(1-'Rent Roll'!N4)*'Rent Roll'!P4)*'Rent Roll'!C4 -> 22300 | H18: =IF('Rent Roll'!V4="Relet",$E$18,0) -> 0 | I18: =IF(AND('Rent Roll'!W4="Relet",'Rent Roll'!V4<>"Relet"),$E$18,0) -> 0 | J18: =IF(AND('Rent Roll'!X4="Relet",'Rent Roll'!W4<>"Relet"),$E$18,0) -> 0 | K18: =IF(AND('Rent Roll'!Y4="Relet",'Rent Roll'!X4<>"Relet"),$E$18,0) -> 0 | L18: =IF(AND('Rent Roll'!Z4="Relet",'Rent Roll'!Y4<>"Relet"),$E$18,0) -> 0 | M18: =IF(AND('Rent Roll'!AA4="Relet",'Rent Roll'!Z4<>"Relet"),$E$18,0) -> 0 | N18: =IF(AND('Rent Roll'!AB4="Relet",'Rent Roll'!AA4<>"Relet"),$E$18,0) -> 0 | O18: =IF(AND('Rent Roll'!AC4="Relet",'Rent Roll'!AB4<>"Relet"),$E$18,0) -> 0 | P18: =IF(AND('Rent Roll'!AD4="Relet",'Rent Roll'!AC4<>"Relet"),$E$18,0) -> 0 | ... BO18: =IF(AND('Rent Roll'!CC4="Relet",'Rent Roll'!CB4<>"Relet"),$E$18,0) -> 0
A19: ='Rent Roll'!A7 -> 4949 B | B19: ='Rent Roll'!B7 -> VACANT | C19: ='Rent Roll'!C7 -> 910 | E19: =('Rent Roll'!N7*'Rent Roll'!Q7+(1-'Rent Roll'!N7)*'Rent Roll'!P7)*'Rent Roll'!C7 -> 22750 | H19: =IF('Rent Roll'!V7="Relet",$E$19,0) -> 0 | I19: =IF(AND('Rent Roll'!W7="Relet",'Rent Roll'!V7<>"Relet"),$E$19,0) -> 0 | J19: =IF(AND('Rent Roll'!X7="Relet",'Rent Roll'!W7<>"Relet"),$E$19,0) -> 0 | K19: =IF(AND('Rent Roll'!Y7="Relet",'Rent Roll'!X7<>"Relet"),$E$19,0) -> 0 | L19: =IF(AND('Rent Roll'!Z7="Relet",'Rent Roll'!Y7<>"Relet"),$E$19,0) -> 0 | M19: =IF(AND('Rent Roll'!AA7="Relet",'Rent Roll'!Z7<>"Relet"),$E$19,0) -> 22750 | N19: =IF(AND('Rent Roll'!AB7="Relet",'Rent Roll'!AA7<>"Relet"),$E$19,0) -> 0 | O19: =IF(AND('Rent Roll'!AC7="Relet",'Rent Roll'!AB7<>"Relet"),$E$19,0) -> 0 | P19: =IF(AND('Rent Roll'!AD7="Relet",'Rent Roll'!AC7<>"Relet"),$E$19,0) -> 0 | ... BO19: =IF(AND('Rent Roll'!CC7="Relet",'Rent Roll'!CB7<>"Relet"),$E$19,0) -> 0
A20: ='Rent Roll'!A10 -> 4949 C | B20: ='Rent Roll'!B10 -> Circle Pizza | C20: ='Rent Roll'!C10 -> 3620 | E20: =('Rent Roll'!N10*'Rent Roll'!Q10+(1-'Rent Roll'!N10)*'Rent Roll'!P10)*'Rent Roll'!C10 -> 36200 | H20: =IF('Rent Roll'!V10="Relet",$E$20,0) -> 0 | I20: =IF(AND('Rent Roll'!W10="Relet",'Rent Roll'!V10<>"Relet"),$E$20,0) -> 0 | J20: =IF(AND('Rent Roll'!X10="Relet",'Rent Roll'!W10<>"Relet"),$E$20,0) -> 0 | K20: =IF(AND('Rent Roll'!Y10="Relet",'Rent Roll'!X10<>"Relet"),$E$20,0) -> 0 | L20: =IF(AND('Rent Roll'!Z10="Relet",'Rent Roll'!Y10<>"Relet"),$E$20,0) -> 0 | M20: =IF(AND('Rent Roll'!AA10="Relet",'Rent Roll'!Z10<>"Relet"),$E$20,0) -> 0 | N20: =IF(AND('Rent Roll'!AB10="Relet",'Rent Roll'!AA10<>"Relet"),$E$20,0) -> 0 | O20: =IF(AND('Rent Roll'!AC10="Relet",'Rent Roll'!AB10<>"Relet"),$E$20,0) -> 0 | P20: =IF(AND('Rent Roll'!AD10="Relet",'Rent Roll'!AC10<>"Relet"),$E$20,0) -> 0 | ... BO20: =IF(AND('Rent Roll'!CC10="Relet",'Rent Roll'!CB10<>"Relet"),$E$20,0) -> 36200
A21: ='Rent Roll'!A13 -> 4949 D&E | B21: ='Rent Roll'!B13 -> Silver Sake | C21: ='Rent Roll'!C13 -> 1990 | E21: =('Rent Roll'!N13*'Rent Roll'!Q13+(1-'Rent Roll'!N13)*'Rent Roll'!P13)*'Rent Roll'!C13 -> 29850 | H21: =IF('Rent Roll'!V13="Relet",$E$21,0) -> 0 | I21: =IF(AND('Rent Roll'!W13="Relet",'Rent Roll'!V13<>"Relet"),$E$21,0) -> 0 | J21: =IF(AND('Rent Roll'!X13="Relet",'Rent Roll'!W13<>"Relet"),$E$21,0) -> 0 | K21: =IF(AND('Rent Roll'!Y13="Relet",'Rent Roll'!X13<>"Relet"),$E$21,0) -> 0 | L21: =IF(AND('Rent Roll'!Z13="Relet",'Rent Roll'!Y13<>"Relet"),$E$21,0) -> 0 | M21: =IF(AND('Rent Roll'!AA13="Relet",'Rent Roll'!Z13<>"Relet"),$E$21,0) -> 0 | N21: =IF(AND('Rent Roll'!AB13="Relet",'Rent Roll'!AA13<>"Relet"),$E$21,0) -> 29850 | O21: =IF(AND('Rent Roll'!AC13="Relet",'Rent Roll'!AB13<>"Relet"),$E$21,0) -> 0 | P21: =IF(AND('Rent Roll'!AD13="Relet",'Rent Roll'!AC13<>"Relet"),$E$21,0) -> 0 | ... BO21: =IF(AND('Rent Roll'!CC13="Relet",'Rent Roll'!CB13<>"Relet"),$E$21,0) -> 0
A22: ='Rent Roll'!A16 -> 4949 F | B22: ='Rent Roll'!B16 -> Waiel Merza | C22: ='Rent Roll'!C16 -> 810 | E22: =('Rent Roll'!N16*'Rent Roll'!Q16+(1-'Rent Roll'!N16)*'Rent Roll'!P16)*'Rent Roll'!C16 -> 8100 | H22: =IF('Rent Roll'!V16="Relet",$E$22,0) -> 0 | I22: =IF(AND('Rent Roll'!W16="Relet",'Rent Roll'!V16<>"Relet"),$E$22,0) -> 0 | J22: =IF(AND('Rent Roll'!X16="Relet",'Rent Roll'!W16<>"Relet"),$E$22,0) -> 0 | K22: =IF(AND('Rent Roll'!Y16="Relet",'Rent Roll'!X16<>"Relet"),$E$22,0) -> 0 | L22: =IF(AND('Rent Roll'!Z16="Relet",'Rent Roll'!Y16<>"Relet"),$E$22,0) -> 0 | M22: =IF(AND('Rent Roll'!AA16="Relet",'Rent Roll'!Z16<>"Relet"),$E$22,0) -> 0 | N22: =IF(AND('Rent Roll'!AB16="Relet",'Rent Roll'!AA16<>"Relet"),$E$22,0) -> 0 | O22: =IF(AND('Rent Roll'!AC16="Relet",'Rent Roll'!AB16<>"Relet"),$E$22,0) -> 0 | P22: =IF(AND('Rent Roll'!AD16="Relet",'Rent Roll'!AC16<>"Relet"),$E$22,0) -> 0 | ... BO22: =IF(AND('Rent Roll'!CC16="Relet",'Rent Roll'!CB16<>"Relet"),$E$22,0) -> 0
A23: ='Rent Roll'!A19 -> 4949 G | B23: ='Rent Roll'!B19 -> Cigarettes & Gifts | C23: ='Rent Roll'!C19 -> 810 | E23: =('Rent Roll'!N19*'Rent Roll'!Q19+(1-'Rent Roll'!N19)*'Rent Roll'!P19)*'Rent Roll'!C19 -> 8100 | H23: =IF('Rent Roll'!V19="Relet",$E$23,0) -> 0 | I23: =IF(AND('Rent Roll'!W19="Relet",'Rent Roll'!V19<>"Relet"),$E$23,0) -> 0 | J23: =IF(AND('Rent Roll'!X19="Relet",'Rent Roll'!W19<>"Relet"),$E$23,0) -> 0 | K23: =IF(AND('Rent Roll'!Y19="Relet",'Rent Roll'!X19<>"Relet"),$E$23,0) -> 0 | L23: =IF(AND('Rent Roll'!Z19="Relet",'Rent Roll'!Y19<>"Relet"),$E$23,0) -> 0 | M23: =IF(AND('Rent Roll'!AA19="Relet",'Rent Roll'!Z19<>"Relet"),$E$23,0) -> 0 | N23: =IF(AND('Rent Roll'!AB19="Relet",'Rent Roll'!AA19<>"Relet"),$E$23,0) -> 8100 | O23: =IF(AND('Rent Roll'!AC19="Relet",'Rent Roll'!AB19<>"Relet"),$E$23,0) -> 0 | P23: =IF(AND('Rent Roll'!AD19="Relet",'Rent Roll'!AC19<>"Relet"),$E$23,0) -> 0 | ... BO23: =IF(AND('Rent Roll'!CC19="Relet",'Rent Roll'!CB19<>"Relet"),$E$23,0) -> 0
A24: ='Rent Roll'!A22 -> 4949 H | B24: ='Rent Roll'!B22 -> Brittany Hair & Nails | C24: ='Rent Roll'!C22 -> 810 | E24: =('Rent Roll'!N22*'Rent Roll'!Q22+(1-'Rent Roll'!N22)*'Rent Roll'!P22)*'Rent Roll'!C22 -> 8100 | H24: =IF('Rent Roll'!V22="Relet",$E$24,0) -> 0 | I24: =IF(AND('Rent Roll'!W22="Relet",'Rent Roll'!V22<>"Relet"),$E$24,0) -> 0 | J24: =IF(AND('Rent Roll'!X22="Relet",'Rent Roll'!W22<>"Relet"),$E$24,0) -> 0 | K24: =IF(AND('Rent Roll'!Y22="Relet",'Rent Roll'!X22<>"Relet"),$E$24,0) -> 0 | L24: =IF(AND('Rent Roll'!Z22="Relet",'Rent Roll'!Y22<>"Relet"),$E$24,0) -> 0 | M24: =IF(AND('Rent Roll'!AA22="Relet",'Rent Roll'!Z22<>"Relet"),$E$24,0) -> 0 | N24: =IF(AND('Rent Roll'!AB22="Relet",'Rent Roll'!AA22<>"Relet"),$E$24,0) -> 8100 | O24: =IF(AND('Rent Roll'!AC22="Relet",'Rent Roll'!AB22<>"Relet"),$E$24,0) -> 0 | P24: =IF(AND('Rent Roll'!AD22="Relet",'Rent Roll'!AC22<>"Relet"),$E$24,0) -> 0 | ... BO24: =IF(AND('Rent Roll'!CC22="Relet",'Rent Roll'!CB22<>"Relet"),$E$24,0) -> 0
A25: ='Rent Roll'!A25 -> 4949 I | B25: ='Rent Roll'!B25 -> Madeville Hair Salon | C25: ='Rent Roll'!C25 -> 810 | E25: =('Rent Roll'!N25*'Rent Roll'!Q25+(1-'Rent Roll'!N25)*'Rent Roll'!P25)*'Rent Roll'!C25 -> 12150 | H25: =IF('Rent Roll'!V25="Relet",$E$25,0) -> 0 | I25: =IF(AND('Rent Roll'!W25="Relet",'Rent Roll'!V25<>"Relet"),$E$25,0) -> 0 | J25: =IF(AND('Rent Roll'!X25="Relet",'Rent Roll'!W25<>"Relet"),$E$25,0) -> 0 | K25: =IF(AND('Rent Roll'!Y25="Relet",'Rent Roll'!X25<>"Relet"),$E$25,0) -> 0 | L25: =IF(AND('Rent Roll'!Z25="Relet",'Rent Roll'!Y25<>"Relet"),$E$25,0) -> 0 | M25: =IF(AND('Rent Roll'!AA25="Relet",'Rent Roll'!Z25<>"Relet"),$E$25,0) -> 0 | N25: =IF(AND('Rent Roll'!AB25="Relet",'Rent Roll'!AA25<>"Relet"),$E$25,0) -> 12150 | O25: =IF(AND('Rent Roll'!AC25="Relet",'Rent Roll'!AB25<>"Relet"),$E$25,0) -> 0 | P25: =IF(AND('Rent Roll'!AD25="Relet",'Rent Roll'!AC25<>"Relet"),$E$25,0) -> 0 | ... BO25: =IF(AND('Rent Roll'!CC25="Relet",'Rent Roll'!CB25<>"Relet"),$E$25,0) -> 0
A26: ='Rent Roll'!A28 -> 4949 J | B26: ='Rent Roll'!B28 -> VACANT | C26: ='Rent Roll'!C28 -> 1350 | E26: =('Rent Roll'!N28*'Rent Roll'!Q28+(1-'Rent Roll'!N28)*'Rent Roll'!P28)*'Rent Roll'!C28 -> 33750 | H26: =IF('Rent Roll'!V28="Relet",$E$26,0) -> 0 | I26: =IF(AND('Rent Roll'!W28="Relet",'Rent Roll'!V28<>"Relet"),$E$26,0) -> 0 | J26: =IF(AND('Rent Roll'!X28="Relet",'Rent Roll'!W28<>"Relet"),$E$26,0) -> 0 | K26: =IF(AND('Rent Roll'!Y28="Relet",'Rent Roll'!X28<>"Relet"),$E$26,0) -> 0 | L26: =IF(AND('Rent Roll'!Z28="Relet",'Rent Roll'!Y28<>"Relet"),$E$26,0) -> 0 | M26: =IF(AND('Rent Roll'!AA28="Relet",'Rent Roll'!Z28<>"Relet"),$E$26,0) -> 33750 | N26: =IF(AND('Rent Roll'!AB28="Relet",'Rent Roll'!AA28<>"Relet"),$E$26,0) -> 0 | O26: =IF(AND('Rent Roll'!AC28="Relet",'Rent Roll'!AB28<>"Relet"),$E$26,0) -> 0 | P26: =IF(AND('Rent Roll'!AD28="Relet",'Rent Roll'!AC28<>"Relet"),$E$26,0) -> 0 | ... BO26: =IF(AND('Rent Roll'!CC28="Relet",'Rent Roll'!CB28<>"Relet"),$E$26,0) -> 0
A27: ='Rent Roll'!A31 -> 4955 A | B27: ='Rent Roll'!B31 -> Sharing & Caring | C27: ='Rent Roll'!C31 -> 1350 | E27: =('Rent Roll'!N31*'Rent Roll'!Q31+(1-'Rent Roll'!N31)*'Rent Roll'!P31)*'Rent Roll'!C31 -> 20250 | H27: =IF('Rent Roll'!V31="Relet",$E$27,0) -> 0 | I27: =IF(AND('Rent Roll'!W31="Relet",'Rent Roll'!V31<>"Relet"),$E$27,0) -> 0 | J27: =IF(AND('Rent Roll'!X31="Relet",'Rent Roll'!W31<>"Relet"),$E$27,0) -> 0 | K27: =IF(AND('Rent Roll'!Y31="Relet",'Rent Roll'!X31<>"Relet"),$E$27,0) -> 0 | L27: =IF(AND('Rent Roll'!Z31="Relet",'Rent Roll'!Y31<>"Relet"),$E$27,0) -> 0 | M27: =IF(AND('Rent Roll'!AA31="Relet",'Rent Roll'!Z31<>"Relet"),$E$27,0) -> 0 | N27: =IF(AND('Rent Roll'!AB31="Relet",'Rent Roll'!AA31<>"Relet"),$E$27,0) -> 20250 | O27: =IF(AND('Rent Roll'!AC31="Relet",'Rent Roll'!AB31<>"Relet"),$E$27,0) -> 0 | P27: =IF(AND('Rent Roll'!AD31="Relet",'Rent Roll'!AC31<>"Relet"),$E$27,0) -> 0 | ... BO27: =IF(AND('Rent Roll'!CC31="Relet",'Rent Roll'!CB31<>"Relet"),$E$27,0) -> 0
A28: ='Rent Roll'!A34 -> 4955 B | B28: ='Rent Roll'!B34 -> Spoteless Cleaners | C28: ='Rent Roll'!C34 -> 1310 | E28: =('Rent Roll'!N34*'Rent Roll'!Q34+(1-'Rent Roll'!N34)*'Rent Roll'!P34)*'Rent Roll'!C34 -> 19650 | H28: =IF('Rent Roll'!V34="Relet",$E$28,0) -> 0 | I28: =IF(AND('Rent Roll'!W34="Relet",'Rent Roll'!V34<>"Relet"),$E$28,0) -> 0 | J28: =IF(AND('Rent Roll'!X34="Relet",'Rent Roll'!W34<>"Relet"),$E$28,0) -> 0 | K28: =IF(AND('Rent Roll'!Y34="Relet",'Rent Roll'!X34<>"Relet"),$E$28,0) -> 0 | L28: =IF(AND('Rent Roll'!Z34="Relet",'Rent Roll'!Y34<>"Relet"),$E$28,0) -> 0 | M28: =IF(AND('Rent Roll'!AA34="Relet",'Rent Roll'!Z34<>"Relet"),$E$28,0) -> 0 | N28: =IF(AND('Rent Roll'!AB34="Relet",'Rent Roll'!AA34<>"Relet"),$E$28,0) -> 19650 | O28: =IF(AND('Rent Roll'!AC34="Relet",'Rent Roll'!AB34<>"Relet"),$E$28,0) -> 0 | P28: =IF(AND('Rent Roll'!AD34="Relet",'Rent Roll'!AC34<>"Relet"),$E$28,0) -> 0 | ... BO28: =IF(AND('Rent Roll'!CC34="Relet",'Rent Roll'!CB34<>"Relet"),$E$28,0) -> 0
A29: ='Rent Roll'!A37 -> 4955 C | B29: ='Rent Roll'!B37 -> Dawn's Pet Palace | C29: ='Rent Roll'!C37 -> 1880 | E29: =('Rent Roll'!N37*'Rent Roll'!Q37+(1-'Rent Roll'!N37)*'Rent Roll'!P37)*'Rent Roll'!C37 -> 18800 | H29: =IF('Rent Roll'!V37="Relet",$E$29,0) -> 0 | I29: =IF(AND('Rent Roll'!W37="Relet",'Rent Roll'!V37<>"Relet"),$E$29,0) -> 0 | J29: =IF(AND('Rent Roll'!X37="Relet",'Rent Roll'!W37<>"Relet"),$E$29,0) -> 0 | K29: =IF(AND('Rent Roll'!Y37="Relet",'Rent Roll'!X37<>"Relet"),$E$29,0) -> 0 | L29: =IF(AND('Rent Roll'!Z37="Relet",'Rent Roll'!Y37<>"Relet"),$E$29,0) -> 0 | M29: =IF(AND('Rent Roll'!AA37="Relet",'Rent Roll'!Z37<>"Relet"),$E$29,0) -> 0 | N29: =IF(AND('Rent Roll'!AB37="Relet",'Rent Roll'!AA37<>"Relet"),$E$29,0) -> 0 | O29: =IF(AND('Rent Roll'!AC37="Relet",'Rent Roll'!AB37<>"Relet"),$E$29,0) -> 0 | P29: =IF(AND('Rent Roll'!AD37="Relet",'Rent Roll'!AC37<>"Relet"),$E$29,0) -> 0 | ... BO29: =IF(AND('Rent Roll'!CC37="Relet",'Rent Roll'!CB37<>"Relet"),$E$29,0) -> 0
B30: TOTAL TI | C30: =SUM(C18:C29) -> 17880 | E30: =SUM(E18:E29) -> 240000 | H30: =SUM(H18:H29) -> 0 | I30: =SUM(I18:I29) -> 0 | J30: =SUM(J18:J29) -> 0 | K30: =SUM(K18:K29) -> 0 | L30: =SUM(L18:L29) -> 0 | M30: =SUM(M18:M29) -> 56500 | N30: =SUM(N18:N29) -> 98100 | O30: =SUM(O18:O29) -> 0 | ... BO30: =SUM(BO18:BO29) -> 36200
E31: =E30 / C30 -> 13.422819
A32: LEASING COMMISSIONS
A33: # | B33: Suite/Tenant | C33: SF | D33: Relet Month | E33: LC Cost ($) | H33: 1 | I33: 2 | J33: 3 | K33: 4 | L33: 5 | M33: 6 | N33: 7 | O33: 8 | P33: 9 | Q33: 10 | R33: 11 | S33: 12 | T33: 13 | U33: 14 | V33: 15 | W33: 16 | X33: 17 | Y33: 18 | Z33: 19 | AA33: 20 | AB33: 21 | AC33: 22 | AD33: 23 | AE33: 24 | AF33: 25 | AG33: 26 | AH33: 27 | AI33: 28 | AJ33: 29 | AK33: 30 | AL33: 31 | AM33: 32 | AN33: 33 | AO33: 34 | AP33: 35 | AQ33: 36 | AR33: 37 | AS33: 38 | AT33: 39 | AU33: 40 | AV33: 41 | AW33: 42 | AX33: 43 | AY33: 44 | AZ33: 45 | BA33: 46 | BB33: 47 | BC33: 48 | BD33: 49 | BE33: 50 | BF33: 51 | BG33: 52 | BH33: 53 | BI33: 54 | BJ33: 55 | BK33: 56 | BL33: 57 | BM33: 58 | BN33: 59 | BO33: 60
A34: ='Rent Roll'!A4 -> 4949 A1&A2 | B34: ='Rent Roll'!B4 -> Middle East Bakery | C34: ='Rent Roll'!C4 -> 2230 | D34: =IFERROR(MATCH("Relet", 'Rent Roll'!V4:CD4, 0), 0) -> 48 | E34: {=IF(D34=0,0,('Rent Roll'!$N$4*'Rent Roll'!$S$4+(1-'Rent Roll'!$N$4)*'Rent Roll'!$R$4)*INDEX('Rent Roll'!V5:CD5,1,D34)*'Rent Roll'!$C$4*12*('Rent Roll'!$K$4/12))} -> 5482.7577 | H34: =IF(H$33=$D$34,$E$34,0) -> 0 | I34: =IF(I$33=$D$34,$E$34,0) -> 0 | J34: =IF(J$33=$D$34,$E$34,0) -> 0 | K34: =IF(K$33=$D$34,$E$34,0) -> 0 | L34: =IF(L$33=$D$34,$E$34,0) -> 0 | M34: =IF(M$33=$D$34,$E$34,0) -> 0 | N34: =IF(N$33=$D$34,$E$34,0) -> 0 | O34: =IF(O$33=$D$34,$E$34,0) -> 0 | ... BO34: =IF(BO$33=$D$34,$E$34,0) -> 0
A35: ='Rent Roll'!A7 -> 4949 B | B35: ='Rent Roll'!B7 -> VACANT | C35: ='Rent Roll'!C7 -> 910 | D35: =IFERROR(MATCH("Relet",'Rent Roll'!V7:CD7,0),0) -> 6 | E35: {=IF(D35=0,0,('Rent Roll'!$N$7*'Rent Roll'!$S$7+(1-'Rent Roll'!$N$7)*'Rent Roll'!$R$7)*INDEX('Rent Roll'!V8:CD8,1,D35)*'Rent Roll'!$C$7*12*('Rent Roll'!$K$7/12))} -> 3276 | H35: =IF(H$33=$D$35,$E$35,0) -> 0 | I35: =IF(I$33=$D$35,$E$35,0) -> 0 | J35: =IF(J$33=$D$35,$E$35,0) -> 0 | K35: =IF(K$33=$D$35,$E$35,0) -> 0 | L35: =IF(L$33=$D$35,$E$35,0) -> 0 | M35: =IF(M$33=$D$35,$E$35,0) -> 3276 | N35: =IF(N$33=$D$35,$E$35,0) -> 0 | O35: =IF(O$33=$D$35,$E$35,0) -> 0 | ... BO35: =IF(BO$33=$D$35,$E$35,0) -> 0
A36: ='Rent Roll'!A10 -> 4949 C | B36: ='Rent Roll'!B10 -> Circle Pizza | C36: ='Rent Roll'!C10 -> 3620 | D36: =IFERROR(MATCH("Relet",'Rent Roll'!V10:CD10,0),0) -> 60 | E36: {=IF(D36=0,0,('Rent Roll'!$N$10*'Rent Roll'!$S$10+(1-'Rent Roll'!$N$10)*'Rent Roll'!$R$10)*INDEX('Rent Roll'!V11:CD11,1,D36)*'Rent Roll'!$C$10*12*('Rent Roll'!$K$10/12))} -> 9167.2693 | H36: =IF(H$33=$D$36,$E$36,0) -> 0 | I36: =IF(I$33=$D$36,$E$36,0) -> 0 | J36: =IF(J$33=$D$36,$E$36,0) -> 0 | K36: =IF(K$33=$D$36,$E$36,0) -> 0 | L36: =IF(L$33=$D$36,$E$36,0) -> 0 | M36: =IF(M$33=$D$36,$E$36,0) -> 0 | N36: =IF(N$33=$D$36,$E$36,0) -> 0 | O36: =IF(O$33=$D$36,$E$36,0) -> 0 | ... BO36: =IF(BO$33=$D$36,$E$36,0) -> 9167.2693
A37: ='Rent Roll'!A13 -> 4949 D&E | B37: ='Rent Roll'!B13 -> Silver Sake | C37: ='Rent Roll'!C13 -> 1990 | D37: =IFERROR(MATCH("Relet",'Rent Roll'!V13:CD13,0),0) -> 7 | E37: =IF(D37=0,0,('Rent Roll'!$N$13*'Rent Roll'!$S$13+(1-'Rent Roll'!$N$13)*'Rent Roll'!$R$13)*INDEX('Rent Roll'!V14:CD14,1,D37)*'Rent Roll'!$C$13*12*('Rent Roll'!$K$13/12)) -> 5373 | H37: =IF(H$33=$D$37,$E$37,0) -> 0 | I37: =IF(I$33=$D$37,$E$37,0) -> 0 | J37: =IF(J$33=$D$37,$E$37,0) -> 0 | K37: =IF(K$33=$D$37,$E$37,0) -> 0 | L37: =IF(L$33=$D$37,$E$37,0) -> 0 | M37: =IF(M$33=$D$37,$E$37,0) -> 0 | N37: =IF(N$33=$D$37,$E$37,0) -> 5373 | O37: =IF(O$33=$D$37,$E$37,0) -> 0 | ... BO37: =IF(BO$33=$D$37,$E$37,0) -> 0
A38: ='Rent Roll'!A16 -> 4949 F | B38: ='Rent Roll'!B16 -> Waiel Merza | C38: ='Rent Roll'!C16 -> 810 | D38: =IFERROR(MATCH("Relet",'Rent Roll'!V16:CD16,0),0) -> 42 | E38: {=IF(D38=0,0,('Rent Roll'!$N$16*'Rent Roll'!$S$16+(1-'Rent Roll'!$N$16)*'Rent Roll'!$R$16)*INDEX('Rent Roll'!V17:CD17,1,D38)*'Rent Roll'!$C$16*12*('Rent Roll'!$L$16/12))} -> 1194.897 | H38: =IF(H$33=$D$38,$E$38,0) -> 0 | I38: =IF(I$33=$D$38,$E$38,0) -> 0 | J38: =IF(J$33=$D$38,$E$38,0) -> 0 | K38: =IF(K$33=$D$38,$E$38,0) -> 0 | L38: =IF(L$33=$D$38,$E$38,0) -> 0 | M38: =IF(M$33=$D$38,$E$38,0) -> 0 | N38: =IF(N$33=$D$38,$E$38,0) -> 0 | O38: =IF(O$33=$D$38,$E$38,0) -> 0 | ... BO38: =IF(BO$33=$D$38,$E$38,0) -> 0
A39: ='Rent Roll'!A19 -> 4949 G | B39: ='Rent Roll'!B19 -> Cigarettes & Gifts | C39: ='Rent Roll'!C19 -> 810 | D39: =IFERROR(MATCH("Relet",'Rent Roll'!V19:CD19,0),0) -> 7 | E39: =IF(D39=0,0,('Rent Roll'!$N$19*'Rent Roll'!$S$19+(1-'Rent Roll'!$N$19)*'Rent Roll'!$R$19)*INDEX('Rent Roll'!V20:CD20,1,D39)*'Rent Roll'!$C$19*12*('Rent Roll'!$K$19/12)) -> 1822.5 | H39: =IF(H$33=$D$39,$E$39,0) -> 0 | I39: =IF(I$33=$D$39,$E$39,0) -> 0 | J39: =IF(J$33=$D$39,$E$39,0) -> 0 | K39: =IF(K$33=$D$39,$E$39,0) -> 0 | L39: =IF(L$33=$D$39,$E$39,0) -> 0 | M39: =IF(M$33=$D$39,$E$39,0) -> 0 | N39: =IF(N$33=$D$39,$E$39,0) -> 1822.5 | O39: =IF(O$33=$D$39,$E$39,0) -> 0 | ... BO39: =IF(BO$33=$D$39,$E$39,0) -> 0
A40: ='Rent Roll'!A22 -> 4949 H | B40: ='Rent Roll'!B22 -> Brittany Hair & Nails | C40: ='Rent Roll'!C22 -> 810 | D40: =IFERROR(MATCH("Relet",'Rent Roll'!V22:CD22,0),0) -> 7 | E40: =IF(D40=0,0,('Rent Roll'!$N$22*'Rent Roll'!$S$22+(1-'Rent Roll'!$N$22)*'Rent Roll'!$R$22)*INDEX('Rent Roll'!V23:CD23,1,D40)*'Rent Roll'!$C$22*12*('Rent Roll'!$K$22/12)) -> 1822.5 | H40: =IF(H$33=$D$40,$E$40,0) -> 0 | I40: =IF(I$33=$D$40,$E$40,0) -> 0 | J40: =IF(J$33=$D$40,$E$40,0) -> 0 | K40: =IF(K$33=$D$40,$E$40,0) -> 0 | L40: =IF(L$33=$D$40,$E$40,0) -> 0 | M40: =IF(M$33=$D$40,$E$40,0) -> 0 | N40: =IF(N$33=$D$40,$E$40,0) -> 1822.5 | O40: =IF(O$33=$D$40,$E$40,0) -> 0 | ... BO40: =IF(BO$33=$D$40,$E$40,0) -> 0
A41: ='Rent Roll'!A25 -> 4949 I | B41: ='Rent Roll'!B25 -> Madeville Hair Salon | C41: ='Rent Roll'!C25 -> 810 | D41: =IFERROR(MATCH("Relet",'Rent Roll'!V25:CD25,0),0) -> 7 | E41: =IF(D41=0,0,('Rent Roll'!$N$25*'Rent Roll'!$S$25+(1-'Rent Roll'!$N$25)*'Rent Roll'!$R$25)*INDEX('Rent Roll'!V26:CD26,1,D41)*'Rent Roll'!$C$25*12*('Rent Roll'!$K$25/12)) -> 2187 | H41: =IF(H$33=$D$41,$E$41,0) -> 0 | I41: =IF(I$33=$D$41,$E$41,0) -> 0 | J41: =IF(J$33=$D$41,$E$41,0) -> 0 | K41: =IF(K$33=$D$41,$E$41,0) -> 0 | L41: =IF(L$33=$D$41,$E$41,0) -> 0 | M41: =IF(M$33=$D$41,$E$41,0) -> 0 | N41: =IF(N$33=$D$41,$E$41,0) -> 2187 | O41: =IF(O$33=$D$41,$E$41,0) -> 0 | ... BO41: =IF(BO$33=$D$41,$E$41,0) -> 0
A42: ='Rent Roll'!A28 -> 4949 J | B42: ='Rent Roll'!B28 -> VACANT | C42: ='Rent Roll'!C28 -> 1350 | D42: =IFERROR(MATCH("Relet",'Rent Roll'!V28:CD28,0),0) -> 6 | E42: =IF(D42=0,0,('Rent Roll'!$N$28*'Rent Roll'!$S$28+(1-'Rent Roll'!$N$28)*'Rent Roll'!$R$28)*INDEX('Rent Roll'!V29:CD29,1,D42)*'Rent Roll'!$C$28*12*('Rent Roll'!$K$28/12)) -> 4860 | H42: =IF(H$33=$D$42,$E$42,0) -> 0 | I42: =IF(I$33=$D$42,$E$42,0) -> 0 | J42: =IF(J$33=$D$42,$E$42,0) -> 0 | K42: =IF(K$33=$D$42,$E$42,0) -> 0 | L42: =IF(L$33=$D$42,$E$42,0) -> 0 | M42: =IF(M$33=$D$42,$E$42,0) -> 4860 | N42: =IF(N$33=$D$42,$E$42,0) -> 0 | O42: =IF(O$33=$D$42,$E$42,0) -> 0 | ... BO42: =IF(BO$33=$D$42,$E$42,0) -> 0
A43: ='Rent Roll'!A31 -> 4955 A | B43: ='Rent Roll'!B31 -> Sharing & Caring | C43: ='Rent Roll'!C31 -> 1350 | D43: =IFERROR(MATCH("Relet",'Rent Roll'!V31:CD31,0),0) -> 7 | E43: =IF(D43=0,0,('Rent Roll'!$N$31*'Rent Roll'!$S$31+(1-'Rent Roll'!$N$31)*'Rent Roll'!$R$31)*INDEX('Rent Roll'!V32:CD32,1,D43)*'Rent Roll'!$C$31*12*('Rent Roll'!$K$31/12)) -> 3645 | H43: =IF(H$33=$D$43,$E$43,0) -> 0 | I43: =IF(I$33=$D$43,$E$43,0) -> 0 | J43: =IF(J$33=$D$43,$E$43,0) -> 0 | K43: =IF(K$33=$D$43,$E$43,0) -> 0 | L43: =IF(L$33=$D$43,$E$43,0) -> 0 | M43: =IF(M$33=$D$43,$E$43,0) -> 0 | N43: =IF(N$33=$D$43,$E$43,0) -> 3645 | O43: =IF(O$33=$D$43,$E$43,0) -> 0 | ... BO43: =IF(BO$33=$D$43,$E$43,0) -> 0
A44: ='Rent Roll'!A34 -> 4955 B | B44: ='Rent Roll'!B34 -> Spoteless Cleaners | C44: ='Rent Roll'!C34 -> 1310 | D44: =IFERROR(MATCH("Relet",'Rent Roll'!V34:CD34,0),0) -> 7 | E44: =IF(D44=0,0,('Rent Roll'!$N$34*'Rent Roll'!$S$34+(1-'Rent Roll'!$N$34)*'Rent Roll'!$R$34)*INDEX('Rent Roll'!V35:CD35,1,D44)*'Rent Roll'!$C$34*12*('Rent Roll'!$K$34/12)) -> 3537 | H44: =IF(H$33=$D$44,$E$44,0) -> 0 | I44: =IF(I$33=$D$44,$E$44,0) -> 0 | J44: =IF(J$33=$D$44,$E$44,0) -> 0 | K44: =IF(K$33=$D$44,$E$44,0) -> 0 | L44: =IF(L$33=$D$44,$E$44,0) -> 0 | M44: =IF(M$33=$D$44,$E$44,0) -> 0 | N44: =IF(N$33=$D$44,$E$44,0) -> 3537 | O44: =IF(O$33=$D$44,$E$44,0) -> 0 | ... BO44: =IF(BO$33=$D$44,$E$44,0) -> 0
A45: ='Rent Roll'!A37 -> 4955 C | B45: ='Rent Roll'!B37 -> Dawn's Pet Palace | C45: ='Rent Roll'!C37 -> 1880 | D45: =IFERROR(MATCH("Relet",'Rent Roll'!V37:CD37,0),0) -> 37 | E45: =IF(D45=0,0,('Rent Roll'!$N$37*'Rent Roll'!$S$37+(1-'Rent Roll'!$N$37)*'Rent Roll'!$R$37)*INDEX('Rent Roll'!V38:CD38,1,D45)*'Rent Roll'!$C$37*12*('Rent Roll'!$K$37/12)) -> 4622.2352 | H45: =IF(H$33=$D$45,$E$45,0) -> 0 | I45: =IF(I$33=$D$45,$E$45,0) -> 0 | J45: =IF(J$33=$D$45,$E$45,0) -> 0 | K45: =IF(K$33=$D$45,$E$45,0) -> 0 | L45: =IF(L$33=$D$45,$E$45,0) -> 0 | M45: =IF(M$33=$D$45,$E$45,0) -> 0 | N45: =IF(N$33=$D$45,$E$45,0) -> 0 | O45: =IF(O$33=$D$45,$E$45,0) -> 0 | ... BO45: =IF(BO$33=$D$45,$E$45,0) -> 0
B46: TOTAL LC | H46: =SUM(H34:H45) -> 0 | I46: =SUM(I34:I45) -> 0 | J46: =SUM(J34:J45) -> 0 | K46: =SUM(K34:K45) -> 0 | L46: =SUM(L34:L45) -> 0 | M46: =SUM(M34:M45) -> 8136 | N46: =SUM(N34:N45) -> 18387 | O46: =SUM(O34:O45) -> 0 | ... BO46: =SUM(BO34:BO45) -> 9167.2693
B48: TOTAL CAPEX + TI + LC | H48: =H13+H30+H46 -> 25000 | I48: =I13+I30+I46 -> 25000 | J48: =J13+J30+J46 -> 25000 | K48: =K13+K30+K46 -> 25000 | L48: =L13+L30+L46 -> 25000 | M48: =M13+M30+M46 -> 89636 | N48: =N13+N30+N46 -> 116487 | O48: =O13+O30+O46 -> 0 | ... BO48: =BO13+BO30+BO46 -> 45367.269

Sheet Rent Roll
A1: RENT ROLL & LEASE-UP SCHEDULE
V2: 1 | W2: 2 | X2: 3 | Y2: 4 | Z2: 5 | AA2: 6 | AB2: 7 | AC2: 8 | AD2: 9 | AE2: 10 | AF2: 11 | AG2: 12 | AH2: 13 | AI2: 14 | AJ2: 15 | AK2: 16 | AL2: 17 | AM2: 18 | AN2: 19 | AO2: 20 | AP2: 21 | AQ2: 22 | AR2: 23 | AS2: 24 | AT2: 25 | AU2: 26 | AV2: 27 | AW2: 28 | AX2: 29 | AY2: 30 | AZ2: 31 | BA2: 32 | BB2: 33 | BC2: 34 | BD2: 35 | BE2: 36 | BF2: 37 | BG2: 38 | BH2: 39 | BI2: 40 | BJ2: 41 | BK2: 42 | BL2: 43 | BM2: 44 | BN2: 45 | BO2: 46 | BP2: 47 | BQ2: 48 | BR2: 49 | BS2: 50 | BT2: 51 | BU2: 52 | BV2: 53 | BW2: 54 | BX2: 55 | BY2: 56 | BZ2: 57 | CA2: 58 | CB2: 59 | CC2: 60 | CD2: 61 | CE2: 62 | CF2: 63 | CG2: 64 | CH2: 65 | CI2: 66 | CJ2: 67 | CK2: 68 | CL2: 69 | CM2: 70 | CN2: 71 | CO2: 72 | CP2: 73 | CQ2: 74 | CR2: 75 | CS2: 76 | CT2: 77 | CU2: 78 | CV2: 79 | CW2: 80 | CX2: 81 | CY2: 82 | CZ2: 83 | DA2: 84 | DB2: 85 | DC2: 86 | DD2: 87 | DE2: 88 | DF2: 89 | DG2: 90 | DH2: 91 | DI2: 92 | DJ2: 93 | DK2: 94 | DL2: 95 | DM2: 96 | DN2: 97 | DO2: 98 | DP2: 99 | DQ2: 100 | DR2: 101 | DS2: 102 | DT2: 103 | DU2: 104 | DV2: 105 | DW2: 106 | DX2: 107 | DY2: 108 | DZ2: 109 | EA2: 110 | EB2: 111 | EC2: 112 | ED2: 113 | EE2: 114 | EF2: 115 | EG2: 116 | EH2: 117 | EI2: 118 | EJ2: 119 | EK2: 120
A3: Suite | B3: Tenant | C3: SF | D3: % GLA | E3: Lease Type | F3: Base Rent ($/SF/mo) | G3: Escalation % | H3: Lease Start | I3: Lease End | J3: Market Rent | K3: New Term | L3: Renewal Term | M3: New Lease Esc % | N3: Renewal Prob % | O3: Downtime (mo) | P3: TI New ($/SF) | Q3: TI Renewal ($/SF) | R3: LC New % | S3: LC Renewal % | T3: NNN Conv? (Y/N) | U3: Initial Lease-Up Month | V3: Month →
A4: ='OM Rent Roll'!A5 -> 4949 A1&A2 | B4: ='OM Rent Roll'!B5 -> Middle East Bakery | C4: ='OM Rent Roll'!C5 -> 2230 | D4: =C4/NRA -> 0.12472036 | E4: ='OM Rent Roll'!D5 -> NNN | F4: ='OM Rent Roll'!G5 -> 1.0304933 | G4: ='OM Rent Roll'!H5 -> 0.019538771 | H4: =IF('OM Rent Roll'!E5=0,"",'OM Rent Roll'!E5) -> 45444 | I4: =IF('OM Rent Roll'!F5=0,"",'OM Rent Roll'!F5) -> 47392 | J4: 1 | K4: 60 | L4: 36 | M4: =Rent_Growth -> 0.03 | N4: 0.75 | O4: 6 | P4: 25 | Q4: 5 | R4: 0.06 | S4: 0.03 | T4: N | U4: 0 | V4: =IF(OR($I$4="",$I$4=0),IF(V$2<$U$4,"Vacant","Relet"),IF(ISTEXT($I$4),IF($U$4>0,IF(V$2<$U$4,"Downtime","Relet"),IF(V$2<=$O$4,"Downtime","Relet")),IF($I$4<=Close_Date,IF(V$2<=$O$4,"Downtime","Relet"),IF(V$2<=DATEDIF(Close_Date,$I$4,"M"),"In-Term",IF(V$2<=DATEDIF(Close_Date,$I$4,"M")+$O$4,"Downtime","Relet"))))) -> In-Term | W4: =IF(OR($I$4="",$I$4=0),IF(W$2<$U$4,"Vacant","Relet"),IF(ISTEXT($I$4),IF($U$4>0,IF(W$2<$U$4,"Downtime","Relet"),IF(W$2<=$O$4,"Downtime","Relet")),IF($I$4<=Close_Date,IF(W$2<=$O$4,"Downtime","Relet"),IF(W$2<=DATEDIF(Close_Date,$I$4,"M"),"In-Term",IF(W$2<=DATEDIF(Close_Date,$I$4,"M")+$O$4,"Downtime","Relet"))))) -> In-Term | X4: =IF(OR($I$4="",$I$4=0),IF(X$2<$U$4,"Vacant","Relet"),IF(ISTEXT($I$4),IF($U$4>0,IF(X$2<$U$4,"Downtime","Relet"),IF(X$2<=$O$4,"Downtime","Relet")),IF($I$4<=Close_Date,IF(X$2<=$O$4,"Downtime","Relet"),IF(X$2<=DATEDIF(Close_Date,$I$4,"M"),"In-Term",IF(X$2<=DATEDIF(Close_Date,$I$4,"M")+$O$4,"Downtime","Relet"))))) -> In-Term | Y4: =IF(OR($I$4="",$I$4=0),IF(Y$2<$U$4,"Vacant","Relet"),IF(ISTEXT($I$4),IF($U$4>0,IF(Y$2<$U$4,"Downtime","Relet"),IF(Y$2<=$O$4,"Downtime","Relet")),IF($I$4<=Close_Date,IF(Y$2<=$O$4,"Downtime","Relet"),IF(Y$2<=DATEDIF(Close_Date,$I$4,"M"),"In-Term",IF(Y$2<=DATEDIF(Close_Date,$I$4,"M")+$O$4,"Downtime","Relet"))))) -> In-Term | Z4: =IF(OR($I$4="",$I$4=0),IF(Z$2<$U$4,"Vacant","Relet"),IF(ISTEXT($I$4),IF($U$4>0,IF(Z$2<$U$4,"Downtime","Relet"),IF(Z$2<=$O$4,"Downtime","Relet")),IF($I$4<=Close_Date,IF(Z$2<=$O$4,"Downtime","Relet"),IF(Z$2<=DATEDIF(Close_Date,$I$4,"M"),"In-Term",IF(Z$2<=DATEDIF(Close_Date,$I$4,"M")+$O$4,"Downtime","Relet"))))) -> In-Term | AA4: =IF(OR($I$4="",$I$4=0),IF(AA$2<$U$4,"Vacant","Relet"),IF(ISTEXT($I$4),IF($U$4>0,IF(AA$2<$U$4,"Downtime","Relet"),IF(AA$2<=$O$4,"Downtime","Relet")),IF($I$4<=Close_Date,IF(AA$2<=$O$4,"Downtime","Relet"),IF(AA$2<=DATEDIF(Close_Date,$I$4,"M"),"In-Term",IF(AA$2<=DATEDIF(Close_Date,$I$4,"M")+$O$4,"Downtime","Relet"))))) -> In-Term | AB4: =IF(OR($I$4="",$I$4=0),IF(AB$2<$U$4,"Vacant","Relet"),IF(ISTEXT($I$4),IF($U$4>0,IF(AB$2<$U$4,"Downtime","Relet"),IF(AB$2<=$O$4,"Downtime","Relet")),IF($I$4<=Close_Date,IF(AB$2<=$O$4,"Downtime","Relet"),IF(AB$2<=DATEDIF(Close_Date,$I$4,"M"),"In-Term",IF(AB$2<=DATEDIF(Close_Date,$I$4,"M")+$O$4,"Downtime","Relet"))))) -> In-Term | AC4: =IF(OR($I$4="",$I$4=0),IF(AC$2<$U$4,"Vacant","Relet"),IF(ISTEXT($I$4),IF($U$4>0,IF(AC$2<$U$4,"Downtime","Relet"),IF(AC$2<=$O$4,"Downtime","Relet")),IF($I$4<=Close_Date,IF(AC$2<=$O$4,"Downtime","Relet"),IF(AC$2<=DATEDIF(Close_Date,$I$4,"M"),"In-Term",IF(AC$2<=DATEDIF(Close_Date,$I$4,"M")+$O$4,"Downtime","Relet"))))) -> In-Term | ... CD4: =IF(OR($I$4="",$I$4=0),IF(CD$2<$U$4,"Vacant","Relet"),IF(ISTEXT($I$4),IF($U$4>0,IF(CD$2<$U$4,"Downtime","Relet"),IF(CD$2<=$O$4,"Downtime","Relet")),IF($I$4<=Close_Date,IF(CD$2<=$O$4,"Downtime","Relet"),IF(CD$2<=DATEDIF(Close_Date,$I$4,"M"),"In-Term",IF(CD$2<=DATEDIF(Close_Date,$I$4,"M")+$O$4,"Downtime","Relet"))))) -> Relet
B5: Rate | V5: =IF(V4="Vacant",0,IF(V4="In-Term",$F$4*(1+$G$4)^(INT((V$2-1)/12)),IF(AND(V4="Downtime",ISTEXT($I$4)),$F$4,$J$4*(1+$M$4)^(INT((V$2-1)/12))))) -> 1.0304933 | W5: =IF(W4="Vacant",0,IF(W4="In-Term",$F$4*(1+$G$4)^(INT((W$2-1)/12)),IF(AND(W4="Downtime",ISTEXT($I$4)),$F$4,$J$4*(1+$M$4)^(INT((W$2-1)/12))))) -> 1.0304933 | X5: =IF(X4="Vacant",0,IF(X4="In-Term",$F$4*(1+$G$4)^(INT((X$2-1)/12)),IF(AND(X4="Downtime",ISTEXT($I$4)),$F$4,$J$4*(1+$M$4)^(INT((X$2-1)/12))))) -> 1.0304933 | Y5: =IF(Y4="Vacant",0,IF(Y4="In-Term",$F$4*(1+$G$4)^(INT((Y$2-1)/12)),IF(AND(Y4="Downtime",ISTEXT($I$4)),$F$4,$J$4*(1+$M$4)^(INT((Y$2-1)/12))))) -> 1.0304933 | Z5: =IF(Z4="Vacant",0,IF(Z4="In-Term",$F$4*(1+$G$4)^(INT((Z$2-1)/12)),IF(AND(Z4="Downtime",ISTEXT($I$4)),$F$4,$J$4*(1+$M$4)^(INT((Z$2-1)/12))))) -> 1.0304933 | AA5: =IF(AA4="Vacant",0,IF(AA4="In-Term",$F$4*(1+$G$4)^(INT((AA$2-1)/12)),IF(AND(AA4="Downtime",ISTEXT($I$4)),$F$4,$J$4*(1+$M$4)^(INT((AA$2-1)/12))))) -> 1.0304933 | AB5: =IF(AB4="Vacant",0,IF(AB4="In-Term",$F$4*(1+$G$4)^(INT((AB$2-1)/12)),IF(AND(AB4="Downtime",ISTEXT($I$4)),$F$4,$J$4*(1+$M$4)^(INT((AB$2-1)/12))))) -> 1.0304933 | AC5: =IF(AC4="Vacant",0,IF(AC4="In-Term",$F$4*(1+$G$4)^(INT((AC$2-1)/12)),IF(AND(AC4="Downtime",ISTEXT($I$4)),$F$4,$J$4*(1+$M$4)^(INT((AC$2-1)/12))))) -> 1.0304933 | ... CD5: =IF(CD4="Vacant",0,IF(CD4="In-Term",$F$4*(1+$G$4)^(INT((CD$2-1)/12)),IF(AND(CD4="Downtime",ISTEXT($I$4)),$F$4,$J$4*(1+$M$4)^(INT((CD$2-1)/12))))) -> 1.1592741
B6: Eff$ | V6: =IF(V4="Vacant",0,IF(V4="Downtime",$N$4*V5*$C$4,V5*$C$4)) -> 2298 | W6: =IF(W4="Vacant",0,IF(W4="Downtime",$N$4*W5*$C$4,W5*$C$4)) -> 2298 | X6: =IF(X4="Vacant",0,IF(X4="Downtime",$N$4*X5*$C$4,X5*$C$4)) -> 2298 | Y6: =IF(Y4="Vacant",0,IF(Y4="Downtime",$N$4*Y5*$C$4,Y5*$C$4)) -> 2298 | Z6: =IF(Z4="Vacant",0,IF(Z4="Downtime",$N$4*Z5*$C$4,Z5*$C$4)) -> 2298 | AA6: =IF(AA4="Vacant",0,IF(AA4="Downtime",$N$4*AA5*$C$4,AA5*$C$4)) -> 2298 | AB6: =IF(AB4="Vacant",0,IF(AB4="Downtime",$N$4*AB5*$C$4,AB5*$C$4)) -> 2298 | AC6: =IF(AC4="Vacant",0,IF(AC4="Downtime",$N$4*AC5*$C$4,AC5*$C$4)) -> 2298 | ... CD6: =IF(CD4="Vacant",0,IF(CD4="Downtime",$N$4*CD5*$C$4,CD5*$C$4)) -> 2585.1812
A7: ='OM Rent Roll'!A6 -> 4949 B | B7: ='OM Rent Roll'!B6 -> VACANT | C7: ='OM Rent Roll'!C6 -> 910 | D7: =C7/NRA -> 0.050894855 | E7: ='OM Rent Roll'!D6 -> NNN | F7: ='OM Rent Roll'!G6 -> 0.9 | G7: ='OM Rent Roll'!H6 -> 0.00043150431 | H7: =IF('OM Rent Roll'!E6=0,"",'OM Rent Roll'!E6) | I7: =IF('OM Rent Roll'!F6=0,"",'OM Rent Roll'!F6) | J7: 1 | K7: 60 | L7: 36 | M7: =Rent_Growth -> 0.03 | N7: 0.75 | O7: 6 | P7: 25 | Q7: 25 | R7: 0.06 | S7: 0.06 | T7: N | U7: 6 | V7: =IF(OR($I$7="",$I$7=0),IF(V$2<$U$7,"Vacant","Relet"),IF(ISTEXT($I$7),IF($U$7>0,IF(V$2<$U$7,"Downtime","Relet"),IF(V$2<=$O$7,"Downtime","Relet")),IF($I$7<=Close_Date,IF(V$2<=$O$7,"Downtime","Relet"),IF(V$2<=DATEDIF(Close_Date,$I$7,"M"),"In-Term",IF(V$2<=DATEDIF(Close_Date,$I$7,"M")+$O$7,"Downtime","Relet"))))) -> Vacant | W7: =IF(OR($I$7="",$I$7=0),IF(W$2<$U$7,"Vacant","Relet"),IF(ISTEXT($I$7),IF($U$7>0,IF(W$2<$U$7,"Downtime","Relet"),IF(W$2<=$O$7,"Downtime","Relet")),IF($I$7<=Close_Date,IF(W$2<=$O$7,"Downtime","Relet"),IF(W$2<=DATEDIF(Close_Date,$I$7,"M"),"In-Term",IF(W$2<=DATEDIF(Close_Date,$I$7,"M")+$O$7,"Downtime","Relet"))))) -> Vacant | X7: =IF(OR($I$7="",$I$7=0),IF(X$2<$U$7,"Vacant","Relet"),IF(ISTEXT($I$7),IF($U$7>0,IF(X$2<$U$7,"Downtime","Relet"),IF(X$2<=$O$7,"Downtime","Relet")),IF($I$7<=Close_Date,IF(X$2<=$O$7,"Downtime","Relet"),IF(X$2<=DATEDIF(Close_Date,$I$7,"M"),"In-Term",IF(X$2<=DATEDIF(Close_Date,$I$7,"M")+$O$7,"Downtime","Relet"))))) -> Vacant | Y7: =IF(OR($I$7="",$I$7=0),IF(Y$2<$U$7,"Vacant","Relet"),IF(ISTEXT($I$7),IF($U$7>0,IF(Y$2<$U$7,"Downtime","Relet"),IF(Y$2<=$O$7,"Downtime","Relet")),IF($I$7<=Close_Date,IF(Y$2<=$O$7,"Downtime","Relet"),IF(Y$2<=DATEDIF(Close_Date,$I$7,"M"),"In-Term",IF(Y$2<=DATEDIF(Close_Date,$I$7,"M")+$O$7,"Downtime","Relet"))))) -> Vacant | Z7: =IF(OR($I$7="",$I$7=0),IF(Z$2<$U$7,"Vacant","Relet"),IF(ISTEXT($I$7),IF($U$7>0,IF(Z$2<$U$7,"Downtime","Relet"),IF(Z$2<=$O$7,"Downtime","Relet")),IF($I$7<=Close_Date,IF(Z$2<=$O$7,"Downtime","Relet"),IF(Z$2<=DATEDIF(Close_Date,$I$7,"M"),"In-Term",IF(Z$2<=DATEDIF(Close_Date,$I$7,"M")+$O$7,"Downtime","Relet"))))) -> Vacant | AA7: =IF(OR($I$7="",$I$7=0),IF(AA$2<$U$7,"Vacant","Relet"),IF(ISTEXT($I$7),IF($U$7>0,IF(AA$2<$U$7,"Downtime","Relet"),IF(AA$2<=$O$7,"Downtime","Relet")),IF($I$7<=Close_Date,IF(AA$2<=$O$7,"Downtime","Relet"),IF(AA$2<=DATEDIF(Close_Date,$I$7,"M"),"In-Term",IF(AA$2<=DATEDIF(Close_Date,$I$7,"M")+$O$7,"Downtime","Relet"))))) -> Relet | AB7: =IF(OR($I$7="",$I$7=0),IF(AB$2<$U$7,"Vacant","Relet"),IF(ISTEXT($I$7),IF($U$7>0,IF(AB$2<$U$7,"Downtime","Relet"),IF(AB$2<=$O$7,"Downtime","Relet")),IF($I$7<=Close_Date,IF(AB$2<=$O$7,"Downtime","Relet"),IF(AB$2<=DATEDIF(Close_Date,$I$7,"M"),"In-Term",IF(AB$2<=DATEDIF(Close_Date,$I$7,"M")+$O$7,"Downtime","Relet"))))) -> Relet | AC7: =IF(OR($I$7="",$I$7=0),IF(AC$2<$U$7,"Vacant","Relet"),IF(ISTEXT($I$7),IF($U$7>0,IF(AC$2<$U$7,"Downtime","Relet"),IF(AC$2<=$O$7,"Downtime","Relet")),IF($I$7<=Close_Date,IF(AC$2<=$O$7,"Downtime","Relet"),IF(AC$2<=DATEDIF(Close_Date,$I$7,"M"),"In-Term",IF(AC$2<=DATEDIF(Close_Date,$I$7,"M")+$O$7,"Downtime","Relet"))))) -> Relet | ... CD7: =IF(OR($I$7="",$I$7=0),IF(CD$2<$U$7,"Vacant","Relet"),IF(ISTEXT($I$7),IF($U$7>0,IF(CD$2<$U$7,"Downtime","Relet"),IF(CD$2<=$O$7,"Downtime","Relet")),IF($I$7<=Close_Date,IF(CD$2<=$O$7,"Downtime","Relet"),IF(CD$2<=DATEDIF(Close_Date,$I$7,"M"),"In-Term",IF(CD$2<=DATEDIF(Close_Date,$I$7,"M")+$O$7,"Downtime","Relet"))))) -> Relet
B8: Rate | V8: =IF(V7="Vacant",0,IF(V7="In-Term",$F$7*(1+$G$7)^(INT((V$2-1)/12)),IF(AND(V7="Downtime",ISTEXT($I$7)),$F$7,$J$7*(1+$M$7)^(INT((V$2-1)/12))))) -> 0 | W8: =IF(W7="Vacant",0,IF(W7="In-Term",$F$7*(1+$G$7)^(INT((W$2-1)/12)),IF(AND(W7="Downtime",ISTEXT($I$7)),$F$7,$J$7*(1+$M$7)^(INT((W$2-1)/12))))) -> 0 | X8: =IF(X7="Vacant",0,IF(X7="In-Term",$F$7*(1+$G$7)^(INT((X$2-1)/12)),IF(AND(X7="Downtime",ISTEXT($I$7)),$F$7,$J$7*(1+$M$7)^(INT((X$2-1)/12))))) -> 0 | Y8: =IF(Y7="Vacant",0,IF(Y7="In-Term",$F$7*(1+$G$7)^(INT((Y$2-1)/12)),IF(AND(Y7="Downtime",ISTEXT($I$7)),$F$7,$J$7*(1+$M$7)^(INT((Y$2-1)/12))))) -> 0 | Z8: =IF(Z7="Vacant",0,IF(Z7="In-Term",$F$7*(1+$G$7)^(INT((Z$2-1)/12)),IF(AND(Z7="Downtime",ISTEXT($I$7)),$F$7,$J$7*(1+$M$7)^(INT((Z$2-1)/12))))) -> 0 | AA8: =IF(AA7="Vacant",0,IF(AA7="In-Term",$F$7*(1+$G$7)^(INT((AA$2-1)/12)),IF(AND(AA7="Downtime",ISTEXT($I$7)),$F$7,$J$7*(1+$M$7)^(INT((AA$2-1)/12))))) -> 1 | AB8: =IF(AB7="Vacant",0,IF(AB7="In-Term",$F$7*(1+$G$7)^(INT((AB$2-1)/12)),IF(AND(AB7="Downtime",ISTEXT($I$7)),$F$7,$J$7*(1+$M$7)^(INT((AB$2-1)/12))))) -> 1 | AC8: =IF(AC7="Vacant",0,IF(AC7="In-Term",$F$7*(1+$G$7)^(INT((AC$2-1)/12)),IF(AND(AC7="Downtime",ISTEXT($I$7)),$F$7,$J$7*(1+$M$7)^(INT((AC$2-1)/12))))) -> 1 | ... CD8: =IF(CD7="Vacant",0,IF(CD7="In-Term",$F$7*(1+$G$7)^(INT((CD$2-1)/12)),IF(AND(CD7="Downtime",ISTEXT($I$7)),$F$7,$J$7*(1+$M$7)^(INT((CD$2-1)/12))))) -> 1.1592741
B9: Eff$ | V9: =IF(V7="Vacant",0,IF(V7="Downtime",$N$7*V8*$C$7,V8*$C$7)) -> 0 | W9: =IF(W7="Vacant",0,IF(W7="Downtime",$N$7*W8*$C$7,W8*$C$7)) -> 0 | X9: =IF(X7="Vacant",0,IF(X7="Downtime",$N$7*X8*$C$7,X8*$C$7)) -> 0 | Y9: =IF(Y7="Vacant",0,IF(Y7="Downtime",$N$7*Y8*$C$7,Y8*$C$7)) -> 0 | Z9: =IF(Z7="Vacant",0,IF(Z7="Downtime",$N$7*Z8*$C$7,Z8*$C$7)) -> 0 | AA9: =IF(AA7="Vacant",0,IF(AA7="Downtime",$N$7*AA8*$C$7,AA8*$C$7)) -> 910 | AB9: =IF(AB7="Vacant",0,IF(AB7="Downtime",$N$7*AB8*$C$7,AB8*$C$7)) -> 910 | AC9: =IF(AC7="Vacant",0,IF(AC7="Downtime",$N$7*AC8*$C$7,AC8*$C$7)) -> 910 | ... CD9: =IF(CD7="Vacant",0,IF(CD7="Downtime",$N$7*CD8*$C$7,CD8*$C$7)) -> 1054.9394
A10: ='OM Rent Roll'!A7 -> 4949 C | B10: ='OM Rent Roll'!B7 -> Circle Pizza | C10: ='OM Rent Roll'!C7 -> 3620 | D10: =C10/NRA -> 0.20246085 | E10: ='OM Rent Roll'!D7 -> NNN | F10: ='OM Rent Roll'!G7 -> 1.4088398 | G10: ='OM Rent Roll'!H7 -> 0.019607843 | H10: =IF('OM Rent Roll'!E7=0,"",'OM Rent Roll'!E7) -> 45962 | I10: =IF('OM Rent Roll'!F7=0,"",'OM Rent Roll'!F7) -> 47787 | J10: 1 | K10: 60 | L10: 36 | M10: =Rent_Growth -> 0.03 | N10: 0.75 | O10: 6 | P10: 25 | Q10: 5 | R10: 0.06 | S10: 0.03 | T10: N | U10: 0 | V10: =IF(OR($I$10="",$I$10=0),IF(V$2<$U$10,"Vacant","Relet"),IF(ISTEXT($I$10),IF($U$10>0,IF(V$2<$U$10,"Downtime","Relet"),IF(V$2<=$O$10,"Downtime","Relet")),IF($I$10<=Close_Date,IF(V$2<=$O$10,"Downtime","Relet"),IF(V$2<=DATEDIF(Close_Date,$I$10,"M"),"In-Term",IF(V$2<=DATEDIF(Close_Date,$I$10,"M")+$O$10,"Downtime","Relet"))))) -> In-Term | W10: =IF(OR($I$10="",$I$10=0),IF(W$2<$U$10,"Vacant","Relet"),IF(ISTEXT($I$10),IF($U$10>0,IF(W$2<$U$10,"Downtime","Relet"),IF(W$2<=$O$10,"Downtime","Relet")),IF($I$10<=Close_Date,IF(W$2<=$O$10,"Downtime","Relet"),IF(W$2<=DATEDIF(Close_Date,$I$10,"M"),"In-Term",IF(W$2<=DATEDIF(Close_Date,$I$10,"M")+$O$10,"Downtime","Relet"))))) -> In-Term | X10: =IF(OR($I$10="",$I$10=0),IF(X$2<$U$10,"Vacant","Relet"),IF(ISTEXT($I$10),IF($U$10>0,IF(X$2<$U$10,"Downtime","Relet"),IF(X$2<=$O$10,"Downtime","Relet")),IF($I$10<=Close_Date,IF(X$2<=$O$10,"Downtime","Relet"),IF(X$2<=DATEDIF(Close_Date,$I$10,"M"),"In-Term",IF(X$2<=DATEDIF(Close_Date,$I$10,"M")+$O$10,"Downtime","Relet"))))) -> In-Term | Y10: =IF(OR($I$10="",$I$10=0),IF(Y$2<$U$10,"Vacant","Relet"),IF(ISTEXT($I$10),IF($U$10>0,IF(Y$2<$U$10,"Downtime","Relet"),IF(Y$2<=$O$10,"Downtime","Relet")),IF($I$10<=Close_Date,IF(Y$2<=$O$10,"Downtime","Relet"),IF(Y$2<=DATEDIF(Close_Date,$I$10,"M"),"In-Term",IF(Y$2<=DATEDIF(Close_Date,$I$10,"M")+$O$10,"Downtime","Relet"))))) -> In-Term | Z10: =IF(OR($I$10="",$I$10=0),IF(Z$2<$U$10,"Vacant","Relet"),IF(ISTEXT($I$10),IF($U$10>0,IF(Z$2<$U$10,"Downtime","Relet"),IF(Z$2<=$O$10,"Downtime","Relet")),IF($I$10<=Close_Date,IF(Z$2<=$O$10,"Downtime","Relet"),IF(Z$2<=DATEDIF(Close_Date,$I$10,"M"),"In-Term",IF(Z$2<=DATEDIF(Close_Date,$I$10,"M")+$O$10,"Downtime","Relet"))))) -> In-Term | AA10: =IF(OR($I$10="",$I$10=0),IF(AA$2<$U$10,"Vacant","Relet"),IF(ISTEXT($I$10),IF($U$10>0,IF(AA$2<$U$10,"Downtime","Relet"),IF(AA$2<=$O$10,"Downtime","Relet")),IF($I$10<=Close_Date,IF(AA$2<=$O$10,"Downtime","Relet"),IF(AA$2<=DATEDIF(Close_Date,$I$10,"M"),"In-Term",IF(AA$2<=DATEDIF(Close_Date,$I$10,"M")+$O$10,"Downtime","Relet"))))) -> In-Term | AB10: =IF(OR($I$10="",$I$10=0),IF(AB$2<$U$10,"Vacant","Relet"),IF(ISTEXT($I$10),IF($U$10>0,IF(AB$2<$U$10,"Downtime","Relet"),IF(AB$2<=$O$10,"Downtime","Relet")),IF($I$10<=Close_Date,IF(AB$2<=$O$10,"Downtime","Relet"),IF(AB$2<=DATEDIF(Close_Date,$I$10,"M"),"In-Term",IF(AB$2<=DATEDIF(Close_Date,$I$10,"M")+$O$10,"Downtime","Relet"))))) -> In-Term | AC10: =IF(OR($I$10="",$I$10=0),IF(AC$2<$U$10,"Vacant","Relet"),IF(ISTEXT($I$10),IF($U$10>0,IF(AC$2<$U$10,"Downtime","Relet"),IF(AC$2<=$O$10,"Downtime","Relet")),IF($I$10<=Close_Date,IF(AC$2<=$O$10,"Downtime","Relet"),IF(AC$2<=DATEDIF(Close_Date,$I$10,"M"),"In-Term",IF(AC$2<=DATEDIF(Close_Date,$I$10,"M")+$O$10,"Downtime","Relet"))))) -> In-Term | ... CD10: =IF(OR($I$10="",$I$10=0),IF(CD$2<$U$10,"Vacant","Relet"),IF(ISTEXT($I$10),IF($U$10>0,IF(CD$2<$U$10,"Downtime","Relet"),IF(CD$2<=$O$10,"Downtime","Relet")),IF($I$10<=Close_Date,IF(CD$2<=$O$10,"Downtime","Relet"),IF(CD$2<=DATEDIF(Close_Date,$I$10,"M"),"In-Term",IF(CD$2<=DATEDIF(Close_Date,$I$10,"M")+$O$10,"Downtime","Relet"))))) -> Relet
B11: Rate | V11: =IF(V10="Vacant",0,IF(V10="In-Term",$F$10*(1+$G$10)^(INT((V$2-1)/12)),IF(AND(V10="Downtime",ISTEXT($I$10)),$F$10,$J$10*(1+$M$10)^(INT((V$2-1)/12))))) -> 1.4088398 | W11: =IF(W10="Vacant",0,IF(W10="In-Term",$F$10*(1+$G$10)^(INT((W$2-1)/12)),IF(AND(W10="Downtime",ISTEXT($I$10)),$F$10,$J$10*(1+$M$10)^(INT((W$2-1)/12))))) -> 1.4088398 | X11: =IF(X10="Vacant",0,IF(X10="In-Term",$F$10*(1+$G$10)^(INT((X$2-1)/12)),IF(AND(X10="Downtime",ISTEXT($I$10)),$F$10,$J$10*(1+$M$10)^(INT((X$2-1)/12))))) -> 1.4088398 | Y11: =IF(Y10="Vacant",0,IF(Y10="In-Term",$F$10*(1+$G$10)^(INT((Y$2-1)/12)),IF(AND(Y10="Downtime",ISTEXT($I$10)),$F$10,$J$10*(1+$M$10)^(INT((Y$2-1)/12))))) -> 1.4088398 | Z11: =IF(Z10="Vacant",0,IF(Z10="In-Term",$F$10*(1+$G$10)^(INT((Z$2-1)/12)),IF(AND(Z10="Downtime",ISTEXT($I$10)),$F$10,$J$10*(1+$M$10)^(INT((Z$2-1)/12))))) -> 1.4088398 | AA11: =IF(AA10="Vacant",0,IF(AA10="In-Term",$F$10*(1+$G$10)^(INT((AA$2-1)/12)),IF(AND(AA10="Downtime",ISTEXT($I$10)),$F$10,$J$10*(1+$M$10)^(INT((AA$2-1)/12))))) -> 1.4088398 | AB11: =IF(AB10="Vacant",0,IF(AB10="In-Term",$F$10*(1+$G$10)^(INT((AB$2-1)/12)),IF(AND(AB10="Downtime",ISTEXT($I$10)),$F$10,$J$10*(1+$M$10)^(INT((AB$2-1)/12))))) -> 1.4088398 | AC11: =IF(AC10="Vacant",0,IF(AC10="In-Term",$F$10*(1+$G$10)^(INT((AC$2-1)/12)),IF(AND(AC10="Downtime",ISTEXT($I$10)),$F$10,$J$10*(1+$M$10)^(INT((AC$2-1)/12))))) -> 1.4088398 | ... CD11: =IF(CD10="Vacant",0,IF(CD10="In-Term",$F$10*(1+$G$10)^(INT((CD$2-1)/12)),IF(AND(CD10="Downtime",ISTEXT($I$10)),$F$10,$J$10*(1+$M$10)^(INT((CD$2-1)/12))))) -> 1.1592741
B12: Eff$ | V12: =IF(V10="Vacant",0,IF(V10="Downtime",$N$10*V11*$C$10,V11*$C$10)) -> 5100 | W12: =IF(W10="Vacant",0,IF(W10="Downtime",$N$10*W11*$C$10,W11*$C$10)) -> 5100 | X12: =IF(X10="Vacant",0,IF(X10="Downtime",$N$10*X11*$C$10,X11*$C$10)) -> 5100 | Y12: =IF(Y10="Vacant",0,IF(Y10="Downtime",$N$10*Y11*$C$10,Y11*$C$10)) -> 5100 | Z12: =IF(Z10="Vacant",0,IF(Z10="Downtime",$N$10*Z11*$C$10,Z11*$C$10)) -> 5100 | AA12: =IF(AA10="Vacant",0,IF(AA10="Downtime",$N$10*AA11*$C$10,AA11*$C$10)) -> 5100 | AB12: =IF(AB10="Vacant",0,IF(AB10="Downtime",$N$10*AB11*$C$10,AB11*$C$10)) -> 5100 | AC12: =IF(AC10="Vacant",0,IF(AC10="Downtime",$N$10*AC11*$C$10,AC11*$C$10)) -> 5100 | ... CD12: =IF(CD10="Vacant",0,IF(CD10="Downtime",$N$10*CD11*$C$10,CD11*$C$10)) -> 4196.5721
A13: ='OM Rent Roll'!A8 -> 4949 D&E | B13: ='OM Rent Roll'!B8 -> Silver Sake | C13: ='OM Rent Roll'!C8 -> 1990 | D13: =C13/NRA -> 0.11129754 | E13: ='OM Rent Roll'!D8 -> NNN | F13: ='OM Rent Roll'!G8 -> 1.5075377 | G13: ='OM Rent Roll'!H8 -> 0 | H13: =IF('OM Rent Roll'!E8=0,"",'OM Rent Roll'!E8) -> MTM | I13: =IF('OM Rent Roll'!F8=0,"",'OM Rent Roll'!F8) -> MTM | J13: 1 | K13: 60 | L13: 36 | M13: =Rent_Growth -> 0.03 | N13: 0.5 | O13: 6 | P13: 25 | Q13: 5 | R13: 0.06 | S13: 0.03 | T13: N | U13: 0 | V13: =IF(OR($I$13="",$I$13=0),IF(V$2<$U$13,"Vacant","Relet"),IF(ISTEXT($I$13),IF($U$13>0,IF(V$2<$U$13,"Downtime","Relet"),IF(V$2<=$O$13,"Downtime","Relet")),IF($I$13<=Close_Date,IF(V$2<=$O$13,"Downtime","Relet"),IF(V$2<=DATEDIF(Close_Date,$I$13,"M"),"In-Term",IF(V$2<=DATEDIF(Close_Date,$I$13,"M")+$O$13,"Downtime","Relet"))))) -> Downtime | W13: =IF(OR($I$13="",$I$13=0),IF(W$2<$U$13,"Vacant","Relet"),IF(ISTEXT($I$13),IF($U$13>0,IF(W$2<$U$13,"Downtime","Relet"),IF(W$2<=$O$13,"Downtime","Relet")),IF($I$13<=Close_Date,IF(W$2<=$O$13,"Downtime","Relet"),IF(W$2<=DATEDIF(Close_Date,$I$13,"M"),"In-Term",IF(W$2<=DATEDIF(Close_Date,$I$13,"M")+$O$13,"Downtime","Relet"))))) -> Downtime | X13: =IF(OR($I$13="",$I$13=0),IF(X$2<$U$13,"Vacant","Relet"),IF(ISTEXT($I$13),IF($U$13>0,IF(X$2<$U$13,"Downtime","Relet"),IF(X$2<=$O$13,"Downtime","Relet")),IF($I$13<=Close_Date,IF(X$2<=$O$13,"Downtime","Relet"),IF(X$2<=DATEDIF(Close_Date,$I$13,"M"),"In-Term",IF(X$2<=DATEDIF(Close_Date,$I$13,"M")+$O$13,"Downtime","Relet"))))) -> Downtime | Y13: =IF(OR($I$13="",$I$13=0),IF(Y$2<$U$13,"Vacant","Relet"),IF(ISTEXT($I$13),IF($U$13>0,IF(Y$2<$U$13,"Downtime","Relet"),IF(Y$2<=$O$13,"Downtime","Relet")),IF($I$13<=Close_Date,IF(Y$2<=$O$13,"Downtime","Relet"),IF(Y$2<=DATEDIF(Close_Date,$I$13,"M"),"In-Term",IF(Y$2<=DATEDIF(Close_Date,$I$13,"M")+$O$13,"Downtime","Relet"))))) -> Downtime | Z13: =IF(OR($I$13="",$I$13=0),IF(Z$2<$U$13,"Vacant","Relet"),IF(ISTEXT($I$13),IF($U$13>0,IF(Z$2<$U$13,"Downtime","Relet"),IF(Z$2<=$O$13,"Downtime","Relet")),IF($I$13<=Close_Date,IF(Z$2<=$O$13,"Downtime","Relet"),IF(Z$2<=DATEDIF(Close_Date,$I$13,"M"),"In-Term",IF(Z$2<=DATEDIF(Close_Date,$I$13,"M")+$O$13,"Downtime","Relet"))))) -> Downtime | AA13: =IF(OR($I$13="",$I$13=0),IF(AA$2<$U$13,"Vacant","Relet"),IF(ISTEXT($I$13),IF($U$13>0,IF(AA$2<$U$13,"Downtime","Relet"),IF(AA$2<=$O$13,"Downtime","Relet")),IF($I$13<=Close_Date,IF(AA$2<=$O$13,"Downtime","Relet"),IF(AA$2<=DATEDIF(Close_Date,$I$13,"M"),"In-Term",IF(AA$2<=DATEDIF(Close_Date,$I$13,"M")+$O$13,"Downtime","Relet"))))) -> Downtime | AB13: =IF(OR($I$13="",$I$13=0),IF(AB$2<$U$13,"Vacant","Relet"),IF(ISTEXT($I$13),IF($U$13>0,IF(AB$2<$U$13,"Downtime","Relet"),IF(AB$2<=$O$13,"Downtime","Relet")),IF($I$13<=Close_Date,IF(AB$2<=$O$13,"Downtime","Relet"),IF(AB$2<=DATEDIF(Close_Date,$I$13,"M"),"In-Term",IF(AB$2<=DATEDIF(Close_Date,$I$13,"M")+$O$13,"Downtime","Relet"))))) -> Relet | AC13: =IF(OR($I$13="",$I$13=0),IF(AC$2<$U$13,"Vacant","Relet"),IF(ISTEXT($I$13),IF($U$13>0,IF(AC$2<$U$13,"Downtime","Relet"),IF(AC$2<=$O$13,"Downtime","Relet")),IF($I$13<=Close_Date,IF(AC$2<=$O$13,"Downtime","Relet"),IF(AC$2<=DATEDIF(Close_Date,$I$13,"M"),"In-Term",IF(AC$2<=DATEDIF(Close_Date,$I$13,"M")+$O$13,"Downtime","Relet"))))) -> Relet | ... CD13: =IF(OR($I$13="",$I$13=0),IF(CD$2<$U$13,"Vacant","Relet"),IF(ISTEXT($I$13),IF($U$13>0,IF(CD$2<$U$13,"Downtime","Relet"),IF(CD$2<=$O$13,"Downtime","Relet")),IF($I$13<=Close_Date,IF(CD$2<=$O$13,"Downtime","Relet"),IF(CD$2<=DATEDIF(Close_Date,$I$13,"M"),"In-Term",IF(CD$2<=DATEDIF(Close_Date,$I$13,"M")+$O$13,"Downtime","Relet"))))) -> Relet
B14: Rate | V14: =IF(V13="Vacant",0,IF(V13="In-Term",$F$13*(1+$G$13)^(INT((V$2-1)/12)),IF(AND(V13="Downtime",ISTEXT($I$13)),$F$13,$J$13*(1+$M$13)^(INT((V$2-1)/12))))) -> 1.5075377 | W14: =IF(W13="Vacant",0,IF(W13="In-Term",$F$13*(1+$G$13)^(INT((W$2-1)/12)),IF(AND(W13="Downtime",ISTEXT($I$13)),$F$13,$J$13*(1+$M$13)^(INT((W$2-1)/12))))) -> 1.5075377 | X14: =IF(X13="Vacant",0,IF(X13="In-Term",$F$13*(1+$G$13)^(INT((X$2-1)/12)),IF(AND(X13="Downtime",ISTEXT($I$13)),$F$13,$J$13*(1+$M$13)^(INT((X$2-1)/12))))) -> 1.5075377 | Y14: =IF(Y13="Vacant",0,IF(Y13="In-Term",$F$13*(1+$G$13)^(INT((Y$2-1)/12)),IF(AND(Y13="Downtime",ISTEXT($I$13)),$F$13,$J$13*(1+$M$13)^(INT((Y$2-1)/12))))) -> 1.5075377 | Z14: =IF(Z13="Vacant",0,IF(Z13="In-Term",$F$13*(1+$G$13)^(INT((Z$2-1)/12)),IF(AND(Z13="Downtime",ISTEXT($I$13)),$F$13,$J$13*(1+$M$13)^(INT((Z$2-1)/12))))) -> 1.5075377 | AA14: =IF(AA13="Vacant",0,IF(AA13="In-Term",$F$13*(1+$G$13)^(INT((AA$2-1)/12)),IF(AND(AA13="Downtime",ISTEXT($I$13)),$F$13,$J$13*(1+$M$13)^(INT((AA$2-1)/12))))) -> 1.5075377 | AB14: =IF(AB13="Vacant",0,IF(AB13="In-Term",$F$13*(1+$G$13)^(INT((AB$2-1)/12)),IF(AND(AB13="Downtime",ISTEXT($I$13)),$F$13,$J$13*(1+$M$13)^(INT((AB$2-1)/12))))) -> 1 | AC14: =IF(AC13="Vacant",0,IF(AC13="In-Term",$F$13*(1+$G$13)^(INT((AC$2-1)/12)),IF(AND(AC13="Downtime",ISTEXT($I$13)),$F$13,$J$13*(1+$M$13)^(INT((AC$2-1)/12))))) -> 1 | ... CD14: =IF(CD13="Vacant",0,IF(CD13="In-Term",$F$13*(1+$G$13)^(INT((CD$2-1)/12)),IF(AND(CD13="Downtime",ISTEXT($I$13)),$F$13,$J$13*(1+$M$13)^(INT((CD$2-1)/12))))) -> 1.1592741
B15: Eff$ | V15: =IF(V13="Vacant",0,IF(V13="Downtime",$N$13*V14*$C$13,V14*$C$13)) -> 1500 | W15: =IF(W13="Vacant",0,IF(W13="Downtime",$N$13*W14*$C$13,W14*$C$13)) -> 1500 | X15: =IF(X13="Vacant",0,IF(X13="Downtime",$N$13*X14*$C$13,X14*$C$13)) -> 1500 | Y15: =IF(Y13="Vacant",0,IF(Y13="Downtime",$N$13*Y14*$C$13,Y14*$C$13)) -> 1500 | Z15: =IF(Z13="Vacant",0,IF(Z13="Downtime",$N$13*Z14*$C$13,Z14*$C$13)) -> 1500 | AA15: =IF(AA13="Vacant",0,IF(AA13="Downtime",$N$13*AA14*$C$13,AA14*$C$13)) -> 1500 | AB15: =IF(AB13="Vacant",0,IF(AB13="Downtime",$N$13*AB14*$C$13,AB14*$C$13)) -> 1990 | AC15: =IF(AC13="Vacant",0,IF(AC13="Downtime",$N$13*AC14*$C$13,AC14*$C$13)) -> 1990 | ... CD15: =IF(CD13="Vacant",0,IF(CD13="Downtime",$N$13*CD14*$C$13,CD14*$C$13)) -> 2306.9554
A16: ='OM Rent Roll'!A9 -> 4949 F | B16: ='OM Rent Roll'!B9 -> Waiel Merza | C16: ='OM Rent Roll'!C9 -> 810 | D16: =C16/NRA -> 0.045302013 | E16: ='OM Rent Roll'!D9 -> NNN | F16: ='OM Rent Roll'!G9 -> 0.95061728 | G16: ='OM Rent Roll'!H9 -> 0.024858298 | H16: =IF('OM Rent Roll'!E9=0,"",'OM Rent Roll'!E9) -> 46054 | I16: =IF('OM Rent Roll'!F9=0,"",'OM Rent Roll'!F9) -> 47238 | J16: 1 | K16: 60 | L16: 36 | M16: =Rent_Growth -> 0.03 | N16: 0.75 | O16: 6 | P16: 25 | Q16: 5 | R16: 0.06 | S16: 0.03 | T16: N | U16: 0 | V16: =IF(OR($I$16="",$I$16=0),IF(V$2<$U$16,"Vacant","Relet"),IF(ISTEXT($I$16),IF($U$16>0,IF(V$2<$U$16,"Downtime","Relet"),IF(V$2<=$O$16,"Downtime","Relet")),IF($I$16<=Close_Date,IF(V$2<=$O$16,"Downtime","Relet"),IF(V$2<=DATEDIF(Close_Date,$I$16,"M"),"In-Term",IF(V$2<=DATEDIF(Close_Date,$I$16,"M")+$O$16,"Downtime","Relet"))))) -> In-Term | W16: =IF(OR($I$16="",$I$16=0),IF(W$2<$U$16,"Vacant","Relet"),IF(ISTEXT($I$16),IF($U$16>0,IF(W$2<$U$16,"Downtime","Relet"),IF(W$2<=$O$16,"Downtime","Relet")),IF($I$16<=Close_Date,IF(W$2<=$O$16,"Downtime","Relet"),IF(W$2<=DATEDIF(Close_Date,$I$16,"M"),"In-Term",IF(W$2<=DATEDIF(Close_Date,$I$16,"M")+$O$16,"Downtime","Relet"))))) -> In-Term | X16: =IF(OR($I$16="",$I$16=0),IF(X$2<$U$16,"Vacant","Relet"),IF(ISTEXT($I$16),IF($U$16>0,IF(X$2<$U$16,"Downtime","Relet"),IF(X$2<=$O$16,"Downtime","Relet")),IF($I$16<=Close_Date,IF(X$2<=$O$16,"Downtime","Relet"),IF(X$2<=DATEDIF(Close_Date,$I$16,"M"),"In-Term",IF(X$2<=DATEDIF(Close_Date,$I$16,"M")+$O$16,"Downtime","Relet"))))) -> In-Term | Y16: =IF(OR($I$16="",$I$16=0),IF(Y$2<$U$16,"Vacant","Relet"),IF(ISTEXT($I$16),IF($U$16>0,IF(Y$2<$U$16,"Downtime","Relet"),IF(Y$2<=$O$16,"Downtime","Relet")),IF($I$16<=Close_Date,IF(Y$2<=$O$16,"Downtime","Relet"),IF(Y$2<=DATEDIF(Close_Date,$I$16,"M"),"In-Term",IF(Y$2<=DATEDIF(Close_Date,$I$16,"M")+$O$16,"Downtime","Relet"))))) -> In-Term | Z16: =IF(OR($I$16="",$I$16=0),IF(Z$2<$U$16,"Vacant","Relet"),IF(ISTEXT($I$16),IF($U$16>0,IF(Z$2<$U$16,"Downtime","Relet"),IF(Z$2<=$O$16,"Downtime","Relet")),IF($I$16<=Close_Date,IF(Z$2<=$O$16,"Downtime","Relet"),IF(Z$2<=DATEDIF(Close_Date,$I$16,"M"),"In-Term",IF(Z$2<=DATEDIF(Close_Date,$I$16,"M")+$O$16,"Downtime","Relet"))))) -> In-Term | AA16: =IF(OR($I$16="",$I$16=0),IF(AA$2<$U$16,"Vacant","Relet"),IF(ISTEXT($I$16),IF($U$16>0,IF(AA$2<$U$16,"Downtime","Relet"),IF(AA$2<=$O$16,"Downtime","Relet")),IF($I$16<=Close_Date,IF(AA$2<=$O$16,"Downtime","Relet"),IF(AA$2<=DATEDIF(Close_Date,$I$16,"M"),"In-Term",IF(AA$2<=DATEDIF(Close_Date,$I$16,"M")+$O$16,"Downtime","Relet"))))) -> In-Term | AB16: =IF(OR($I$16="",$I$16=0),IF(AB$2<$U$16,"Vacant","Relet"),IF(ISTEXT($I$16),IF($U$16>0,IF(AB$2<$U$16,"Downtime","Relet"),IF(AB$2<=$O$16,"Downtime","Relet")),IF($I$16<=Close_Date,IF(AB$2<=$O$16,"Downtime","Relet"),IF(AB$2<=DATEDIF(Close_Date,$I$16,"M"),"In-Term",IF(AB$2<=DATEDIF(Close_Date,$I$16,"M")+$O$16,"Downtime","Relet"))))) -> In-Term | AC16: =IF(OR($I$16="",$I$16=0),IF(AC$2<$U$16,"Vacant","Relet"),IF(ISTEXT($I$16),IF($U$16>0,IF(AC$2<$U$16,"Downtime","Relet"),IF(AC$2<=$O$16,"Downtime","Relet")),IF($I$16<=Close_Date,IF(AC$2<=$O$16,"Downtime","Relet"),IF(AC$2<=DATEDIF(Close_Date,$I$16,"M"),"In-Term",IF(AC$2<=DATEDIF(Close_Date,$I$16,"M")+$O$16,"Downtime","Relet"))))) -> In-Term | ... CD16: =IF(OR($I$16="",$I$16=0),IF(CD$2<$U$16,"Vacant","Relet"),IF(ISTEXT($I$16),IF($U$16>0,IF(CD$2<$U$16,"Downtime","Relet"),IF(CD$2<=$O$16,"Downtime","Relet")),IF($I$16<=Close_Date,IF(CD$2<=$O$16,"Downtime","Relet"),IF(CD$2<=DATEDIF(Close_Date,$I$16,"M"),"In-Term",IF(CD$2<=DATEDIF(Close_Date,$I$16,"M")+$O$16,"Downtime","Relet"))))) -> Relet
B17: Rate | V17: =IF(V16="Vacant",0,IF(V16="In-Term",$F$16*(1+$G$16)^(INT((V$2-1)/12)),IF(AND(V16="Downtime",ISTEXT($I$16)),$F$16,$J$16*(1+$M$16)^(INT((V$2-1)/12))))) -> 0.95061728 | W17: =IF(W16="Vacant",0,IF(W16="In-Term",$F$16*(1+$G$16)^(INT((W$2-1)/12)),IF(AND(W16="Downtime",ISTEXT($I$16)),$F$16,$J$16*(1+$M$16)^(INT((W$2-1)/12))))) -> 0.95061728 | X17: =IF(X16="Vacant",0,IF(X16="In-Term",$F$16*(1+$G$16)^(INT((X$2-1)/12)),IF(AND(X16="Downtime",ISTEXT($I$16)),$F$16,$J$16*(1+$M$16)^(INT((X$2-1)/12))))) -> 0.95061728 | Y17: =IF(Y16="Vacant",0,IF(Y16="In-Term",$F$16*(1+$G$16)^(INT((Y$2-1)/12)),IF(AND(Y16="Downtime",ISTEXT($I$16)),$F$16,$J$16*(1+$M$16)^(INT((Y$2-1)/12))))) -> 0.95061728 | Z17: =IF(Z16="Vacant",0,IF(Z16="In-Term",$F$16*(1+$G$16)^(INT((Z$2-1)/12)),IF(AND(Z16="Downtime",ISTEXT($I$16)),$F$16,$J$16*(1+$M$16)^(INT((Z$2-1)/12))))) -> 0.95061728 | AA17: =IF(AA16="Vacant",0,IF(AA16="In-Term",$F$16*(1+$G$16)^(INT((AA$2-1)/12)),IF(AND(AA16="Downtime",ISTEXT($I$16)),$F$16,$J$16*(1+$M$16)^(INT((AA$2-1)/12))))) -> 0.95061728 | AB17: =IF(AB16="Vacant",0,IF(AB16="In-Term",$F$16*(1+$G$16)^(INT((AB$2-1)/12)),IF(AND(AB16="Downtime",ISTEXT($I$16)),$F$16,$J$16*(1+$M$16)^(INT((AB$2-1)/12))))) -> 0.95061728 | AC17: =IF(AC16="Vacant",0,IF(AC16="In-Term",$F$16*(1+$G$16)^(INT((AC$2-1)/12)),IF(AND(AC16="Downtime",ISTEXT($I$16)),$F$16,$J$16*(1+$M$16)^(INT((AC$2-1)/12))))) -> 0.95061728 | ... CD17: =IF(CD16="Vacant",0,IF(CD16="In-Term",$F$16*(1+$G$16)^(INT((CD$2-1)/12)),IF(AND(CD16="Downtime",ISTEXT($I$16)),$F$16,$J$16*(1+$M$16)^(INT((CD$2-1)/12))))) -> 1.1592741
B18: Eff$ | V18: =IF(V16="Vacant",0,IF(V16="Downtime",$N$16*V17*$C$16,V17*$C$16)) -> 770 | W18: =IF(W16="Vacant",0,IF(W16="Downtime",$N$16*W17*$C$16,W17*$C$16)) -> 770 | X18: =IF(X16="Vacant",0,IF(X16="Downtime",$N$16*X17*$C$16,X17*$C$16)) -> 770 | Y18: =IF(Y16="Vacant",0,IF(Y16="Downtime",$N$16*Y17*$C$16,Y17*$C$16)) -> 770 | Z18: =IF(Z16="Vacant",0,IF(Z16="Downtime",$N$16*Z17*$C$16,Z17*$C$16)) -> 770 | AA18: =IF(AA16="Vacant",0,IF(AA16="Downtime",$N$16*AA17*$C$16,AA17*$C$16)) -> 770 | AB18: =IF(AB16="Vacant",0,IF(AB16="Downtime",$N$16*AB17*$C$16,AB17*$C$16)) -> 770 | AC18: =IF(AC16="Vacant",0,IF(AC16="Downtime",$N$16*AC17*$C$16,AC17*$C$16)) -> 770 | ... CD18: =IF(CD16="Vacant",0,IF(CD16="Downtime",$N$16*CD17*$C$16,CD17*$C$16)) -> 939.012
A19: ='OM Rent Roll'!A10 -> 4949 G | B19: ='OM Rent Roll'!B10 -> Cigarettes & Gifts | C19: ='OM Rent Roll'!C10 -> 810 | D19: =C19/NRA -> 0.045302013 | E19: ='OM Rent Roll'!D10 -> NNN | F19: ='OM Rent Roll'!G10 -> 1.2506173 | G19: ='OM Rent Roll'!H10 -> 0 | H19: =IF('OM Rent Roll'!E10=0,"",'OM Rent Roll'!E10) -> 44105 | I19: =IF('OM Rent Roll'!F10=0,"",'OM Rent Roll'!F10) -> 45930 | J19: 1 | K19: 60 | L19: 36 | M19: =Rent_Growth -> 0.03 | N19: 0.75 | O19: 6 | P19: 25 | Q19: 5 | R19: 0.06 | S19: 0.03 | T19: N | U19: 0 | V19: =IF(OR($I$19="",$I$19=0),IF(V$2<$U$19,"Vacant","Relet"),IF(ISTEXT($I$19),IF($U$19>0,IF(V$2<$U$19,"Downtime","Relet"),IF(V$2<=$O$19,"Downtime","Relet")),IF($I$19<=Close_Date,IF(V$2<=$O$19,"Downtime","Relet"),IF(V$2<=DATEDIF(Close_Date,$I$19,"M"),"In-Term",IF(V$2<=DATEDIF(Close_Date,$I$19,"M")+$O$19,"Downtime","Relet"))))) -> Downtime | W19: =IF(OR($I$19="",$I$19=0),IF(W$2<$U$19,"Vacant","Relet"),IF(ISTEXT($I$19),IF($U$19>0,IF(W$2<$U$19,"Downtime","Relet"),IF(W$2<=$O$19,"Downtime","Relet")),IF($I$19<=Close_Date,IF(W$2<=$O$19,"Downtime","Relet"),IF(W$2<=DATEDIF(Close_Date,$I$19,"M"),"In-Term",IF(W$2<=DATEDIF(Close_Date,$I$19,"M")+$O$19,"Downtime","Relet"))))) -> Downtime | X19: =IF(OR($I$19="",$I$19=0),IF(X$2<$U$19,"Vacant","Relet"),IF(ISTEXT($I$19),IF($U$19>0,IF(X$2<$U$19,"Downtime","Relet"),IF(X$2<=$O$19,"Downtime","Relet")),IF($I$19<=Close_Date,IF(X$2<=$O$19,"Downtime","Relet"),IF(X$2<=DATEDIF(Close_Date,$I$19,"M"),"In-Term",IF(X$2<=DATEDIF(Close_Date,$I$19,"M")+$O$19,"Downtime","Relet"))))) -> Downtime | Y19: =IF(OR($I$19="",$I$19=0),IF(Y$2<$U$19,"Vacant","Relet"),IF(ISTEXT($I$19),IF($U$19>0,IF(Y$2<$U$19,"Downtime","Relet"),IF(Y$2<=$O$19,"Downtime","Relet")),IF($I$19<=Close_Date,IF(Y$2<=$O$19,"Downtime","Relet"),IF(Y$2<=DATEDIF(Close_Date,$I$19,"M"),"In-Term",IF(Y$2<=DATEDIF(Close_Date,$I$19,"M")+$O$19,"Downtime","Relet"))))) -> Downtime | Z19: =IF(OR($I$19="",$I$19=0),IF(Z$2<$U$19,"Vacant","Relet"),IF(ISTEXT($I$19),IF($U$19>0,IF(Z$2<$U$19,"Downtime","Relet"),IF(Z$2<=$O$19,"Downtime","Relet")),IF($I$19<=Close_Date,IF(Z$2<=$O$19,"Downtime","Relet"),IF(Z$2<=DATEDIF(Close_Date,$I$19,"M"),"In-Term",IF(Z$2<=DATEDIF(Close_Date,$I$19,"M")+$O$19,"Downtime","Relet"))))) -> Downtime | AA19: =IF(OR($I$19="",$I$19=0),IF(AA$2<$U$19,"Vacant","Relet"),IF(ISTEXT($I$19),IF($U$19>0,IF(AA$2<$U$19,"Downtime","Relet"),IF(AA$2<=$O$19,"Downtime","Relet")),IF($I$19<=Close_Date,IF(AA$2<=$O$19,"Downtime","Relet"),IF(AA$2<=DATEDIF(Close_Date,$I$19,"M"),"In-Term",IF(AA$2<=DATEDIF(Close_Date,$I$19,"M")+$O$19,"Downtime","Relet"))))) -> Downtime | AB19: =IF(OR($I$19="",$I$19=0),IF(AB$2<$U$19,"Vacant","Relet"),IF(ISTEXT($I$19),IF($U$19>0,IF(AB$2<$U$19,"Downtime","Relet"),IF(AB$2<=$O$19,"Downtime","Relet")),IF($I$19<=Close_Date,IF(AB$2<=$O$19,"Downtime","Relet"),IF(AB$2<=DATEDIF(Close_Date,$I$19,"M"),"In-Term",IF(AB$2<=DATEDIF(Close_Date,$I$19,"M")+$O$19,"Downtime","Relet"))))) -> Relet | AC19: =IF(OR($I$19="",$I$19=0),IF(AC$2<$U$19,"Vacant","Relet"),IF(ISTEXT($I$19),IF($U$19>0,IF(AC$2<$U$19,"Downtime","Relet"),IF(AC$2<=$O$19,"Downtime","Relet")),IF($I$19<=Close_Date,IF(AC$2<=$O$19,"Downtime","Relet"),IF(AC$2<=DATEDIF(Close_Date,$I$19,"M"),"In-Term",IF(AC$2<=DATEDIF(Close_Date,$I$19,"M")+$O$19,"Downtime","Relet"))))) -> Relet | ... CD19: =IF(OR($I$19="",$I$19=0),IF(CD$2<$U$19,"Vacant","Relet"),IF(ISTEXT($I$19),IF($U$19>0,IF(CD$2<$U$19,"Downtime","Relet"),IF(CD$2<=$O$19,"Downtime","Relet")),IF($I$19<=Close_Date,IF(CD$2<=$O$19,"Downtime","Relet"),IF(CD$2<=DATEDIF(Close_Date,$I$19,"M"),"In-Term",IF(CD$2<=DATEDIF(Close_Date,$I$19,"M")+$O$19,"Downtime","Relet"))))) -> Relet
B20: Rate | V20: =IF(V19="Vacant",0,IF(V19="In-Term",$F$19*(1+$G$19)^(INT((V$2-1)/12)),IF(AND(V19="Downtime",ISTEXT($I$19)),$F$19,$J$19*(1+$M$19)^(INT((V$2-1)/12))))) -> 1 | W20: =IF(W19="Vacant",0,IF(W19="In-Term",$F$19*(1+$G$19)^(INT((W$2-1)/12)),IF(AND(W19="Downtime",ISTEXT($I$19)),$F$19,$J$19*(1+$M$19)^(INT((W$2-1)/12))))) -> 1 | X20: =IF(X19="Vacant",0,IF(X19="In-Term",$F$19*(1+$G$19)^(INT((X$2-1)/12)),IF(AND(X19="Downtime",ISTEXT($I$19)),$F$19,$J$19*(1+$M$19)^(INT((X$2-1)/12))))) -> 1 | Y20: =IF(Y19="Vacant",0,IF(Y19="In-Term",$F$19*(1+$G$19)^(INT((Y$2-1)/12)),IF(AND(Y19="Downtime",ISTEXT($I$19)),$F$19,$J$19*(1+$M$19)^(INT((Y$2-1)/12))))) -> 1 | Z20: =IF(Z19="Vacant",0,IF(Z19="In-Term",$F$19*(1+$G$19)^(INT((Z$2-1)/12)),IF(AND(Z19="Downtime",ISTEXT($I$19)),$F$19,$J$19*(1+$M$19)^(INT((Z$2-1)/12))))) -> 1 | AA20: =IF(AA19="Vacant",0,IF(AA19="In-Term",$F$19*(1+$G$19)^(INT((AA$2-1)/12)),IF(AND(AA19="Downtime",ISTEXT($I$19)),$F$19,$J$19*(1+$M$19)^(INT((AA$2-1)/12))))) -> 1 | AB20: =IF(AB19="Vacant",0,IF(AB19="In-Term",$F$19*(1+$G$19)^(INT((AB$2-1)/12)),IF(AND(AB19="Downtime",ISTEXT($I$19)),$F$19,$J$19*(1+$M$19)^(INT((AB$2-1)/12))))) -> 1 | AC20: =IF(AC19="Vacant",0,IF(AC19="In-Term",$F$19*(1+$G$19)^(INT((AC$2-1)/12)),IF(AND(AC19="Downtime",ISTEXT($I$19)),$F$19,$J$19*(1+$M$19)^(INT((AC$2-1)/12))))) -> 1 | ... CD20: =IF(CD19="Vacant",0,IF(CD19="In-Term",$F$19*(1+$G$19)^(INT((CD$2-1)/12)),IF(AND(CD19="Downtime",ISTEXT($I$19)),$F$19,$J$19*(1+$M$19)^(INT((CD$2-1)/12))))) -> 1.1592741
B21: Eff$ | V21: =IF(V19="Vacant",0,IF(V19="Downtime",$N$19*V20*$C$19,V20*$C$19)) -> 607.5 | W21: =IF(W19="Vacant",0,IF(W19="Downtime",$N$19*W20*$C$19,W20*$C$19)) -> 607.5 | X21: =IF(X19="Vacant",0,IF(X19="Downtime",$N$19*X20*$C$19,X20*$C$19)) -> 607.5 | Y21: =IF(Y19="Vacant",0,IF(Y19="Downtime",$N$19*Y20*$C$19,Y20*$C$19)) -> 607.5 | Z21: =IF(Z19="Vacant",0,IF(Z19="Downtime",$N$19*Z20*$C$19,Z20*$C$19)) -> 607.5 | AA21: =IF(AA19="Vacant",0,IF(AA19="Downtime",$N$19*AA20*$C$19,AA20*$C$19)) -> 607.5 | AB21: =IF(AB19="Vacant",0,IF(AB19="Downtime",$N$19*AB20*$C$19,AB20*$C$19)) -> 810 | AC21: =IF(AC19="Vacant",0,IF(AC19="Downtime",$N$19*AC20*$C$19,AC20*$C$19)) -> 810 | ... CD21: =IF(CD19="Vacant",0,IF(CD19="Downtime",$N$19*CD20*$C$19,CD20*$C$19)) -> 939.012
A22: ='OM Rent Roll'!A11 -> 4949 H | B22: ='OM Rent Roll'!B11 -> Brittany Hair & Nails | C22: ='OM Rent Roll'!C11 -> 810 | D22: =C22/NRA -> 0.045302013 | E22: ='OM Rent Roll'!D11 -> MG | F22: ='OM Rent Roll'!G11 -> 1.6975309 | G22: ='OM Rent Roll'!H11 -> 0 | H22: =IF('OM Rent Roll'!E11=0,"",'OM Rent Roll'!E11) -> 43070 | I22: =IF('OM Rent Roll'!F11=0,"",'OM Rent Roll'!F11) -> 46142 | J22: 1 | K22: 60 | L22: 36 | M22: =Rent_Growth -> 0.03 | N22: 0.75 | O22: 6 | P22: 25 | Q22: 5 | R22: 0.06 | S22: 0.03 | T22: Y | U22: 0 | V22: =IF(OR($I$22="",$I$22=0),IF(V$2<$U$22,"Vacant","Relet"),IF(ISTEXT($I$22),IF($U$22>0,IF(V$2<$U$22,"Downtime","Relet"),IF(V$2<=$O$22,"Downtime","Relet")),IF($I$22<=Close_Date,IF(V$2<=$O$22,"Downtime","Relet"),IF(V$2<=DATEDIF(Close_Date,$I$22,"M"),"In-Term",IF(V$2<=DATEDIF(Close_Date,$I$22,"M")+$O$22,"Downtime","Relet"))))) -> Downtime | W22: =IF(OR($I$22="",$I$22=0),IF(W$2<$U$22,"Vacant","Relet"),IF(ISTEXT($I$22),IF($U$22>0,IF(W$2<$U$22,"Downtime","Relet"),IF(W$2<=$O$22,"Downtime","Relet")),IF($I$22<=Close_Date,IF(W$2<=$O$22,"Downtime","Relet"),IF(W$2<=DATEDIF(Close_Date,$I$22,"M"),"In-Term",IF(W$2<=DATEDIF(Close_Date,$I$22,"M")+$O$22,"Downtime","Relet"))))) -> Downtime | X22: =IF(OR($I$22="",$I$22=0),IF(X$2<$U$22,"Vacant","Relet"),IF(ISTEXT($I$22),IF($U$22>0,IF(X$2<$U$22,"Downtime","Relet"),IF(X$2<=$O$22,"Downtime","Relet")),IF($I$22<=Close_Date,IF(X$2<=$O$22,"Downtime","Relet"),IF(X$2<=DATEDIF(Close_Date,$I$22,"M"),"In-Term",IF(X$2<=DATEDIF(Close_Date,$I$22,"M")+$O$22,"Downtime","Relet"))))) -> Downtime | Y22: =IF(OR($I$22="",$I$22=0),IF(Y$2<$U$22,"Vacant","Relet"),IF(ISTEXT($I$22),IF($U$22>0,IF(Y$2<$U$22,"Downtime","Relet"),IF(Y$2<=$O$22,"Downtime","Relet")),IF($I$22<=Close_Date,IF(Y$2<=$O$22,"Downtime","Relet"),IF(Y$2<=DATEDIF(Close_Date,$I$22,"M"),"In-Term",IF(Y$2<=DATEDIF(Close_Date,$I$22,"M")+$O$22,"Downtime","Relet"))))) -> Downtime | Z22: =IF(OR($I$22="",$I$22=0),IF(Z$2<$U$22,"Vacant","Relet"),IF(ISTEXT($I$22),IF($U$22>0,IF(Z$2<$U$22,"Downtime","Relet"),IF(Z$2<=$O$22,"Downtime","Relet")),IF($I$22<=Close_Date,IF(Z$2<=$O$22,"Downtime","Relet"),IF(Z$2<=DATEDIF(Close_Date,$I$22,"M"),"In-Term",IF(Z$2<=DATEDIF(Close_Date,$I$22,"M")+$O$22,"Downtime","Relet"))))) -> Downtime | AA22: =IF(OR($I$22="",$I$22=0),IF(AA$2<$U$22,"Vacant","Relet"),IF(ISTEXT($I$22),IF($U$22>0,IF(AA$2<$U$22,"Downtime","Relet"),IF(AA$2<=$O$22,"Downtime","Relet")),IF($I$22<=Close_Date,IF(AA$2<=$O$22,"Downtime","Relet"),IF(AA$2<=DATEDIF(Close_Date,$I$22,"M"),"In-Term",IF(AA$2<=DATEDIF(Close_Date,$I$22,"M")+$O$22,"Downtime","Relet"))))) -> Downtime | AB22: =IF(OR($I$22="",$I$22=0),IF(AB$2<$U$22,"Vacant","Relet"),IF(ISTEXT($I$22),IF($U$22>0,IF(AB$2<$U$22,"Downtime","Relet"),IF(AB$2<=$O$22,"Downtime","Relet")),IF($I$22<=Close_Date,IF(AB$2<=$O$22,"Downtime","Relet"),IF(AB$2<=DATEDIF(Close_Date,$I$22,"M"),"In-Term",IF(AB$2<=DATEDIF(Close_Date,$I$22,"M")+$O$22,"Downtime","Relet"))))) -> Relet | AC22: =IF(OR($I$22="",$I$22=0),IF(AC$2<$U$22,"Vacant","Relet"),IF(ISTEXT($I$22),IF($U$22>0,IF(AC$2<$U$22,"Downtime","Relet"),IF(AC$2<=$O$22,"Downtime","Relet")),IF($I$22<=Close_Date,IF(AC$2<=$O$22,"Downtime","Relet"),IF(AC$2<=DATEDIF(Close_Date,$I$22,"M"),"In-Term",IF(AC$2<=DATEDIF(Close_Date,$I$22,"M")+$O$22,"Downtime","Relet"))))) -> Relet | ... CD22: =IF(OR($I$22="",$I$22=0),IF(CD$2<$U$22,"Vacant","Relet"),IF(ISTEXT($I$22),IF($U$22>0,IF(CD$2<$U$22,"Downtime","Relet"),IF(CD$2<=$O$22,"Downtime","Relet")),IF($I$22<=Close_Date,IF(CD$2<=$O$22,"Downtime","Relet"),IF(CD$2<=DATEDIF(Close_Date,$I$22,"M"),"In-Term",IF(CD$2<=DATEDIF(Close_Date,$I$22,"M")+$O$22,"Downtime","Relet"))))) -> Relet
B23: Rate | V23: =IF(V22="Vacant",0,IF(V22="In-Term",$F$22*(1+$G$22)^(INT((V$2-1)/12)),IF(AND(V22="Downtime",ISTEXT($I$22)),$F$22,$J$22*(1+$M$22)^(INT((V$2-1)/12))))) -> 1 | W23: =IF(W22="Vacant",0,IF(W22="In-Term",$F$22*(1+$G$22)^(INT((W$2-1)/12)),IF(AND(W22="Downtime",ISTEXT($I$22)),$F$22,$J$22*(1+$M$22)^(INT((W$2-1)/12))))) -> 1 | X23: =IF(X22="Vacant",0,IF(X22="In-Term",$F$22*(1+$G$22)^(INT((X$2-1)/12)),IF(AND(X22="Downtime",ISTEXT($I$22)),$F$22,$J$22*(1+$M$22)^(INT((X$2-1)/12))))) -> 1 | Y23: =IF(Y22="Vacant",0,IF(Y22="In-Term",$F$22*(1+$G$22)^(INT((Y$2-1)/12)),IF(AND(Y22="Downtime",ISTEXT($I$22)),$F$22,$J$22*(1+$M$22)^(INT((Y$2-1)/12))))) -> 1 | Z23: =IF(Z22="Vacant",0,IF(Z22="In-Term",$F$22*(1+$G$22)^(INT((Z$2-1)/12)),IF(AND(Z22="Downtime",ISTEXT($I$22)),$F$22,$J$22*(1+$M$22)^(INT((Z$2-1)/12))))) -> 1 | AA23: =IF(AA22="Vacant",0,IF(AA22="In-Term",$F$22*(1+$G$22)^(INT((AA$2-1)/12)),IF(AND(AA22="Downtime",ISTEXT($I$22)),$F$22,$J$22*(1+$M$22)^(INT((AA$2-1)/12))))) -> 1 | AB23: =IF(AB22="Vacant",0,IF(AB22="In-Term",$F$22*(1+$G$22)^(INT((AB$2-1)/12)),IF(AND(AB22="Downtime",ISTEXT($I$22)),$F$22,$J$22*(1+$M$22)^(INT((AB$2-1)/12))))) -> 1 | AC23: =IF(AC22="Vacant",0,IF(AC22="In-Term",$F$22*(1+$G$22)^(INT((AC$2-1)/12)),IF(AND(AC22="Downtime",ISTEXT($I$22)),$F$22,$J$22*(1+$M$22)^(INT((AC$2-1)/12))))) -> 1 | ... CD23: =IF(CD22="Vacant",0,IF(CD22="In-Term",$F$22*(1+$G$22)^(INT((CD$2-1)/12)),IF(AND(CD22="Downtime",ISTEXT($I$22)),$F$22,$J$22*(1+$M$22)^(INT((CD$2-1)/12))))) -> 1.1592741
B24: Eff$ | V24: =IF(V22="Vacant",0,IF(V22="Downtime",$N$22*V23*$C$22,V23*$C$22)) -> 607.5 | W24: =IF(W22="Vacant",0,IF(W22="Downtime",$N$22*W23*$C$22,W23*$C$22)) -> 607.5 | X24: =IF(X22="Vacant",0,IF(X22="Downtime",$N$22*X23*$C$22,X23*$C$22)) -> 607.5 | Y24: =IF(Y22="Vacant",0,IF(Y22="Downtime",$N$22*Y23*$C$22,Y23*$C$22)) -> 607.5 | Z24: =IF(Z22="Vacant",0,IF(Z22="Downtime",$N$22*Z23*$C$22,Z23*$C$22)) -> 607.5 | AA24: =IF(AA22="Vacant",0,IF(AA22="Downtime",$N$22*AA23*$C$22,AA23*$C$22)) -> 607.5 | AB24: =IF(AB22="Vacant",0,IF(AB22="Downtime",$N$22*AB23*$C$22,AB23*$C$22)) -> 810 | AC24: =IF(AC22="Vacant",0,IF(AC22="Downtime",$N$22*AC23*$C$22,AC23*$C$22)) -> 810 | ... CD24: =IF(CD22="Vacant",0,IF(CD22="Downtime",$N$22*CD23*$C$22,CD23*$C$22)) -> 939.012
A25: ='OM Rent Roll'!A12 -> 4949 I | B25: ='OM Rent Roll'!B12 -> Madeville Hair Salon | C25: ='OM Rent Roll'!C12 -> 810 | D25: =C25/NRA -> 0.045302013 | E25: ='OM Rent Roll'!D12 -> NNN | F25: ='OM Rent Roll'!G12 -> 1.2197531 | G25: ='OM Rent Roll'!H12 -> 0 | H25: =IF('OM Rent Roll'!E12=0,"",'OM Rent Roll'!E12) -> MTM | I25: =IF('OM Rent Roll'!F12=0,"",'OM Rent Roll'!F12) -> MTM | J25: 1 | K25: 60 | L25: 36 | M25: =Rent_Growth -> 0.03 | N25: 0.5 | O25: 6 | P25: 25 | Q25: 5 | R25: 0.06 | S25: 0.03 | T25: N | U25: 0 | V25: =IF(OR($I$25="",$I$25=0),IF(V$2<$U$25,"Vacant","Relet"),IF(ISTEXT($I$25),IF($U$25>0,IF(V$2<$U$25,"Downtime","Relet"),IF(V$2<=$O$25,"Downtime","Relet")),IF($I$25<=Close_Date,IF(V$2<=$O$25,"Downtime","Relet"),IF(V$2<=DATEDIF(Close_Date,$I$25,"M"),"In-Term",IF(V$2<=DATEDIF(Close_Date,$I$25,"M")+$O$25,"Downtime","Relet"))))) -> Downtime | W25: =IF(OR($I$25="",$I$25=0),IF(W$2<$U$25,"Vacant","Relet"),IF(ISTEXT($I$25),IF($U$25>0,IF(W$2<$U$25,"Downtime","Relet"),IF(W$2<=$O$25,"Downtime","Relet")),IF($I$25<=Close_Date,IF(W$2<=$O$25,"Downtime","Relet"),IF(W$2<=DATEDIF(Close_Date,$I$25,"M"),"In-Term",IF(W$2<=DATEDIF(Close_Date,$I$25,"M")+$O$25,"Downtime","Relet"))))) -> Downtime | X25: =IF(OR($I$25="",$I$25=0),IF(X$2<$U$25,"Vacant","Relet"),IF(ISTEXT($I$25),IF($U$25>0,IF(X$2<$U$25,"Downtime","Relet"),IF(X$2<=$O$25,"Downtime","Relet")),IF($I$25<=Close_Date,IF(X$2<=$O$25,"Downtime","Relet"),IF(X$2<=DATEDIF(Close_Date,$I$25,"M"),"In-Term",IF(X$2<=DATEDIF(Close_Date,$I$25,"M")+$O$25,"Downtime","Relet"))))) -> Downtime | Y25: =IF(OR($I$25="",$I$25=0),IF(Y$2<$U$25,"Vacant","Relet"),IF(ISTEXT($I$25),IF($U$25>0,IF(Y$2<$U$25,"Downtime","Relet"),IF(Y$2<=$O$25,"Downtime","Relet")),IF($I$25<=Close_Date,IF(Y$2<=$O$25,"Downtime","Relet"),IF(Y$2<=DATEDIF(Close_Date,$I$25,"M"),"In-Term",IF(Y$2<=DATEDIF(Close_Date,$I$25,"M")+$O$25,"Downtime","Relet"))))) -> Downtime | Z25: =IF(OR($I$25="",$I$25=0),IF(Z$2<$U$25,"Vacant","Relet"),IF(ISTEXT($I$25),IF($U$25>0,IF(Z$2<$U$25,"Downtime","Relet"),IF(Z$2<=$O$25,"Downtime","Relet")),IF($I$25<=Close_Date,IF(Z$2<=$O$25,"Downtime","Relet"),IF(Z$2<=DATEDIF(Close_Date,$I$25,"M"),"In-Term",IF(Z$2<=DATEDIF(Close_Date,$I$25,"M")+$O$25,"Downtime","Relet"))))) -> Downtime | AA25: =IF(OR($I$25="",$I$25=0),IF(AA$2<$U$25,"Vacant","Relet"),IF(ISTEXT($I$25),IF($U$25>0,IF(AA$2<$U$25,"Downtime","Relet"),IF(AA$2<=$O$25,"Downtime","Relet")),IF($I$25<=Close_Date,IF(AA$2<=$O$25,"Downtime","Relet"),IF(AA$2<=DATEDIF(Close_Date,$I$25,"M"),"In-Term",IF(AA$2<=DATEDIF(Close_Date,$I$25,"M")+$O$25,"Downtime","Relet"))))) -> Downtime | AB25: =IF(OR($I$25="",$I$25=0),IF(AB$2<$U$25,"Vacant","Relet"),IF(ISTEXT($I$25),IF($U$25>0,IF(AB$2<$U$25,"Downtime","Relet"),IF(AB$2<=$O$25,"Downtime","Relet")),IF($I$25<=Close_Date,IF(AB$2<=$O$25,"Downtime","Relet"),IF(AB$2<=DATEDIF(Close_Date,$I$25,"M"),"In-Term",IF(AB$2<=DATEDIF(Close_Date,$I$25,"M")+$O$25,"Downtime","Relet"))))) -> Relet | AC25: =IF(OR($I$25="",$I$25=0),IF(AC$2<$U$25,"Vacant","Relet"),IF(ISTEXT($I$25),IF($U$25>0,IF(AC$2<$U$25,"Downtime","Relet"),IF(AC$2<=$O$25,"Downtime","Relet")),IF($I$25<=Close_Date,IF(AC$2<=$O$25,"Downtime","Relet"),IF(AC$2<=DATEDIF(Close_Date,$I$25,"M"),"In-Term",IF(AC$2<=DATEDIF(Close_Date,$I$25,"M")+$O$25,"Downtime","Relet"))))) -> Relet | ... CD25: =IF(OR($I$25="",$I$25=0),IF(CD$2<$U$25,"Vacant","Relet"),IF(ISTEXT($I$25),IF($U$25>0,IF(CD$2<$U$25,"Downtime","Relet"),IF(CD$2<=$O$25,"Downtime","Relet")),IF($I$25<=Close_Date,IF(CD$2<=$O$25,"Downtime","Relet"),IF(CD$2<=DATEDIF(Close_Date,$I$25,"M"),"In-Term",IF(CD$2<=DATEDIF(Close_Date,$I$25,"M")+$O$25,"Downtime","Relet"))))) -> Relet
B26: Rate | V26: =IF(V25="Vacant",0,IF(V25="In-Term",$F$25*(1+$G$25)^(INT((V$2-1)/12)),IF(AND(V25="Downtime",ISTEXT($I$25)),$F$25,$J$25*(1+$M$25)^(INT((V$2-1)/12))))) -> 1.2197531 | W26: =IF(W25="Vacant",0,IF(W25="In-Term",$F$25*(1+$G$25)^(INT((W$2-1)/12)),IF(AND(W25="Downtime",ISTEXT($I$25)),$F$25,$J$25*(1+$M$25)^(INT((W$2-1)/12))))) -> 1.2197531 | X26: =IF(X25="Vacant",0,IF(X25="In-Term",$F$25*(1+$G$25)^(INT((X$2-1)/12)),IF(AND(X25="Downtime",ISTEXT($I$25)),$F$25,$J$25*(1+$M$25)^(INT((X$2-1)/12))))) -> 1.2197531 | Y26: =IF(Y25="Vacant",0,IF(Y25="In-Term",$F$25*(1+$G$25)^(INT((Y$2-1)/12)),IF(AND(Y25="Downtime",ISTEXT($I$25)),$F$25,$J$25*(1+$M$25)^(INT((Y$2-1)/12))))) -> 1.2197531 | Z26: =IF(Z25="Vacant",0,IF(Z25="In-Term",$F$25*(1+$G$25)^(INT((Z$2-1)/12)),IF(AND(Z25="Downtime",ISTEXT($I$25)),$F$25,$J$25*(1+$M$25)^(INT((Z$2-1)/12))))) -> 1.2197531 | AA26: =IF(AA25="Vacant",0,IF(AA25="In-Term",$F$25*(1+$G$25)^(INT((AA$2-1)/12)),IF(AND(AA25="Downtime",ISTEXT($I$25)),$F$25,$J$25*(1+$M$25)^(INT((AA$2-1)/12))))) -> 1.2197531 | AB26: =IF(AB25="Vacant",0,IF(AB25="In-Term",$F$25*(1+$G$25)^(INT((AB$2-1)/12)),IF(AND(AB25="Downtime",ISTEXT($I$25)),$F$25,$J$25*(1+$M$25)^(INT((AB$2-1)/12))))) -> 1 | AC26: =IF(AC25="Vacant",0,IF(AC25="In-Term",$F$25*(1+$G$25)^(INT((AC$2-1)/12)),IF(AND(AC25="Downtime",ISTEXT($I$25)),$F$25,$J$25*(1+$M$25)^(INT((AC$2-1)/12))))) -> 1 | ... CD26: =IF(CD25="Vacant",0,IF(CD25="In-Term",$F$25*(1+$G$25)^(INT((CD$2-1)/12)),IF(AND(CD25="Downtime",ISTEXT($I$25)),$F$25,$J$25*(1+$M$25)^(INT((CD$2-1)/12))))) -> 1.1592741
B27: Eff$ | V27: =IF(V25="Vacant",0,IF(V25="Downtime",$N$25*V26*$C$25,V26*$C$25)) -> 494 | W27: =IF(W25="Vacant",0,IF(W25="Downtime",$N$25*W26*$C$25,W26*$C$25)) -> 494 | X27: =IF(X25="Vacant",0,IF(X25="Downtime",$N$25*X26*$C$25,X26*$C$25)) -> 494 | Y27: =IF(Y25="Vacant",0,IF(Y25="Downtime",$N$25*Y26*$C$25,Y26*$C$25)) -> 494 | Z27: =IF(Z25="Vacant",0,IF(Z25="Downtime",$N$25*Z26*$C$25,Z26*$C$25)) -> 494 | AA27: =IF(AA25="Vacant",0,IF(AA25="Downtime",$N$25*AA26*$C$25,AA26*$C$25)) -> 494 | AB27: =IF(AB25="Vacant",0,IF(AB25="Downtime",$N$25*AB26*$C$25,AB26*$C$25)) -> 810 | AC27: =IF(AC25="Vacant",0,IF(AC25="Downtime",$N$25*AC26*$C$25,AC26*$C$25)) -> 810 | ... CD27: =IF(CD25="Vacant",0,IF(CD25="Downtime",$N$25*CD26*$C$25,CD26*$C$25)) -> 939.012
A28: ='OM Rent Roll'!A13 -> 4949 J | B28: ='OM Rent Roll'!B13 -> VACANT | C28: ='OM Rent Roll'!C13 -> 1350 | D28: =C28/NRA -> 0.075503356 | E28: ='OM Rent Roll'!D13 -> NNN | F28: ='OM Rent Roll'!G13 -> 0 | G28: ='OM Rent Roll'!H13 -> 0 | H28: =IF('OM Rent Roll'!E13=0,"",'OM Rent Roll'!E13) | I28: =IF('OM Rent Roll'!F13=0,"",'OM Rent Roll'!F13) | J28: 1 | K28: 60 | L28: 36 | M28: =Rent_Growth -> 0.03 | N28: 0 | O28: 6 | P28: 25 | Q28: 25 | R28: 0.06 | S28: 0.03 | T28: N | U28: 6 | V28: =IF(OR($I$28="",$I$28=0),IF(V$2<$U$28,"Vacant","Relet"),IF(ISTEXT($I$28),IF($U$28>0,IF(V$2<$U$28,"Downtime","Relet"),IF(V$2<=$O$28,"Downtime","Relet")),IF($I$28<=Close_Date,IF(V$2<=$O$28,"Downtime","Relet"),IF(V$2<=DATEDIF(Close_Date,$I$28,"M"),"In-Term",IF(V$2<=DATEDIF(Close_Date,$I$28,"M")+$O$28,"Downtime","Relet"))))) -> Vacant | W28: =IF(OR($I$28="",$I$28=0),IF(W$2<$U$28,"Vacant","Relet"),IF(ISTEXT($I$28),IF($U$28>0,IF(W$2<$U$28,"Downtime","Relet"),IF(W$2<=$O$28,"Downtime","Relet")),IF($I$28<=Close_Date,IF(W$2<=$O$28,"Downtime","Relet"),IF(W$2<=DATEDIF(Close_Date,$I$28,"M"),"In-Term",IF(W$2<=DATEDIF(Close_Date,$I$28,"M")+$O$28,"Downtime","Relet"))))) -> Vacant | X28: =IF(OR($I$28="",$I$28=0),IF(X$2<$U$28,"Vacant","Relet"),IF(ISTEXT($I$28),IF($U$28>0,IF(X$2<$U$28,"Downtime","Relet"),IF(X$2<=$O$28,"Downtime","Relet")),IF($I$28<=Close_Date,IF(X$2<=$O$28,"Downtime","Relet"),IF(X$2<=DATEDIF(Close_Date,$I$28,"M"),"In-Term",IF(X$2<=DATEDIF(Close_Date,$I$28,"M")+$O$28,"Downtime","Relet"))))) -> Vacant | Y28: =IF(OR($I$28="",$I$28=0),IF(Y$2<$U$28,"Vacant","Relet"),IF(ISTEXT($I$28),IF($U$28>0,IF(Y$2<$U$28,"Downtime","Relet"),IF(Y$2<=$O$28,"Downtime","Relet")),IF($I$28<=Close_Date,IF(Y$2<=$O$28,"Downtime","Relet"),IF(Y$2<=DATEDIF(Close_Date,$I$28,"M"),"In-Term",IF(Y$2<=DATEDIF(Close_Date,$I$28,"M")+$O$28,"Downtime","Relet"))))) -> Vacant | Z28: =IF(OR($I$28="",$I$28=0),IF(Z$2<$U$28,"Vacant","Relet"),IF(ISTEXT($I$28),IF($U$28>0,IF(Z$2<$U$28,"Downtime","Relet"),IF(Z$2<=$O$28,"Downtime","Relet")),IF($I$28<=Close_Date,IF(Z$2<=$O$28,"Downtime","Relet"),IF(Z$2<=DATEDIF(Close_Date,$I$28,"M"),"In-Term",IF(Z$2<=DATEDIF(Close_Date,$I$28,"M")+$O$28,"Downtime","Relet"))))) -> Vacant | AA28: =IF(OR($I$28="",$I$28=0),IF(AA$2<$U$28,"Vacant","Relet"),IF(ISTEXT($I$28),IF($U$28>0,IF(AA$2<$U$28,"Downtime","Relet"),IF(AA$2<=$O$28,"Downtime","Relet")),IF($I$28<=Close_Date,IF(AA$2<=$O$28,"Downtime","Relet"),IF(AA$2<=DATEDIF(Close_Date,$I$28,"M"),"In-Term",IF(AA$2<=DATEDIF(Close_Date,$I$28,"M")+$O$28,"Downtime","Relet"))))) -> Relet | AB28: =IF(OR($I$28="",$I$28=0),IF(AB$2<$U$28,"Vacant","Relet"),IF(ISTEXT($I$28),IF($U$28>0,IF(AB$2<$U$28,"Downtime","Relet"),IF(AB$2<=$O$28,"Downtime","Relet")),IF($I$28<=Close_Date,IF(AB$2<=$O$28,"Downtime","Relet"),IF(AB$2<=DATEDIF(Close_Date,$I$28,"M"),"In-Term",IF(AB$2<=DATEDIF(Close_Date,$I$28,"M")+$O$28,"Downtime","Relet"))))) -> Relet | AC28: =IF(OR($I$28="",$I$28=0),IF(AC$2<$U$28,"Vacant","Relet"),IF(ISTEXT($I$28),IF($U$28>0,IF(AC$2<$U$28,"Downtime","Relet"),IF(AC$2<=$O$28,"Downtime","Relet")),IF($I$28<=Close_Date,IF(AC$2<=$O$28,"Downtime","Relet"),IF(AC$2<=DATEDIF(Close_Date,$I$28,"M"),"In-Term",IF(AC$2<=DATEDIF(Close_Date,$I$28,"M")+$O$28,"Downtime","Relet"))))) -> Relet | ... CD28: =IF(OR($I$28="",$I$28=0),IF(CD$2<$U$28,"Vacant","Relet"),IF(ISTEXT($I$28),IF($U$28>0,IF(CD$2<$U$28,"Downtime","Relet"),IF(CD$2<=$O$28,"Downtime","Relet")),IF($I$28<=Close_Date,IF(CD$2<=$O$28,"Downtime","Relet"),IF(CD$2<=DATEDIF(Close_Date,$I$28,"M"),"In-Term",IF(CD$2<=DATEDIF(Close_Date,$I$28,"M")+$O$28,"Downtime","Relet"))))) -> Relet
B29: Rate | V29: =IF(V28="Vacant",0,IF(V28="In-Term",$F$28*(1+$G$28)^(INT((V$2-1)/12)),IF(AND(V28="Downtime",ISTEXT($I$28)),$F$28,$J$28*(1+$M$28)^(INT((V$2-1)/12))))) -> 0 | W29: =IF(W28="Vacant",0,IF(W28="In-Term",$F$28*(1+$G$28)^(INT((W$2-1)/12)),IF(AND(W28="Downtime",ISTEXT($I$28)),$F$28,$J$28*(1+$M$28)^(INT((W$2-1)/12))))) -> 0 | X29: =IF(X28="Vacant",0,IF(X28="In-Term",$F$28*(1+$G$28)^(INT((X$2-1)/12)),IF(AND(X28="Downtime",ISTEXT($I$28)),$F$28,$J$28*(1+$M$28)^(INT((X$2-1)/12))))) -> 0 | Y29: =IF(Y28="Vacant",0,IF(Y28="In-Term",$F$28*(1+$G$28)^(INT((Y$2-1)/12)),IF(AND(Y28="Downtime",ISTEXT($I$28)),$F$28,$J$28*(1+$M$28)^(INT((Y$2-1)/12))))) -> 0 | Z29: =IF(Z28="Vacant",0,IF(Z28="In-Term",$F$28*(1+$G$28)^(INT((Z$2-1)/12)),IF(AND(Z28="Downtime",ISTEXT($I$28)),$F$28,$J$28*(1+$M$28)^(INT((Z$2-1)/12))))) -> 0 | AA29: =IF(AA28="Vacant",0,IF(AA28="In-Term",$F$28*(1+$G$28)^(INT((AA$2-1)/12)),IF(AND(AA28="Downtime",ISTEXT($I$28)),$F$28,$J$28*(1+$M$28)^(INT((AA$2-1)/12))))) -> 1 | AB29: =IF(AB28="Vacant",0,IF(AB28="In-Term",$F$28*(1+$G$28)^(INT((AB$2-1)/12)),IF(AND(AB28="Downtime",ISTEXT($I$28)),$F$28,$J$28*(1+$M$28)^(INT((AB$2-1)/12))))) -> 1 | AC29: =IF(AC28="Vacant",0,IF(AC28="In-Term",$F$28*(1+$G$28)^(INT((AC$2-1)/12)),IF(AND(AC28="Downtime",ISTEXT($I$28)),$F$28,$J$28*(1+$M$28)^(INT((AC$2-1)/12))))) -> 1 | ... CD29: =IF(CD28="Vacant",0,IF(CD28="In-Term",$F$28*(1+$G$28)^(INT((CD$2-1)/12)),IF(AND(CD28="Downtime",ISTEXT($I$28)),$F$28,$J$28*(1+$M$28)^(INT((CD$2-1)/12))))) -> 1.1592741
B30: Eff$ | V30: =IF(V28="Vacant",0,IF(V28="Downtime",$N$28*V29*$C$28,V29*$C$28)) -> 0 | W30: =IF(W28="Vacant",0,IF(W28="Downtime",$N$28*W29*$C$28,W29*$C$28)) -> 0 | X30: =IF(X28="Vacant",0,IF(X28="Downtime",$N$28*X29*$C$28,X29*$C$28)) -> 0 | Y30: =IF(Y28="Vacant",0,IF(Y28="Downtime",$N$28*Y29*$C$28,Y29*$C$28)) -> 0 | Z30: =IF(Z28="Vacant",0,IF(Z28="Downtime",$N$28*Z29*$C$28,Z29*$C$28)) -> 0 | AA30: =IF(AA28="Vacant",0,IF(AA28="Downtime",$N$28*AA29*$C$28,AA29*$C$28)) -> 1350 | AB30: =IF(AB28="Vacant",0,IF(AB28="Downtime",$N$28*AB29*$C$28,AB29*$C$28)) -> 1350 | AC30: =IF(AC28="Vacant",0,IF(AC28="Downtime",$N$28*AC29*$C$28,AC29*$C$28)) -> 1350 | ... CD30: =IF(CD28="Vacant",0,IF(CD28="Downtime",$N$28*CD29*$C$28,CD29*$C$28)) -> 1565.02
A31: ='OM Rent Roll'!A14 -> 4955 A | B31: ='OM Rent Roll'!B14 -> Sharing & Caring | C31: ='OM Rent Roll'!C14 -> 1350 | D31: =C31/NRA -> 0.075503356 | E31: ='OM Rent Roll'!D14 -> MG | F31: ='OM Rent Roll'!G14 -> 1.0185185 | G31: ='OM Rent Roll'!H14 -> 0 | H31: =IF('OM Rent Roll'!E14=0,"",'OM Rent Roll'!E14) -> MTM | I31: =IF('OM Rent Roll'!F14=0,"",'OM Rent Roll'!F14) -> MTM | J31: 1 | K31: 60 | L31: 36 | M31: =Rent_Growth -> 0.03 | N31: 0.5 | O31: 6 | P31: 25 | Q31: 5 | R31: 0.06 | S31: 0.03 | T31: Y | U31: 0 | V31: =IF(OR($I$31="",$I$31=0),IF(V$2<$U$31,"Vacant","Relet"),IF(ISTEXT($I$31),IF($U$31>0,IF(V$2<$U$31,"Downtime","Relet"),IF(V$2<=$O$31,"Downtime","Relet")),IF($I$31<=Close_Date,IF(V$2<=$O$31,"Downtime","Relet"),IF(V$2<=DATEDIF(Close_Date,$I$31,"M"),"In-Term",IF(V$2<=DATEDIF(Close_Date,$I$31,"M")+$O$31,"Downtime","Relet"))))) -> Downtime | W31: =IF(OR($I$31="",$I$31=0),IF(W$2<$U$31,"Vacant","Relet"),IF(ISTEXT($I$31),IF($U$31>0,IF(W$2<$U$31,"Downtime","Relet"),IF(W$2<=$O$31,"Downtime","Relet")),IF($I$31<=Close_Date,IF(W$2<=$O$31,"Downtime","Relet"),IF(W$2<=DATEDIF(Close_Date,$I$31,"M"),"In-Term",IF(W$2<=DATEDIF(Close_Date,$I$31,"M")+$O$31,"Downtime","Relet"))))) -> Downtime | X31: =IF(OR($I$31="",$I$31=0),IF(X$2<$U$31,"Vacant","Relet"),IF(ISTEXT($I$31),IF($U$31>0,IF(X$2<$U$31,"Downtime","Relet"),IF(X$2<=$O$31,"Downtime","Relet")),IF($I$31<=Close_Date,IF(X$2<=$O$31,"Downtime","Relet"),IF(X$2<=DATEDIF(Close_Date,$I$31,"M"),"In-Term",IF(X$2<=DATEDIF(Close_Date,$I$31,"M")+$O$31,"Downtime","Relet"))))) -> Downtime | Y31: =IF(OR($I$31="",$I$31=0),IF(Y$2<$U$31,"Vacant","Relet"),IF(ISTEXT($I$31),IF($U$31>0,IF(Y$2<$U$31,"Downtime","Relet"),IF(Y$2<=$O$31,"Downtime","Relet")),IF($I$31<=Close_Date,IF(Y$2<=$O$31,"Downtime","Relet"),IF(Y$2<=DATEDIF(Close_Date,$I$31,"M"),"In-Term",IF(Y$2<=DATEDIF(Close_Date,$I$31,"M")+$O$31,"Downtime","Relet"))))) -> Downtime | Z31: =IF(OR($I$31="",$I$31=0),IF(Z$2<$U$31,"Vacant","Relet"),IF(ISTEXT($I$31),IF($U$31>0,IF(Z$2<$U$31,"Downtime","Relet"),IF(Z$2<=$O$31,"Downtime","Relet")),IF($I$31<=Close_Date,IF(Z$2<=$O$31,"Downtime","Relet"),IF(Z$2<=DATEDIF(Close_Date,$I$31,"M"),"In-Term",IF(Z$2<=DATEDIF(Close_Date,$I$31,"M")+$O$31,"Downtime","Relet"))))) -> Downtime | AA31: =IF(OR($I$31="",$I$31=0),IF(AA$2<$U$31,"Vacant","Relet"),IF(ISTEXT($I$31),IF($U$31>0,IF(AA$2<$U$31,"Downtime","Relet"),IF(AA$2<=$O$31,"Downtime","Relet")),IF($I$31<=Close_Date,IF(AA$2<=$O$31,"Downtime","Relet"),IF(AA$2<=DATEDIF(Close_Date,$I$31,"M"),"In-Term",IF(AA$2<=DATEDIF(Close_Date,$I$31,"M")+$O$31,"Downtime","Relet"))))) -> Downtime | AB31: =IF(OR($I$31="",$I$31=0),IF(AB$2<$U$31,"Vacant","Relet"),IF(ISTEXT($I$31),IF($U$31>0,IF(AB$2<$U$31,"Downtime","Relet"),IF(AB$2<=$O$31,"Downtime","Relet")),IF($I$31<=Close_Date,IF(AB$2<=$O$31,"Downtime","Relet"),IF(AB$2<=DATEDIF(Close_Date,$I$31,"M"),"In-Term",IF(AB$2<=DATEDIF(Close_Date,$I$31,"M")+$O$31,"Downtime","Relet"))))) -> Relet | AC31: =IF(OR($I$31="",$I$31=0),IF(AC$2<$U$31,"Vacant","Relet"),IF(ISTEXT($I$31),IF($U$31>0,IF(AC$2<$U$31,"Downtime","Relet"),IF(AC$2<=$O$31,"Downtime","Relet")),IF($I$31<=Close_Date,IF(AC$2<=$O$31,"Downtime","Relet"),IF(AC$2<=DATEDIF(Close_Date,$I$31,"M"),"In-Term",IF(AC$2<=DATEDIF(Close_Date,$I$31,"M")+$O$31,"Downtime","Relet"))))) -> Relet | ... CD31: =IF(OR($I$31="",$I$31=0),IF(CD$2<$U$31,"Vacant","Relet"),IF(ISTEXT($I$31),IF($U$31>0,IF(CD$2<$U$31,"Downtime","Relet"),IF(CD$2<=$O$31,"Downtime","Relet")),IF($I$31<=Close_Date,IF(CD$2<=$O$31,"Downtime","Relet"),IF(CD$2<=DATEDIF(Close_Date,$I$31,"M"),"In-Term",IF(CD$2<=DATEDIF(Close_Date,$I$31,"M")+$O$31,"Downtime","Relet"))))) -> Relet
B32: Rate | V32: =IF(V31="Vacant",0,IF(V31="In-Term",$F$31*(1+$G$31)^(INT((V$2-1)/12)),IF(AND(V31="Downtime",ISTEXT($I$31)),$F$31,$J$31*(1+$M$31)^(INT((V$2-1)/12))))) -> 1.0185185 | W32: =IF(W31="Vacant",0,IF(W31="In-Term",$F$31*(1+$G$31)^(INT((W$2-1)/12)),IF(AND(W31="Downtime",ISTEXT($I$31)),$F$31,$J$31*(1+$M$31)^(INT((W$2-1)/12))))) -> 1.0185185 | X32: =IF(X31="Vacant",0,IF(X31="In-Term",$F$31*(1+$G$31)^(INT((X$2-1)/12)),IF(AND(X31="Downtime",ISTEXT($I$31)),$F$31,$J$31*(1+$M$31)^(INT((X$2-1)/12))))) -> 1.0185185 | Y32: =IF(Y31="Vacant",0,IF(Y31="In-Term",$F$31*(1+$G$31)^(INT((Y$2-1)/12)),IF(AND(Y31="Downtime",ISTEXT($I$31)),$F$31,$J$31*(1+$M$31)^(INT((Y$2-1)/12))))) -> 1.0185185 | Z32: =IF(Z31="Vacant",0,IF(Z31="In-Term",$F$31*(1+$G$31)^(INT((Z$2-1)/12)),IF(AND(Z31="Downtime",ISTEXT($I$31)),$F$31,$J$31*(1+$M$31)^(INT((Z$2-1)/12))))) -> 1.0185185 | AA32: =IF(AA31="Vacant",0,IF(AA31="In-Term",$F$31*(1+$G$31)^(INT((AA$2-1)/12)),IF(AND(AA31="Downtime",ISTEXT($I$31)),$F$31,$J$31*(1+$M$31)^(INT((AA$2-1)/12))))) -> 1.0185185 | AB32: =IF(AB31="Vacant",0,IF(AB31="In-Term",$F$31*(1+$G$31)^(INT((AB$2-1)/12)),IF(AND(AB31="Downtime",ISTEXT($I$31)),$F$31,$J$31*(1+$M$31)^(INT((AB$2-1)/12))))) -> 1 | AC32: =IF(AC31="Vacant",0,IF(AC31="In-Term",$F$31*(1+$G$31)^(INT((AC$2-1)/12)),IF(AND(AC31="Downtime",ISTEXT($I$31)),$F$31,$J$31*(1+$M$31)^(INT((AC$2-1)/12))))) -> 1 | ... CD32: =IF(CD31="Vacant",0,IF(CD31="In-Term",$F$31*(1+$G$31)^(INT((CD$2-1)/12)),IF(AND(CD31="Downtime",ISTEXT($I$31)),$F$31,$J$31*(1+$M$31)^(INT((CD$2-1)/12))))) -> 1.1592741
B33: Eff$ | V33: =IF(V31="Vacant",0,IF(V31="Downtime",$N$31*V32*$C$31,V32*$C$31)) -> 687.5 | W33: =IF(W31="Vacant",0,IF(W31="Downtime",$N$31*W32*$C$31,W32*$C$31)) -> 687.5 | X33: =IF(X31="Vacant",0,IF(X31="Downtime",$N$31*X32*$C$31,X32*$C$31)) -> 687.5 | Y33: =IF(Y31="Vacant",0,IF(Y31="Downtime",$N$31*Y32*$C$31,Y32*$C$31)) -> 687.5 | Z33: =IF(Z31="Vacant",0,IF(Z31="Downtime",$N$31*Z32*$C$31,Z32*$C$31)) -> 687.5 | AA33: =IF(AA31="Vacant",0,IF(AA31="Downtime",$N$31*AA32*$C$31,AA32*$C$31)) -> 687.5 | AB33: =IF(AB31="Vacant",0,IF(AB31="Downtime",$N$31*AB32*$C$31,AB32*$C$31)) -> 1350 | AC33: =IF(AC31="Vacant",0,IF(AC31="Downtime",$N$31*AC32*$C$31,AC32*$C$31)) -> 1350 | ... CD33: =IF(CD31="Vacant",0,IF(CD31="Downtime",$N$31*CD32*$C$31,CD32*$C$31)) -> 1565.02
A34: ='OM Rent Roll'!A15 -> 4955 B | B34: ='OM Rent Roll'!B15 -> Spoteless Cleaners | C34: ='OM Rent Roll'!C15 -> 1310 | D34: =C34/NRA -> 0.073266219 | E34: ='OM Rent Roll'!D15 -> NNN | F34: ='OM Rent Roll'!G15 -> 0.8259542 | G34: ='OM Rent Roll'!H15 -> 0 | H34: =IF('OM Rent Roll'!E15=0,"",'OM Rent Roll'!E15) -> MTM | I34: =IF('OM Rent Roll'!F15=0,"",'OM Rent Roll'!F15) -> MTM | J34: 1 | K34: 60 | L34: 36 | M34: =Rent_Growth -> 0.03 | N34: 0.5 | O34: 6 | P34: 25 | Q34: 5 | R34: 0.06 | S34: 0.03 | T34: N | U34: 0 | V34: =IF(OR($I$34="",$I$34=0),IF(V$2<$U$34,"Vacant","Relet"),IF(ISTEXT($I$34),IF($U$34>0,IF(V$2<$U$34,"Downtime","Relet"),IF(V$2<=$O$34,"Downtime","Relet")),IF($I$34<=Close_Date,IF(V$2<=$O$34,"Downtime","Relet"),IF(V$2<=DATEDIF(Close_Date,$I$34,"M"),"In-Term",IF(V$2<=DATEDIF(Close_Date,$I$34,"M")+$O$34,"Downtime","Relet"))))) -> Downtime | W34: =IF(OR($I$34="",$I$34=0),IF(W$2<$U$34,"Vacant","Relet"),IF(ISTEXT($I$34),IF($U$34>0,IF(W$2<$U$34,"Downtime","Relet"),IF(W$2<=$O$34,"Downtime","Relet")),IF($I$34<=Close_Date,IF(W$2<=$O$34,"Downtime","Relet"),IF(W$2<=DATEDIF(Close_Date,$I$34,"M"),"In-Term",IF(W$2<=DATEDIF(Close_Date,$I$34,"M")+$O$34,"Downtime","Relet"))))) -> Downtime | X34: =IF(OR($I$34="",$I$34=0),IF(X$2<$U$34,"Vacant","Relet"),IF(ISTEXT($I$34),IF($U$34>0,IF(X$2<$U$34,"Downtime","Relet"),IF(X$2<=$O$34,"Downtime","Relet")),IF($I$34<=Close_Date,IF(X$2<=$O$34,"Downtime","Relet"),IF(X$2<=DATEDIF(Close_Date,$I$34,"M"),"In-Term",IF(X$2<=DATEDIF(Close_Date,$I$34,"M")+$O$34,"Downtime","Relet"))))) -> Downtime | Y34: =IF(OR($I$34="",$I$34=0),IF(Y$2<$U$34,"Vacant","Relet"),IF(ISTEXT($I$34),IF($U$34>0,IF(Y$2<$U$34,"Downtime","Relet"),IF(Y$2<=$O$34,"Downtime","Relet")),IF($I$34<=Close_Date,IF(Y$2<=$O$34,"Downtime","Relet"),IF(Y$2<=DATEDIF(Close_Date,$I$34,"M"),"In-Term",IF(Y$2<=DATEDIF(Close_Date,$I$34,"M")+$O$34,"Downtime","Relet"))))) -> Downtime | Z34: =IF(OR($I$34="",$I$34=0),IF(Z$2<$U$34,"Vacant","Relet"),IF(ISTEXT($I$34),IF($U$34>0,IF(Z$2<$U$34,"Downtime","Relet"),IF(Z$2<=$O$34,"Downtime","Relet")),IF($I$34<=Close_Date,IF(Z$2<=$O$34,"Downtime","Relet"),IF(Z$2<=DATEDIF(Close_Date,$I$34,"M"),"In-Term",IF(Z$2<=DATEDIF(Close_Date,$I$34,"M")+$O$34,"Downtime","Relet"))))) -> Downtime | AA34: =IF(OR($I$34="",$I$34=0),IF(AA$2<$U$34,"Vacant","Relet"),IF(ISTEXT($I$34),IF($U$34>0,IF(AA$2<$U$34,"Downtime","Relet"),IF(AA$2<=$O$34,"Downtime","Relet")),IF($I$34<=Close_Date,IF(AA$2<=$O$34,"Downtime","Relet"),IF(AA$2<=DATEDIF(Close_Date,$I$34,"M"),"In-Term",IF(AA$2<=DATEDIF(Close_Date,$I$34,"M")+$O$34,"Downtime","Relet"))))) -> Downtime | AB34: =IF(OR($I$34="",$I$34=0),IF(AB$2<$U$34,"Vacant","Relet"),IF(ISTEXT($I$34),IF($U$34>0,IF(AB$2<$U$34,"Downtime","Relet"),IF(AB$2<=$O$34,"Downtime","Relet")),IF($I$34<=Close_Date,IF(AB$2<=$O$34,"Downtime","Relet"),IF(AB$2<=DATEDIF(Close_Date,$I$34,"M"),"In-Term",IF(AB$2<=DATEDIF(Close_Date,$I$34,"M")+$O$34,"Downtime","Relet"))))) -> Relet | AC34: =IF(OR($I$34="",$I$34=0),IF(AC$2<$U$34,"Vacant","Relet"),IF(ISTEXT($I$34),IF($U$34>0,IF(AC$2<$U$34,"Downtime","Relet"),IF(AC$2<=$O$34,"Downtime","Relet")),IF($I$34<=Close_Date,IF(AC$2<=$O$34,"Downtime","Relet"),IF(AC$2<=DATEDIF(Close_Date,$I$34,"M"),"In-Term",IF(AC$2<=DATEDIF(Close_Date,$I$34,"M")+$O$34,"Downtime","Relet"))))) -> Relet | ... CD34: =IF(OR($I$34="",$I$34=0),IF(CD$2<$U$34,"Vacant","Relet"),IF(ISTEXT($I$34),IF($U$34>0,IF(CD$2<$U$34,"Downtime","Relet"),IF(CD$2<=$O$34,"Downtime","Relet")),IF($I$34<=Close_Date,IF(CD$2<=$O$34,"Downtime","Relet"),IF(CD$2<=DATEDIF(Close_Date,$I$34,"M"),"In-Term",IF(CD$2<=DATEDIF(Close_Date,$I$34,"M")+$O$34,"Downtime","Relet"))))) -> Relet
B35: Rate | V35: =IF(V34="Vacant",0,IF(V34="In-Term",$F$34*(1+$G$34)^(INT((V$2-1)/12)),IF(AND(V34="Downtime",ISTEXT($I$34)),$F$34,$J$34*(1+$M$34)^(INT((V$2-1)/12))))) -> 0.8259542 | W35: =IF(W34="Vacant",0,IF(W34="In-Term",$F$34*(1+$G$34)^(INT((W$2-1)/12)),IF(AND(W34="Downtime",ISTEXT($I$34)),$F$34,$J$34*(1+$M$34)^(INT((W$2-1)/12))))) -> 0.8259542 | X35: =IF(X34="Vacant",0,IF(X34="In-Term",$F$34*(1+$G$34)^(INT((X$2-1)/12)),IF(AND(X34="Downtime",ISTEXT($I$34)),$F$34,$J$34*(1+$M$34)^(INT((X$2-1)/12))))) -> 0.8259542 | Y35: =IF(Y34="Vacant",0,IF(Y34="In-Term",$F$34*(1+$G$34)^(INT((Y$2-1)/12)),IF(AND(Y34="Downtime",ISTEXT($I$34)),$F$34,$J$34*(1+$M$34)^(INT((Y$2-1)/12))))) -> 0.8259542 | Z35: =IF(Z34="Vacant",0,IF(Z34="In-Term",$F$34*(1+$G$34)^(INT((Z$2-1)/12)),IF(AND(Z34="Downtime",ISTEXT($I$34)),$F$34,$J$34*(1+$M$34)^(INT((Z$2-1)/12))))) -> 0.8259542 | AA35: =IF(AA34="Vacant",0,IF(AA34="In-Term",$F$34*(1+$G$34)^(INT((AA$2-1)/12)),IF(AND(AA34="Downtime",ISTEXT($I$34)),$F$34,$J$34*(1+$M$34)^(INT((AA$2-1)/12))))) -> 0.8259542 | AB35: =IF(AB34="Vacant",0,IF(AB34="In-Term",$F$34*(1+$G$34)^(INT((AB$2-1)/12)),IF(AND(AB34="Downtime",ISTEXT($I$34)),$F$34,$J$34*(1+$M$34)^(INT((AB$2-1)/12))))) -> 1 | AC35: =IF(AC34="Vacant",0,IF(AC34="In-Term",$F$34*(1+$G$34)^(INT((AC$2-1)/12)),IF(AND(AC34="Downtime",ISTEXT($I$34)),$F$34,$J$34*(1+$M$34)^(INT((AC$2-1)/12))))) -> 1 | ... CD35: =IF(CD34="Vacant",0,IF(CD34="In-Term",$F$34*(1+$G$34)^(INT((CD$2-1)/12)),IF(AND(CD34="Downtime",ISTEXT($I$34)),$F$34,$J$34*(1+$M$34)^(INT((CD$2-1)/12))))) -> 1.1592741
B36: Eff$ | V36: =IF(V34="Vacant",0,IF(V34="Downtime",$N$34*V35*$C$34,V35*$C$34)) -> 541 | W36: =IF(W34="Vacant",0,IF(W34="Downtime",$N$34*W35*$C$34,W35*$C$34)) -> 541 | X36: =IF(X34="Vacant",0,IF(X34="Downtime",$N$34*X35*$C$34,X35*$C$34)) -> 541 | Y36: =IF(Y34="Vacant",0,IF(Y34="Downtime",$N$34*Y35*$C$34,Y35*$C$34)) -> 541 | Z36: =IF(Z34="Vacant",0,IF(Z34="Downtime",$N$34*Z35*$C$34,Z35*$C$34)) -> 541 | AA36: =IF(AA34="Vacant",0,IF(AA34="Downtime",$N$34*AA35*$C$34,AA35*$C$34)) -> 541 | AB36: =IF(AB34="Vacant",0,IF(AB34="Downtime",$N$34*AB35*$C$34,AB35*$C$34)) -> 1310 | AC36: =IF(AC34="Vacant",0,IF(AC34="Downtime",$N$34*AC35*$C$34,AC35*$C$34)) -> 1310 | ... CD36: =IF(CD34="Vacant",0,IF(CD34="Downtime",$N$34*CD35*$C$34,CD35*$C$34)) -> 1518.649
A37: ='OM Rent Roll'!A16 -> 4955 C | B37: ='OM Rent Roll'!B16 -> Dawn's Pet Palace | C37: ='OM Rent Roll'!C16 -> 1880 | D37: =C37/NRA -> 0.10514541 | E37: ='OM Rent Roll'!D16 -> NNN | F37: ='OM Rent Roll'!G16 -> 0.80106383 | G37: ='OM Rent Roll'!H16 -> 0.030736144 | H37: =IF('OM Rent Roll'!E16=0,"",'OM Rent Roll'!E16) -> 45992 | I37: =IF('OM Rent Roll'!F16=0,"",'OM Rent Roll'!F16) -> 47087 | J37: 1 | K37: 60 | L37: 36 | M37: =Rent_Growth -> 0.03 | N37: 0.75 | O37: 6 | P37: 25 | Q37: 5 | R37: 0.06 | S37: 0.03 | T37: N | U37: 0 | V37: =IF(OR($I$37="",$I$37=0),IF(V$2<$U$37,"Vacant","Relet"),IF(ISTEXT($I$37),IF($U$37>0,IF(V$2<$U$37,"Downtime","Relet"),IF(V$2<=$O$37,"Downtime","Relet")),IF($I$37<=Close_Date,IF(V$2<=$O$37,"Downtime","Relet"),IF(V$2<=DATEDIF(Close_Date,$I$37,"M"),"In-Term",IF(V$2<=DATEDIF(Close_Date,$I$37,"M")+$O$37,"Downtime","Relet"))))) -> In-Term | W37: =IF(OR($I$37="",$I$37=0),IF(W$2<$U$37,"Vacant","Relet"),IF(ISTEXT($I$37),IF($U$37>0,IF(W$2<$U$37,"Downtime","Relet"),IF(W$2<=$O$37,"Downtime","Relet")),IF($I$37<=Close_Date,IF(W$2<=$O$37,"Downtime","Relet"),IF(W$2<=DATEDIF(Close_Date,$I$37,"M"),"In-Term",IF(W$2<=DATEDIF(Close_Date,$I$37,"M")+$O$37,"Downtime","Relet"))))) -> In-Term | X37: =IF(OR($I$37="",$I$37=0),IF(X$2<$U$37,"Vacant","Relet"),IF(ISTEXT($I$37),IF($U$37>0,IF(X$2<$U$37,"Downtime","Relet"),IF(X$2<=$O$37,"Downtime","Relet")),IF($I$37<=Close_Date,IF(X$2<=$O$37,"Downtime","Relet"),IF(X$2<=DATEDIF(Close_Date,$I$37,"M"),"In-Term",IF(X$2<=DATEDIF(Close_Date,$I$37,"M")+$O$37,"Downtime","Relet"))))) -> In-Term | Y37: =IF(OR($I$37="",$I$37=0),IF(Y$2<$U$37,"Vacant","Relet"),IF(ISTEXT($I$37),IF($U$37>0,IF(Y$2<$U$37,"Downtime","Relet"),IF(Y$2<=$O$37,"Downtime","Relet")),IF($I$37<=Close_Date,IF(Y$2<=$O$37,"Downtime","Relet"),IF(Y$2<=DATEDIF(Close_Date,$I$37,"M"),"In-Term",IF(Y$2<=DATEDIF(Close_Date,$I$37,"M")+$O$37,"Downtime","Relet"))))) -> In-Term | Z37: =IF(OR($I$37="",$I$37=0),IF(Z$2<$U$37,"Vacant","Relet"),IF(ISTEXT($I$37),IF($U$37>0,IF(Z$2<$U$37,"Downtime","Relet"),IF(Z$2<=$O$37,"Downtime","Relet")),IF($I$37<=Close_Date,IF(Z$2<=$O$37,"Downtime","Relet"),IF(Z$2<=DATEDIF(Close_Date,$I$37,"M"),"In-Term",IF(Z$2<=DATEDIF(Close_Date,$I$37,"M")+$O$37,"Downtime","Relet"))))) -> In-Term | AA37: =IF(OR($I$37="",$I$37=0),IF(AA$2<$U$37,"Vacant","Relet"),IF(ISTEXT($I$37),IF($U$37>0,IF(AA$2<$U$37,"Downtime","Relet"),IF(AA$2<=$O$37,"Downtime","Relet")),IF($I$37<=Close_Date,IF(AA$2<=$O$37,"Downtime","Relet"),IF(AA$2<=DATEDIF(Close_Date,$I$37,"M"),"In-Term",IF(AA$2<=DATEDIF(Close_Date,$I$37,"M")+$O$37,"Downtime","Relet"))))) -> In-Term | AB37: =IF(OR($I$37="",$I$37=0),IF(AB$2<$U$37,"Vacant","Relet"),IF(ISTEXT($I$37),IF($U$37>0,IF(AB$2<$U$37,"Downtime","Relet"),IF(AB$2<=$O$37,"Downtime","Relet")),IF($I$37<=Close_Date,IF(AB$2<=$O$37,"Downtime","Relet"),IF(AB$2<=DATEDIF(Close_Date,$I$37,"M"),"In-Term",IF(AB$2<=DATEDIF(Close_Date,$I$37,"M")+$O$37,"Downtime","Relet"))))) -> In-Term | AC37: =IF(OR($I$37="",$I$37=0),IF(AC$2<$U$37,"Vacant","Relet"),IF(ISTEXT($I$37),IF($U$37>0,IF(AC$2<$U$37,"Downtime","Relet"),IF(AC$2<=$O$37,"Downtime","Relet")),IF($I$37<=Close_Date,IF(AC$2<=$O$37,"Downtime","Relet"),IF(AC$2<=DATEDIF(Close_Date,$I$37,"M"),"In-Term",IF(AC$2<=DATEDIF(Close_Date,$I$37,"M")+$O$37,"Downtime","Relet"))))) -> In-Term | ... CD37: =IF(OR($I$37="",$I$37=0),IF(CD$2<$U$37,"Vacant","Relet"),IF(ISTEXT($I$37),IF($U$37>0,IF(CD$2<$U$37,"Downtime","Relet"),IF(CD$2<=$O$37,"Downtime","Relet")),IF($I$37<=Close_Date,IF(CD$2<=$O$37,"Downtime","Relet"),IF(CD$2<=DATEDIF(Close_Date,$I$37,"M"),"In-Term",IF(CD$2<=DATEDIF(Close_Date,$I$37,"M")+$O$37,"Downtime","Relet"))))) -> Relet
B38: Rate | V38: =IF(V37="Vacant",0,IF(V37="In-Term",$F$37*(1+$G$37)^(INT((V$2-1)/12)),IF(AND(V37="Downtime",ISTEXT($I$37)),$F$37,$J$37*(1+$M$37)^(INT((V$2-1)/12))))) -> 0.80106383 | W38: =IF(W37="Vacant",0,IF(W37="In-Term",$F$37*(1+$G$37)^(INT((W$2-1)/12)),IF(AND(W37="Downtime",ISTEXT($I$37)),$F$37,$J$37*(1+$M$37)^(INT((W$2-1)/12))))) -> 0.80106383 | X38: =IF(X37="Vacant",0,IF(X37="In-Term",$F$37*(1+$G$37)^(INT((X$2-1)/12)),IF(AND(X37="Downtime",ISTEXT($I$37)),$F$37,$J$37*(1+$M$37)^(INT((X$2-1)/12))))) -> 0.80106383 | Y38: =IF(Y37="Vacant",0,IF(Y37="In-Term",$F$37*(1+$G$37)^(INT((Y$2-1)/12)),IF(AND(Y37="Downtime",ISTEXT($I$37)),$F$37,$J$37*(1+$M$37)^(INT((Y$2-1)/12))))) -> 0.80106383 | Z38: =IF(Z37="Vacant",0,IF(Z37="In-Term",$F$37*(1+$G$37)^(INT((Z$2-1)/12)),IF(AND(Z37="Downtime",ISTEXT($I$37)),$F$37,$J$37*(1+$M$37)^(INT((Z$2-1)/12))))) -> 0.80106383 | AA38: =IF(AA37="Vacant",0,IF(AA37="In-Term",$F$37*(1+$G$37)^(INT((AA$2-1)/12)),IF(AND(AA37="Downtime",ISTEXT($I$37)),$F$37,$J$37*(1+$M$37)^(INT((AA$2-1)/12))))) -> 0.80106383 | AB38: =IF(AB37="Vacant",0,IF(AB37="In-Term",$F$37*(1+$G$37)^(INT((AB$2-1)/12)),IF(AND(AB37="Downtime",ISTEXT($I$37)),$F$37,$J$37*(1+$M$37)^(INT((AB$2-1)/12))))) -> 0.80106383 | AC38: =IF(AC37="Vacant",0,IF(AC37="In-Term",$F$37*(1+$G$37)^(INT((AC$2-1)/12)),IF(AND(AC37="Downtime",ISTEXT($I$37)),$F$37,$J$37*(1+$M$37)^(INT((AC$2-1)/12))))) -> 0.80106383 | ... CD38: =IF(CD37="Vacant",0,IF(CD37="In-Term",$F$37*(1+$G$37)^(INT((CD$2-1)/12)),IF(AND(CD37="Downtime",ISTEXT($I$37)),$F$37,$J$37*(1+$M$37)^(INT((CD$2-1)/12))))) -> 1.1592741
B39: Eff$ | V39: =IF(V37="Vacant",0,IF(V37="Downtime",$N$37*V38*$C$37,V38*$C$37)) -> 1506 | W39: =IF(W37="Vacant",0,IF(W37="Downtime",$N$37*W38*$C$37,W38*$C$37)) -> 1506 | X39: =IF(X37="Vacant",0,IF(X37="Downtime",$N$37*X38*$C$37,X38*$C$37)) -> 1506 | Y39: =IF(Y37="Vacant",0,IF(Y37="Downtime",$N$37*Y38*$C$37,Y38*$C$37)) -> 1506 | Z39: =IF(Z37="Vacant",0,IF(Z37="Downtime",$N$37*Z38*$C$37,Z38*$C$37)) -> 1506 | AA39: =IF(AA37="Vacant",0,IF(AA37="Downtime",$N$37*AA38*$C$37,AA38*$C$37)) -> 1506 | AB39: =IF(AB37="Vacant",0,IF(AB37="Downtime",$N$37*AB38*$C$37,AB38*$C$37)) -> 1506 | AC39: =IF(AC37="Vacant",0,IF(AC37="Downtime",$N$37*AC38*$C$37,AC38*$C$37)) -> 1506 | ... CD39: =IF(CD37="Vacant",0,IF(CD37="Downtime",$N$37*CD38*$C$37,CD38*$C$37)) -> 2179.4353
B41: SUMMARY | J41: =AVERAGE(J4:J40) -> 1
B42: Occupied SF | V42: =IF(OR(V4="In-Term",V4="Relet"),$C$4,IF(V4="Downtime",$N$4*$C$4,0))+IF(OR(V7="In-Term",V7="Relet"),$C$7,IF(V7="Downtime",$N$7*$C$7,0))+IF(OR(V10="In-Term",V10="Relet"),$C$10,IF(V10="Downtime",$N$10*$C$10,0))+IF(OR(V13="In-Term",V13="Relet"),$C$13,IF(V13="Downtime",$N$13*$C$13,0))+IF(OR(V16="In-Term",V16="Relet"),$C$16,IF(V16="Downtime",$N$16*$C$16,0))+IF(OR(V19="In-Term",V19="Relet"),$C$19,IF(V19="Downtime",$N$19*$C$19,0))+IF(OR(V22="In-Term",V22="Relet"),$C$22,IF(V22="Downtime",$N$22*$C$22,0))+IF(OR(V25="In-Term",V25="Relet"),$C$25,IF(V25="Downtime",$N$25*$C$25,0))+IF(OR(V28="In-Term",V28="Relet"),$C$28,IF(V28="Downtime",$N$28*$C$28,0))+IF(OR(V31="In-Term",V31="Relet"),$C$31,IF(V31="Downtime",$N$31*$C$31,0))+IF(OR(V34="In-Term",V34="Relet"),$C$34,IF(V34="Downtime",$N$34*$C$34,0))+IF(OR(V37="In-Term",V37="Relet"),$C$37,IF(V37="Downtime",$N$37*$C$37,0)) -> 12485 | W42: =IF(OR(W4="In-Term",W4="Relet"),$C$4,IF(W4="Downtime",$N$4*$C$4,0))+IF(OR(W7="In-Term",W7="Relet"),$C$7,IF(W7="Downtime",$N$7*$C$7,0))+IF(OR(W10="In-Term",W10="Relet"),$C$10,IF(W10="Downtime",$N$10*$C$10,0))+IF(OR(W13="In-Term",W13="Relet"),$C$13,IF(W13="Downtime",$N$13*$C$13,0))+IF(OR(W16="In-Term",W16="Relet"),$C$16,IF(W16="Downtime",$N$16*$C$16,0))+IF(OR(W19="In-Term",W19="Relet"),$C$19,IF(W19="Downtime",$N$19*$C$19,0))+IF(OR(W22="In-Term",W22="Relet"),$C$22,IF(W22="Downtime",$N$22*$C$22,0))+IF(OR(W25="In-Term",W25="Relet"),$C$25,IF(W25="Downtime",$N$25*$C$25,0))+IF(OR(W28="In-Term",W28="Relet"),$C$28,IF(W28="Downtime",$N$28*$C$28,0))+IF(OR(W31="In-Term",W31="Relet"),$C$31,IF(W31="Downtime",$N$31*$C$31,0))+IF(OR(W34="In-Term",W34="Relet"),$C$34,IF(W34="Downtime",$N$34*$C$34,0))+IF(OR(W37="In-Term",W37="Relet"),$C$37,IF(W37="Downtime",$N$37*$C$37,0)) -> 12485 | X42: =IF(OR(X4="In-Term",X4="Relet"),$C$4,IF(X4="Downtime",$N$4*$C$4,0))+IF(OR(X7="In-Term",X7="Relet"),$C$7,IF(X7="Downtime",$N$7*$C$7,0))+IF(OR(X10="In-Term",X10="Relet"),$C$10,IF(X10="Downtime",$N$10*$C$10,0))+IF(OR(X13="In-Term",X13="Relet"),$C$13,IF(X13="Downtime",$N$13*$C$13,0))+IF(OR(X16="In-Term",X16="Relet"),$C$16,IF(X16="Downtime",$N$16*$C$16,0))+IF(OR(X19="In-Term",X19="Relet"),$C$19,IF(X19="Downtime",$N$19*$C$19,0))+IF(OR(X22="In-Term",X22="Relet"),$C$22,IF(X22="Downtime",$N$22*$C$22,0))+IF(OR(X25="In-Term",X25="Relet"),$C$25,IF(X25="Downtime",$N$25*$C$25,0))+IF(OR(X28="In-Term",X28="Relet"),$C$28,IF(X28="Downtime",$N$28*$C$28,0))+IF(OR(X31="In-Term",X31="Relet"),$C$31,IF(X31="Downtime",$N$31*$C$31,0))+IF(OR(X34="In-Term",X34="Relet"),$C$34,IF(X34="Downtime",$N$34*$C$34,0))+IF(OR(X37="In-Term",X37="Relet"),$C$37,IF(X37="Downtime",$N$37*$C$37,0)) -> 12485 | Y42: =IF(OR(Y4="In-Term",Y4="Relet"),$C$4,IF(Y4="Downtime",$N$4*$C$4,0))+IF(OR(Y7="In-Term",Y7="Relet"),$C$7,IF(Y7="Downtime",$N$7*$C$7,0))+IF(OR(Y10="In-Term",Y10="Relet"),$C$10,IF(Y10="Downtime",$N$10*$C$10,0))+IF(OR(Y13="In-Term",Y13="Relet"),$C$13,IF(Y13="Downtime",$N$13*$C$13,0))+IF(OR(Y16="In-Term",Y16="Relet"),$C$16,IF(Y16="Downtime",$N$16*$C$16,0))+IF(OR(Y19="In-Term",Y19="Relet"),$C$19,IF(Y19="Downtime",$N$19*$C$19,0))+IF(OR(Y22="In-Term",Y22="Relet"),$C$22,IF(Y22="Downtime",$N$22*$C$22,0))+IF(OR(Y25="In-Term",Y25="Relet"),$C$25,IF(Y25="Downtime",$N$25*$C$25,0))+IF(OR(Y28="In-Term",Y28="Relet"),$C$28,IF(Y28="Downtime",$N$28*$C$28,0))+IF(OR(Y31="In-Term",Y31="Relet"),$C$31,IF(Y31="Downtime",$N$31*$C$31,0))+IF(OR(Y34="In-Term",Y34="Relet"),$C$34,IF(Y34="Downtime",$N$34*$C$34,0))+IF(OR(Y37="In-Term",Y37="Relet"),$C$37,IF(Y37="Downtime",$N$37*$C$37,0)) -> 12485 | Z42: =IF(OR(Z4="In-Term",Z4="Relet"),$C$4,IF(Z4="Downtime",$N$4*$C$4,0))+IF(OR(Z7="In-Term",Z7="Relet"),$C$7,IF(Z7="Downtime",$N$7*$C$7,0))+IF(OR(Z10="In-Term",Z10="Relet"),$C$10,IF(Z10="Downtime",$N$10*$C$10,0))+IF(OR(Z13="In-Term",Z13="Relet"),$C$13,IF(Z13="Downtime",$N$13*$C$13,0))+IF(OR(Z16="In-Term",Z16="Relet"),$C$16,IF(Z16="Downtime",$N$16*$C$16,0))+IF(OR(Z19="In-Term",Z19="Relet"),$C$19,IF(Z19="Downtime",$N$19*$C$19,0))+IF(OR(Z22="In-Term",Z22="Relet"),$C$22,IF(Z22="Downtime",$N$22*$C$22,0))+IF(OR(Z25="In-Term",Z25="Relet"),$C$25,IF(Z25="Downtime",$N$25*$C$25,0))+IF(OR(Z28="In-Term",Z28="Relet"),$C$28,IF(Z28="Downtime",$N$28*$C$28,0))+IF(OR(Z31="In-Term",Z31="Relet"),$C$31,IF(Z31="Downtime",$N$31*$C$31,0))+IF(OR(Z34="In-Term",Z34="Relet"),$C$34,IF(Z34="Downtime",$N$34*$C$34,0))+IF(OR(Z37="In-Term",Z37="Relet"),$C$37,IF(Z37="Downtime",$N$37*$C$37,0)) -> 12485 | AA42: =IF(OR(AA4="In-Term",AA4="Relet"),$C$4,IF(AA4="Downtime",$N$4*$C$4,0))+IF(OR(AA7="In-Term",AA7="Relet"),$C$7,IF(AA7="Downtime",$N$7*$C$7,0))+IF(OR(AA10="In-Term",AA10="Relet"),$C$10,IF(AA10="Downtime",$N$10*$C$10,0))+IF(OR(AA13="In-Term",AA13="Relet"),$C$13,IF(AA13="Downtime",$N$13*$C$13,0))+IF(OR(AA16="In-Term",AA16="Relet"),$C$16,IF(AA16="Downtime",$N$16*$C$16,0))+IF(OR(AA19="In-Term",AA19="Relet"),$C$19,IF(AA19="Downtime",$N$19*$C$19,0))+IF(OR(AA22="In-Term",AA22="Relet"),$C$22,IF(AA22="Downtime",$N$22*$C$22,0))+IF(OR(AA25="In-Term",AA25="Relet"),$C$25,IF(AA25="Downtime",$N$25*$C$25,0))+IF(OR(AA28="In-Term",AA28="Relet"),$C$28,IF(AA28="Downtime",$N$28*$C$28,0))+IF(OR(AA31="In-Term",AA31="Relet"),$C$31,IF(AA31="Downtime",$N$31*$C$31,0))+IF(OR(AA34="In-Term",AA34="Relet"),$C$34,IF(AA34="Downtime",$N$34*$C$34,0))+IF(OR(AA37="In-Term",AA37="Relet"),$C$37,IF(AA37="Downtime",$N$37*$C$37,0)) -> 14745 | AB42: =IF(OR(AB4="In-Term",AB4="Relet"),$C$4,IF(AB4="Downtime",$N$4*$C$4,0))+IF(OR(AB7="In-Term",AB7="Relet"),$C$7,IF(AB7="Downtime",$N$7*$C$7,0))+IF(OR(AB10="In-Term",AB10="Relet"),$C$10,IF(AB10="Downtime",$N$10*$C$10,0))+IF(OR(AB13="In-Term",AB13="Relet"),$C$13,IF(AB13="Downtime",$N$13*$C$13,0))+IF(OR(AB16="In-Term",AB16="Relet"),$C$16,IF(AB16="Downtime",$N$16*$C$16,0))+IF(OR(AB19="In-Term",AB19="Relet"),$C$19,IF(AB19="Downtime",$N$19*$C$19,0))+IF(OR(AB22="In-Term",AB22="Relet"),$C$22,IF(AB22="Downtime",$N$22*$C$22,0))+IF(OR(AB25="In-Term",AB25="Relet"),$C$25,IF(AB25="Downtime",$N$25*$C$25,0))+IF(OR(AB28="In-Term",AB28="Relet"),$C$28,IF(AB28="Downtime",$N$28*$C$28,0))+IF(OR(AB31="In-Term",AB31="Relet"),$C$31,IF(AB31="Downtime",$N$31*$C$31,0))+IF(OR(AB34="In-Term",AB34="Relet"),$C$34,IF(AB34="Downtime",$N$34*$C$34,0))+IF(OR(AB37="In-Term",AB37="Relet"),$C$37,IF(AB37="Downtime",$N$37*$C$37,0)) -> 17880 | AC42: =IF(OR(AC4="In-Term",AC4="Relet"),$C$4,IF(AC4="Downtime",$N$4*$C$4,0))+IF(OR(AC7="In-Term",AC7="Relet"),$C$7,IF(AC7="Downtime",$N$7*$C$7,0))+IF(OR(AC10="In-Term",AC10="Relet"),$C$10,IF(AC10="Downtime",$N$10*$C$10,0))+IF(OR(AC13="In-Term",AC13="Relet"),$C$13,IF(AC13="Downtime",$N$13*$C$13,0))+IF(OR(AC16="In-Term",AC16="Relet"),$C$16,IF(AC16="Downtime",$N$16*$C$16,0))+IF(OR(AC19="In-Term",AC19="Relet"),$C$19,IF(AC19="Downtime",$N$19*$C$19,0))+IF(OR(AC22="In-Term",AC22="Relet"),$C$22,IF(AC22="Downtime",$N$22*$C$22,0))+IF(OR(AC25="In-Term",AC25="Relet"),$C$25,IF(AC25="Downtime",$N$25*$C$25,0))+IF(OR(AC28="In-Term",AC28="Relet"),$C$28,IF(AC28="Downtime",$N$28*$C$28,0))+IF(OR(AC31="In-Term",AC31="Relet"),$C$31,IF(AC31="Downtime",$N$31*$C$31,0))+IF(OR(AC34="In-Term",AC34="Relet"),$C$34,IF(AC34="Downtime",$N$34*$C$34,0))+IF(OR(AC37="In-Term",AC37="Relet"),$C$37,IF(AC37="Downtime",$N$37*$C$37,0)) -> 17880 | ... CD42: =IF(OR(CD4="In-Term",CD4="Relet"),$C$4,IF(CD4="Downtime",$N$4*$C$4,0))+IF(OR(CD7="In-Term",CD7="Relet"),$C$7,IF(CD7="Downtime",$N$7*$C$7,0))+IF(OR(CD10="In-Term",CD10="Relet"),$C$10,IF(CD10="Downtime",$N$10*$C$10,0))+IF(OR(CD13="In-Term",CD13="Relet"),$C$13,IF(CD13="Downtime",$N$13*$C$13,0))+IF(OR(CD16="In-Term",CD16="Relet"),$C$16,IF(CD16="Downtime",$N$16*$C$16,0))+IF(OR(CD19="In-Term",CD19="Relet"),$C$19,IF(CD19="Downtime",$N$19*$C$19,0))+IF(OR(CD22="In-Term",CD22="Relet"),$C$22,IF(CD22="Downtime",$N$22*$C$22,0))+IF(OR(CD25="In-Term",CD25="Relet"),$C$25,IF(CD25="Downtime",$N$25*$C$25,0))+IF(OR(CD28="In-Term",CD28="Relet"),$C$28,IF(CD28="Downtime",$N$28*$C$28,0))+IF(OR(CD31="In-Term",CD31="Relet"),$C$31,IF(CD31="Downtime",$N$31*$C$31,0))+IF(OR(CD34="In-Term",CD34="Relet"),$C$34,IF(CD34="Downtime",$N$34*$C$34,0))+IF(OR(CD37="In-Term",CD37="Relet"),$C$37,IF(CD37="Downtime",$N$37*$C$37,0)) -> 17880
B43: Occupancy Rate | V43: =V42/NRA -> 0.69826622 | W43: =W42/NRA -> 0.69826622 | X43: =X42/NRA -> 0.69826622 | Y43: =Y42/NRA -> 0.69826622 | Z43: =Z42/NRA -> 0.69826622 | AA43: =AA42/NRA -> 0.82466443 | AB43: =AB42/NRA -> 1 | AC43: =AC42/NRA -> 1 | ... CD43: =CD42/NRA -> 1
B44: Total Monthly Rent | V44: =V6+V9+V12+V15+V18+V21+V24+V27+V30+V33+V36+V39 -> 14111.5 | W44: =W6+W9+W12+W15+W18+W21+W24+W27+W30+W33+W36+W39 -> 14111.5 | X44: =X6+X9+X12+X15+X18+X21+X24+X27+X30+X33+X36+X39 -> 14111.5 | Y44: =Y6+Y9+Y12+Y15+Y18+Y21+Y24+Y27+Y30+Y33+Y36+Y39 -> 14111.5 | Z44: =Z6+Z9+Z12+Z15+Z18+Z21+Z24+Z27+Z30+Z33+Z36+Z39 -> 14111.5 | AA44: =AA6+AA9+AA12+AA15+AA18+AA21+AA24+AA27+AA30+AA33+AA36+AA39 -> 16371.5 | AB44: =AB6+AB9+AB12+AB15+AB18+AB21+AB24+AB27+AB30+AB33+AB36+AB39 -> 19014 | AC44: =AC6+AC9+AC12+AC15+AC18+AC21+AC24+AC27+AC30+AC33+AC36+AC39 -> 19014 | ... CD44: =CD6+CD9+CD12+CD15+CD18+CD21+CD24+CD27+CD30+CD33+CD36+CD39 -> 20727.82
B45: Reimbursement Income | V45: =V47 * 'Monthly CF'!C20 -> 10950.016 | W45: =W47 * 'Monthly CF'!D20 -> 10967.422 | X45: =X47 * 'Monthly CF'!E20 -> 10984.857 | Y45: =Y47 * 'Monthly CF'!F20 -> 11002.32 | Z45: =Z47 * 'Monthly CF'!G20 -> 11019.813 | AA45: =AA47 * 'Monthly CF'!H20 -> 13106.104 | AB45: =AB47 * 'Monthly CF'!I20 -> 16018.2 | AC45: =AC47 * 'Monthly CF'!J20 -> 16043.376 | ... CD45: =CD47 * 'Monthly CF'!BK20 -> 0
B46: NNN-Occupied SF | V46: =IF($E$4="NNN",IF(OR(V4="In-Term",V4="Relet"),$C$4,IF(V4="Downtime",$N$4*$C$4,0)),IF($T$4="Y",IF(V4="Relet",$C$4,IF(V4="Downtime",$N$4*$C$4,0)),0))+IF($E$7="NNN",IF(OR(V7="In-Term",V7="Relet"),$C$7,IF(V7="Downtime",$N$7*$C$7,0)),IF($T$7="Y",IF(V7="Relet",$C$7,IF(V7="Downtime",$N$7*$C$7,0)),0))+IF($E$10="NNN",IF(OR(V10="In-Term",V10="Relet"),$C$10,IF(V10="Downtime",$N$10*$C$10,0)),IF($T$10="Y",IF(V10="Relet",$C$10,IF(V10="Downtime",$N$10*$C$10,0)),0))+IF($E$13="NNN",IF(OR(V13="In-Term",V13="Relet"),$C$13,IF(V13="Downtime",$N$13*$C$13,0)),IF($T$13="Y",IF(V13="Relet",$C$13,IF(V13="Downtime",$N$13*$C$13,0)),0))+IF($E$16="NNN",IF(OR(V16="In-Term",V16="Relet"),$C$16,IF(V16="Downtime",$N$16*$C$16,0)),IF($T$16="Y",IF(V16="Relet",$C$16,IF(V16="Downtime",$N$16*$C$16,0)),0))+IF($E$19="NNN",IF(OR(V19="In-Term",V19="Relet"),$C$19,IF(V19="Downtime",$N$19*$C$19,0)),IF($T$19="Y",IF(V19="Relet",$C$19,IF(V19="Downtime",$N$19*$C$19,0)),0))+IF($E$22="NNN",IF(OR(V22="In-Term",V22="Relet"),$C$22,IF(V22="Downtime",$N$22*$C$22,0)),IF($T$22="Y",IF(V22="Relet",$C$22,IF(V22="Downtime",$N$22*$C$22,0)),0))+IF($E$25="NNN",IF(OR(V25="In-Term",V25="Relet"),$C$25,IF(V25="Downtime",$N$25*$C$25,0)),IF($T$25="Y",IF(V25="Relet",$C$25,IF(V25="Downtime",$N$25*$C$25,0)),0))+IF($E$28="NNN",IF(OR(V28="In-Term",V28="Relet"),$C$28,IF(V28="Downtime",$N$28*$C$28,0)),IF($T$28="Y",IF(V28="Relet",$C$28,IF(V28="Downtime",$N$28*$C$28,0)),0))+IF($E$31="NNN",IF(OR(V31="In-Term",V31="Relet"),$C$31,IF(V31="Downtime",$N$31*$C$31,0)),IF($T$31="Y",IF(V31="Relet",$C$31,IF(V31="Downtime",$N$31*$C$31,0)),0))+IF($E$34="NNN",IF(OR(V34="In-Term",V34="Relet"),$C$34,IF(V34="Downtime",$N$34*$C$34,0)),IF($T$34="Y",IF(V34="Relet",$C$34,IF(V34="Downtime",$N$34*$C$34,0)),0))+IF($E$37="NNN",IF(OR(V37="In-Term",V37="Relet"),$C$37,IF(V37="Downtime",$N$37*$C$37,0)),IF($T$37="Y",IF(V37="Relet",$C$37,IF(V37="Downtime",$N$37*$C$37,0)),0)) -> 12485 | W46: =IF($E$4="NNN",IF(OR(W4="In-Term",W4="Relet"),$C$4,IF(W4="Downtime",$N$4*$C$4,0)),IF($T$4="Y",IF(W4="Relet",$C$4,IF(W4="Downtime",$N$4*$C$4,0)),0))+IF($E$7="NNN",IF(OR(W7="In-Term",W7="Relet"),$C$7,IF(W7="Downtime",$N$7*$C$7,0)),IF($T$7="Y",IF(W7="Relet",$C$7,IF(W7="Downtime",$N$7*$C$7,0)),0))+IF($E$10="NNN",IF(OR(W10="In-Term",W10="Relet"),$C$10,IF(W10="Downtime",$N$10*$C$10,0)),IF($T$10="Y",IF(W10="Relet",$C$10,IF(W10="Downtime",$N$10*$C$10,0)),0))+IF($E$13="NNN",IF(OR(W13="In-Term",W13="Relet"),$C$13,IF(W13="Downtime",$N$13*$C$13,0)),IF($T$13="Y",IF(W13="Relet",$C$13,IF(W13="Downtime",$N$13*$C$13,0)),0))+IF($E$16="NNN",IF(OR(W16="In-Term",W16="Relet"),$C$16,IF(W16="Downtime",$N$16*$C$16,0)),IF($T$16="Y",IF(W16="Relet",$C$16,IF(W16="Downtime",$N$16*$C$16,0)),0))+IF($E$19="NNN",IF(OR(W19="In-Term",W19="Relet"),$C$19,IF(W19="Downtime",$N$19*$C$19,0)),IF($T$19="Y",IF(W19="Relet",$C$19,IF(W19="Downtime",$N$19*$C$19,0)),0))+IF($E$22="NNN",IF(OR(W22="In-Term",W22="Relet"),$C$22,IF(W22="Downtime",$N$22*$C$22,0)),IF($T$22="Y",IF(W22="Relet",$C$22,IF(W22="Downtime",$N$22*$C$22,0)),0))+IF($E$25="NNN",IF(OR(W25="In-Term",W25="Relet"),$C$25,IF(W25="Downtime",$N$25*$C$25,0)),IF($T$25="Y",IF(W25="Relet",$C$25,IF(W25="Downtime",$N$25*$C$25,0)),0))+IF($E$28="NNN",IF(OR(W28="In-Term",W28="Relet"),$C$28,IF(W28="Downtime",$N$28*$C$28,0)),IF($T$28="Y",IF(W28="Relet",$C$28,IF(W28="Downtime",$N$28*$C$28,0)),0))+IF($E$31="NNN",IF(OR(W31="In-Term",W31="Relet"),$C$31,IF(W31="Downtime",$N$31*$C$31,0)),IF($T$31="Y",IF(W31="Relet",$C$31,IF(W31="Downtime",$N$31*$C$31,0)),0))+IF($E$34="NNN",IF(OR(W34="In-Term",W34="Relet"),$C$34,IF(W34="Downtime",$N$34*$C$34,0)),IF($T$34="Y",IF(W34="Relet",$C$34,IF(W34="Downtime",$N$34*$C$34,0)),0))+IF($E$37="NNN",IF(OR(W37="In-Term",W37="Relet"),$C$37,IF(W37="Downtime",$N$37*$C$37,0)),IF($T$37="Y",IF(W37="Relet",$C$37,IF(W37="Downtime",$N$37*$C$37,0)),0)) -> 12485 | X46: =IF($E$4="NNN",IF(OR(X4="In-Term",X4="Relet"),$C$4,IF(X4="Downtime",$N$4*$C$4,0)),IF($T$4="Y",IF(X4="Relet",$C$4,IF(X4="Downtime",$N$4*$C$4,0)),0))+IF($E$7="NNN",IF(OR(X7="In-Term",X7="Relet"),$C$7,IF(X7="Downtime",$N$7*$C$7,0)),IF($T$7="Y",IF(X7="Relet",$C$7,IF(X7="Downtime",$N$7*$C$7,0)),0))+IF($E$10="NNN",IF(OR(X10="In-Term",X10="Relet"),$C$10,IF(X10="Downtime",$N$10*$C$10,0)),IF($T$10="Y",IF(X10="Relet",$C$10,IF(X10="Downtime",$N$10*$C$10,0)),0))+IF($E$13="NNN",IF(OR(X13="In-Term",X13="Relet"),$C$13,IF(X13="Downtime",$N$13*$C$13,0)),IF($T$13="Y",IF(X13="Relet",$C$13,IF(X13="Downtime",$N$13*$C$13,0)),0))+IF($E$16="NNN",IF(OR(X16="In-Term",X16="Relet"),$C$16,IF(X16="Downtime",$N$16*$C$16,0)),IF($T$16="Y",IF(X16="Relet",$C$16,IF(X16="Downtime",$N$16*$C$16,0)),0))+IF($E$19="NNN",IF(OR(X19="In-Term",X19="Relet"),$C$19,IF(X19="Downtime",$N$19*$C$19,0)),IF($T$19="Y",IF(X19="Relet",$C$19,IF(X19="Downtime",$N$19*$C$19,0)),0))+IF($E$22="NNN",IF(OR(X22="In-Term",X22="Relet"),$C$22,IF(X22="Downtime",$N$22*$C$22,0)),IF($T$22="Y",IF(X22="Relet",$C$22,IF(X22="Downtime",$N$22*$C$22,0)),0))+IF($E$25="NNN",IF(OR(X25="In-Term",X25="Relet"),$C$25,IF(X25="Downtime",$N$25*$C$25,0)),IF($T$25="Y",IF(X25="Relet",$C$25,IF(X25="Downtime",$N$25*$C$25,0)),0))+IF($E$28="NNN",IF(OR(X28="In-Term",X28="Relet"),$C$28,IF(X28="Downtime",$N$28*$C$28,0)),IF($T$28="Y",IF(X28="Relet",$C$28,IF(X28="Downtime",$N$28*$C$28,0)),0))+IF($E$31="NNN",IF(OR(X31="In-Term",X31="Relet"),$C$31,IF(X31="Downtime",$N$31*$C$31,0)),IF($T$31="Y",IF(X31="Relet",$C$31,IF(X31="Downtime",$N$31*$C$31,0)),0))+IF($E$34="NNN",IF(OR(X34="In-Term",X34="Relet"),$C$34,IF(X34="Downtime",$N$34*$C$34,0)),IF($T$34="Y",IF(X34="Relet",$C$34,IF(X34="Downtime",$N$34*$C$34,0)),0))+IF($E$37="NNN",IF(OR(X37="In-Term",X37="Relet"),$C$37,IF(X37="Downtime",$N$37*$C$37,0)),IF($T$37="Y",IF(X37="Relet",$C$37,IF(X37="Downtime",$N$37*$C$37,0)),0)) -> 12485 | Y46: =IF($E$4="NNN",IF(OR(Y4="In-Term",Y4="Relet"),$C$4,IF(Y4="Downtime",$N$4*$C$4,0)),IF($T$4="Y",IF(Y4="Relet",$C$4,IF(Y4="Downtime",$N$4*$C$4,0)),0))+IF($E$7="NNN",IF(OR(Y7="In-Term",Y7="Relet"),$C$7,IF(Y7="Downtime",$N$7*$C$7,0)),IF($T$7="Y",IF(Y7="Relet",$C$7,IF(Y7="Downtime",$N$7*$C$7,0)),0))+IF($E$10="NNN",IF(OR(Y10="In-Term",Y10="Relet"),$C$10,IF(Y10="Downtime",$N$10*$C$10,0)),IF($T$10="Y",IF(Y10="Relet",$C$10,IF(Y10="Downtime",$N$10*$C$10,0)),0))+IF($E$13="NNN",IF(OR(Y13="In-Term",Y13="Relet"),$C$13,IF(Y13="Downtime",$N$13*$C$13,0)),IF($T$13="Y",IF(Y13="Relet",$C$13,IF(Y13="Downtime",$N$13*$C$13,0)),0))+IF($E$16="NNN",IF(OR(Y16="In-Term",Y16="Relet"),$C$16,IF(Y16="Downtime",$N$16*$C$16,0)),IF($T$16="Y",IF(Y16="Relet",$C$16,IF(Y16="Downtime",$N$16*$C$16,0)),0))+IF($E$19="NNN",IF(OR(Y19="In-Term",Y19="Relet"),$C$19,IF(Y19="Downtime",$N$19*$C$19,0)),IF($T$19="Y",IF(Y19="Relet",$C$19,IF(Y19="Downtime",$N$19*$C$19,0)),0))+IF($E$22="NNN",IF(OR(Y22="In-Term",Y22="Relet"),$C$22,IF(Y22="Downtime",$N$22*$C$22,0)),IF($T$22="Y",IF(Y22="Relet",$C$22,IF(Y22="Downtime",$N$22*$C$22,0)),0))+IF($E$25="NNN",IF(OR(Y25="In-Term",Y25="Relet"),$C$25,IF(Y25="Downtime",$N$25*$C$25,0)),IF($T$25="Y",IF(Y25="Relet",$C$25,IF(Y25="Downtime",$N$25*$C$25,0)),0))+IF($E$28="NNN",IF(OR(Y28="In-Term",Y28="Relet"),$C$28,IF(Y28="Downtime",$N$28*$C$28,0)),IF($T$28="Y",IF(Y28="Relet",$C$28,IF(Y28="Downtime",$N$28*$C$28,0)),0))+IF($E$31="NNN",IF(OR(Y31="In-Term",Y31="Relet"),$C$31,IF(Y31="Downtime",$N$31*$C$31,0)),IF($T$31="Y",IF(Y31="Relet",$C$31,IF(Y31="Downtime",$N$31*$C$31,0)),0))+IF($E$34="NNN",IF(OR(Y34="In-Term",Y34="Relet"),$C$34,IF(Y34="Downtime",$N$34*$C$34,0)),IF($T$34="Y",IF(Y34="Relet",$C$34,IF(Y34="Downtime",$N$34*$C$34,0)),0))+IF($E$37="NNN",IF(OR(Y37="In-Term",Y37="Relet"),$C$37,IF(Y37="Downtime",$N$37*$C$37,0)),IF($T$37="Y",IF(Y37="Relet",$C$37,IF(Y37="Downtime",$N$37*$C$37,0)),0)) -> 12485 | Z46: =IF($E$4="NNN",IF(OR(Z4="In-Term",Z4="Relet"),$C$4,IF(Z4="Downtime",$N$4*$C$4,0)),IF($T$4="Y",IF(Z4="Relet",$C$4,IF(Z4="Downtime",$N$4*$C$4,0)),0))+IF($E$7="NNN",IF(OR(Z7="In-Term",Z7="Relet"),$C$7,IF(Z7="Downtime",$N$7*$C$7,0)),IF($T$7="Y",IF(Z7="Relet",$C$7,IF(Z7="Downtime",$N$7*$C$7,0)),0))+IF($E$10="NNN",IF(OR(Z10="In-Term",Z10="Relet"),$C$10,IF(Z10="Downtime",$N$10*$C$10,0)),IF($T$10="Y",IF(Z10="Relet",$C$10,IF(Z10="Downtime",$N$10*$C$10,0)),0))+IF($E$13="NNN",IF(OR(Z13="In-Term",Z13="Relet"),$C$13,IF(Z13="Downtime",$N$13*$C$13,0)),IF($T$13="Y",IF(Z13="Relet",$C$13,IF(Z13="Downtime",$N$13*$C$13,0)),0))+IF($E$16="NNN",IF(OR(Z16="In-Term",Z16="Relet"),$C$16,IF(Z16="Downtime",$N$16*$C$16,0)),IF($T$16="Y",IF(Z16="Relet",$C$16,IF(Z16="Downtime",$N$16*$C$16,0)),0))+IF($E$19="NNN",IF(OR(Z19="In-Term",Z19="Relet"),$C$19,IF(Z19="Downtime",$N$19*$C$19,0)),IF($T$19="Y",IF(Z19="Relet",$C$19,IF(Z19="Downtime",$N$19*$C$19,0)),0))+IF($E$22="NNN",IF(OR(Z22="In-Term",Z22="Relet"),$C$22,IF(Z22="Downtime",$N$22*$C$22,0)),IF($T$22="Y",IF(Z22="Relet",$C$22,IF(Z22="Downtime",$N$22*$C$22,0)),0))+IF($E$25="NNN",IF(OR(Z25="In-Term",Z25="Relet"),$C$25,IF(Z25="Downtime",$N$25*$C$25,0)),IF($T$25="Y",IF(Z25="Relet",$C$25,IF(Z25="Downtime",$N$25*$C$25,0)),0))+IF($E$28="NNN",IF(OR(Z28="In-Term",Z28="Relet"),$C$28,IF(Z28="Downtime",$N$28*$C$28,0)),IF($T$28="Y",IF(Z28="Relet",$C$28,IF(Z28="Downtime",$N$28*$C$28,0)),0))+IF($E$31="NNN",IF(OR(Z31="In-Term",Z31="Relet"),$C$31,IF(Z31="Downtime",$N$31*$C$31,0)),IF($T$31="Y",IF(Z31="Relet",$C$31,IF(Z31="Downtime",$N$31*$C$31,0)),0))+IF($E$34="NNN",IF(OR(Z34="In-Term",Z34="Relet"),$C$34,IF(Z34="Downtime",$N$34*$C$34,0)),IF($T$34="Y",IF(Z34="Relet",$C$34,IF(Z34="Downtime",$N$34*$C$34,0)),0))+IF($E$37="NNN",IF(OR(Z37="In-Term",Z37="Relet"),$C$37,IF(Z37="Downtime",$N$37*$C$37,0)),IF($T$37="Y",IF(Z37="Relet",$C$37,IF(Z37="Downtime",$N$37*$C$37,0)),0)) -> 12485 | AA46: =IF($E$4="NNN",IF(OR(AA4="In-Term",AA4="Relet"),$C$4,IF(AA4="Downtime",$N$4*$C$4,0)),IF($T$4="Y",IF(AA4="Relet",$C$4,IF(AA4="Downtime",$N$4*$C$4,0)),0))+IF($E$7="NNN",IF(OR(AA7="In-Term",AA7="Relet"),$C$7,IF(AA7="Downtime",$N$7*$C$7,0)),IF($T$7="Y",IF(AA7="Relet",$C$7,IF(AA7="Downtime",$N$7*$C$7,0)),0))+IF($E$10="NNN",IF(OR(AA10="In-Term",AA10="Relet"),$C$10,IF(AA10="Downtime",$N$10*$C$10,0)),IF($T$10="Y",IF(AA10="Relet",$C$10,IF(AA10="Downtime",$N$10*$C$10,0)),0))+IF($E$13="NNN",IF(OR(AA13="In-Term",AA13="Relet"),$C$13,IF(AA13="Downtime",$N$13*$C$13,0)),IF($T$13="Y",IF(AA13="Relet",$C$13,IF(AA13="Downtime",$N$13*$C$13,0)),0))+IF($E$16="NNN",IF(OR(AA16="In-Term",AA16="Relet"),$C$16,IF(AA16="Downtime",$N$16*$C$16,0)),IF($T$16="Y",IF(AA16="Relet",$C$16,IF(AA16="Downtime",$N$16*$C$16,0)),0))+IF($E$19="NNN",IF(OR(AA19="In-Term",AA19="Relet"),$C$19,IF(AA19="Downtime",$N$19*$C$19,0)),IF($T$19="Y",IF(AA19="Relet",$C$19,IF(AA19="Downtime",$N$19*$C$19,0)),0))+IF($E$22="NNN",IF(OR(AA22="In-Term",AA22="Relet"),$C$22,IF(AA22="Downtime",$N$22*$C$22,0)),IF($T$22="Y",IF(AA22="Relet",$C$22,IF(AA22="Downtime",$N$22*$C$22,0)),0))+IF($E$25="NNN",IF(OR(AA25="In-Term",AA25="Relet"),$C$25,IF(AA25="Downtime",$N$25*$C$25,0)),IF($T$25="Y",IF(AA25="Relet",$C$25,IF(AA25="Downtime",$N$25*$C$25,0)),0))+IF($E$28="NNN",IF(OR(AA28="In-Term",AA28="Relet"),$C$28,IF(AA28="Downtime",$N$28*$C$28,0)),IF($T$28="Y",IF(AA28="Relet",$C$28,IF(AA28="Downtime",$N$28*$C$28,0)),0))+IF($E$31="NNN",IF(OR(AA31="In-Term",AA31="Relet"),$C$31,IF(AA31="Downtime",$N$31*$C$31,0)),IF($T$31="Y",IF(AA31="Relet",$C$31,IF(AA31="Downtime",$N$31*$C$31,0)),0))+IF($E$34="NNN",IF(OR(AA34="In-Term",AA34="Relet"),$C$34,IF(AA34="Downtime",$N$34*$C$34,0)),IF($T$34="Y",IF(AA34="Relet",$C$34,IF(AA34="Downtime",$N$34*$C$34,0)),0))+IF($E$37="NNN",IF(OR(AA37="In-Term",AA37="Relet"),$C$37,IF(AA37="Downtime",$N$37*$C$37,0)),IF($T$37="Y",IF(AA37="Relet",$C$37,IF(AA37="Downtime",$N$37*$C$37,0)),0)) -> 14745 | AB46: =IF($E$4="NNN",IF(OR(AB4="In-Term",AB4="Relet"),$C$4,IF(AB4="Downtime",$N$4*$C$4,0)),IF($T$4="Y",IF(AB4="Relet",$C$4,IF(AB4="Downtime",$N$4*$C$4,0)),0))+IF($E$7="NNN",IF(OR(AB7="In-Term",AB7="Relet"),$C$7,IF(AB7="Downtime",$N$7*$C$7,0)),IF($T$7="Y",IF(AB7="Relet",$C$7,IF(AB7="Downtime",$N$7*$C$7,0)),0))+IF($E$10="NNN",IF(OR(AB10="In-Term",AB10="Relet"),$C$10,IF(AB10="Downtime",$N$10*$C$10,0)),IF($T$10="Y",IF(AB10="Relet",$C$10,IF(AB10="Downtime",$N$10*$C$10,0)),0))+IF($E$13="NNN",IF(OR(AB13="In-Term",AB13="Relet"),$C$13,IF(AB13="Downtime",$N$13*$C$13,0)),IF($T$13="Y",IF(AB13="Relet",$C$13,IF(AB13="Downtime",$N$13*$C$13,0)),0))+IF($E$16="NNN",IF(OR(AB16="In-Term",AB16="Relet"),$C$16,IF(AB16="Downtime",$N$16*$C$16,0)),IF($T$16="Y",IF(AB16="Relet",$C$16,IF(AB16="Downtime",$N$16*$C$16,0)),0))+IF($E$19="NNN",IF(OR(AB19="In-Term",AB19="Relet"),$C$19,IF(AB19="Downtime",$N$19*$C$19,0)),IF($T$19="Y",IF(AB19="Relet",$C$19,IF(AB19="Downtime",$N$19*$C$19,0)),0))+IF($E$22="NNN",IF(OR(AB22="In-Term",AB22="Relet"),$C$22,IF(AB22="Downtime",$N$22*$C$22,0)),IF($T$22="Y",IF(AB22="Relet",$C$22,IF(AB22="Downtime",$N$22*$C$22,0)),0))+IF($E$25="NNN",IF(OR(AB25="In-Term",AB25="Relet"),$C$25,IF(AB25="Downtime",$N$25*$C$25,0)),IF($T$25="Y",IF(AB25="Relet",$C$25,IF(AB25="Downtime",$N$25*$C$25,0)),0))+IF($E$28="NNN",IF(OR(AB28="In-Term",AB28="Relet"),$C$28,IF(AB28="Downtime",$N$28*$C$28,0)),IF($T$28="Y",IF(AB28="Relet",$C$28,IF(AB28="Downtime",$N$28*$C$28,0)),0))+IF($E$31="NNN",IF(OR(AB31="In-Term",AB31="Relet"),$C$31,IF(AB31="Downtime",$N$31*$C$31,0)),IF($T$31="Y",IF(AB31="Relet",$C$31,IF(AB31="Downtime",$N$31*$C$31,0)),0))+IF($E$34="NNN",IF(OR(AB34="In-Term",AB34="Relet"),$C$34,IF(AB34="Downtime",$N$34*$C$34,0)),IF($T$34="Y",IF(AB34="Relet",$C$34,IF(AB34="Downtime",$N$34*$C$34,0)),0))+IF($E$37="NNN",IF(OR(AB37="In-Term",AB37="Relet"),$C$37,IF(AB37="Downtime",$N$37*$C$37,0)),IF($T$37="Y",IF(AB37="Relet",$C$37,IF(AB37="Downtime",$N$37*$C$37,0)),0)) -> 17880 | AC46: =IF($E$4="NNN",IF(OR(AC4="In-Term",AC4="Relet"),$C$4,IF(AC4="Downtime",$N$4*$C$4,0)),IF($T$4="Y",IF(AC4="Relet",$C$4,IF(AC4="Downtime",$N$4*$C$4,0)),0))+IF($E$7="NNN",IF(OR(AC7="In-Term",AC7="Relet"),$C$7,IF(AC7="Downtime",$N$7*$C$7,0)),IF($T$7="Y",IF(AC7="Relet",$C$7,IF(AC7="Downtime",$N$7*$C$7,0)),0))+IF($E$10="NNN",IF(OR(AC10="In-Term",AC10="Relet"),$C$10,IF(AC10="Downtime",$N$10*$C$10,0)),IF($T$10="Y",IF(AC10="Relet",$C$10,IF(AC10="Downtime",$N$10*$C$10,0)),0))+IF($E$13="NNN",IF(OR(AC13="In-Term",AC13="Relet"),$C$13,IF(AC13="Downtime",$N$13*$C$13,0)),IF($T$13="Y",IF(AC13="Relet",$C$13,IF(AC13="Downtime",$N$13*$C$13,0)),0))+IF($E$16="NNN",IF(OR(AC16="In-Term",AC16="Relet"),$C$16,IF(AC16="Downtime",$N$16*$C$16,0)),IF($T$16="Y",IF(AC16="Relet",$C$16,IF(AC16="Downtime",$N$16*$C$16,0)),0))+IF($E$19="NNN",IF(OR(AC19="In-Term",AC19="Relet"),$C$19,IF(AC19="Downtime",$N$19*$C$19,0)),IF($T$19="Y",IF(AC19="Relet",$C$19,IF(AC19="Downtime",$N$19*$C$19,0)),0))+IF($E$22="NNN",IF(OR(AC22="In-Term",AC22="Relet"),$C$22,IF(AC22="Downtime",$N$22*$C$22,0)),IF($T$22="Y",IF(AC22="Relet",$C$22,IF(AC22="Downtime",$N$22*$C$22,0)),0))+IF($E$25="NNN",IF(OR(AC25="In-Term",AC25="Relet"),$C$25,IF(AC25="Downtime",$N$25*$C$25,0)),IF($T$25="Y",IF(AC25="Relet",$C$25,IF(AC25="Downtime",$N$25*$C$25,0)),0))+IF($E$28="NNN",IF(OR(AC28="In-Term",AC28="Relet"),$C$28,IF(AC28="Downtime",$N$28*$C$28,0)),IF($T$28="Y",IF(AC28="Relet",$C$28,IF(AC28="Downtime",$N$28*$C$28,0)),0))+IF($E$31="NNN",IF(OR(AC31="In-Term",AC31="Relet"),$C$31,IF(AC31="Downtime",$N$31*$C$31,0)),IF($T$31="Y",IF(AC31="Relet",$C$31,IF(AC31="Downtime",$N$31*$C$31,0)),0))+IF($E$34="NNN",IF(OR(AC34="In-Term",AC34="Relet"),$C$34,IF(AC34="Downtime",$N$34*$C$34,0)),IF($T$34="Y",IF(AC34="Relet",$C$34,IF(AC34="Downtime",$N$34*$C$34,0)),0))+IF($E$37="NNN",IF(OR(AC37="In-Term",AC37="Relet"),$C$37,IF(AC37="Downtime",$N$37*$C$37,0)),IF($T$37="Y",IF(AC37="Relet",$C$37,IF(AC37="Downtime",$N$37*$C$37,0)),0)) -> 17880 | ... CD46: =IF($E$4="NNN",IF(OR(CD4="In-Term",CD4="Relet"),$C$4,IF(CD4="Downtime",$N$4*$C$4,0)),IF($T$4="Y",IF(CD4="Relet",$C$4,IF(CD4="Downtime",$N$4*$C$4,0)),0))+IF($E$7="NNN",IF(OR(CD7="In-Term",CD7="Relet"),$C$7,IF(CD7="Downtime",$N$7*$C$7,0)),IF($T$7="Y",IF(CD7="Relet",$C$7,IF(CD7="Downtime",$N$7*$C$7,0)),0))+IF($E$10="NNN",IF(OR(CD10="In-Term",CD10="Relet"),$C$10,IF(CD10="Downtime",$N$10*$C$10,0)),IF($T$10="Y",IF(CD10="Relet",$C$10,IF(CD10="Downtime",$N$10*$C$10,0)),0))+IF($E$13="NNN",IF(OR(CD13="In-Term",CD13="Relet"),$C$13,IF(CD13="Downtime",$N$13*$C$13,0)),IF($T$13="Y",IF(CD13="Relet",$C$13,IF(CD13="Downtime",$N$13*$C$13,0)),0))+IF($E$16="NNN",IF(OR(CD16="In-Term",CD16="Relet"),$C$16,IF(CD16="Downtime",$N$16*$C$16,0)),IF($T$16="Y",IF(CD16="Relet",$C$16,IF(CD16="Downtime",$N$16*$C$16,0)),0))+IF($E$19="NNN",IF(OR(CD19="In-Term",CD19="Relet"),$C$19,IF(CD19="Downtime",$N$19*$C$19,0)),IF($T$19="Y",IF(CD19="Relet",$C$19,IF(CD19="Downtime",$N$19*$C$19,0)),0))+IF($E$22="NNN",IF(OR(CD22="In-Term",CD22="Relet"),$C$22,IF(CD22="Downtime",$N$22*$C$22,0)),IF($T$22="Y",IF(CD22="Relet",$C$22,IF(CD22="Downtime",$N$22*$C$22,0)),0))+IF($E$25="NNN",IF(OR(CD25="In-Term",CD25="Relet"),$C$25,IF(CD25="Downtime",$N$25*$C$25,0)),IF($T$25="Y",IF(CD25="Relet",$C$25,IF(CD25="Downtime",$N$25*$C$25,0)),0))+IF($E$28="NNN",IF(OR(CD28="In-Term",CD28="Relet"),$C$28,IF(CD28="Downtime",$N$28*$C$28,0)),IF($T$28="Y",IF(CD28="Relet",$C$28,IF(CD28="Downtime",$N$28*$C$28,0)),0))+IF($E$31="NNN",IF(OR(CD31="In-Term",CD31="Relet"),$C$31,IF(CD31="Downtime",$N$31*$C$31,0)),IF($T$31="Y",IF(CD31="Relet",$C$31,IF(CD31="Downtime",$N$31*$C$31,0)),0))+IF($E$34="NNN",IF(OR(CD34="In-Term",CD34="Relet"),$C$34,IF(CD34="Downtime",$N$34*$C$34,0)),IF($T$34="Y",IF(CD34="Relet",$C$34,IF(CD34="Downtime",$N$34*$C$34,0)),0))+IF($E$37="NNN",IF(OR(CD37="In-Term",CD37="Relet"),$C$37,IF(CD37="Downtime",$N$37*$C$37,0)),IF($T$37="Y",IF(CD37="Relet",$C$37,IF(CD37="Downtime",$N$37*$C$37,0)),0)) -> 17880
B47: NNN Occupancy Rate | V47: =V46/NRA -> 0.69826622 | W47: =W46/NRA -> 0.69826622 | X47: =X46/NRA -> 0.69826622 | Y47: =Y46/NRA -> 0.69826622 | Z47: =Z46/NRA -> 0.69826622 | AA47: =AA46/NRA -> 0.82466443 | AB47: =AB46/NRA -> 1 | AC47: =AC46/NRA -> 1 | ... CD47: =CD46/NRA -> 1
U48: NNN's | V48: =V45 / V46 -> 0.87705373 | W48: =W45 / W46 -> 0.87844789 | X48: =X45 / X46 -> 0.87984436 | Y48: =Y45 / Y46 -> 0.88124313 | Z48: =Z45 / Z46 -> 0.88264421 | AA48: =AA45 / AA46 -> 0.88885074 | AB48: =AB45 / AB46 -> 0.8958725 | AC48: =AC45 / AC46 -> 0.89728054 | ... CD48: =CD45 / CD46 -> 0

Sheet OM Rent Roll
A1: OM RENT ROLL — AS-IS AT ACQUISITION
A2: Input raw rent roll data from the offering memorandum below. All cells should be blue text (inputs).
A4: Suite / Unit # | B4: Tenant Name | C4: SF | D4: Lease Type | E4: Lease Start | F4: Lease End | G4: Base Rent ($/SF/mo) | H4: Implied Esc %/yr | I4: Total Rent ($/mo) | J4: Bump Date | K4: Bump To ($/mo) | L4: Bump $/SF/mo | M4: Renewal Options
A5: 4949 A1&A2 | B5: Middle East Bakery | C5: 2230 | D5: NNN | E5: 45444 | F5: 47392 | G5: =IFERROR(I5/C5,0) -> 1.0304933 | H5: =IFERROR(IF(OR(J5="",K5=""),0,((K5/C5)/G5)^(12/MAX(1,DATEDIF(E5,J5,"M")))-1),0) -> 0.019538771 | I5: 2298 | J5: 47027 | K5: 2499 | L5: =IFERROR(K5/C5,"") -> 1.1206278
A6: 4949 B | B6: VACANT | C6: 910 | D6: NNN | G6: =IFERROR(I6/C6,0) -> 0.9 | H6: =IFERROR(IF(OR(J6="",K6=""),0,((K6/C6)/G6)^(12/MAX(1,DATEDIF(E6,J6,"M")))-1),0) -> 0.00043150431 | I6: 819 | J6: 46266 | K6: 865 | L6: =IFERROR(K6/C6,"") -> 0.95054945 | M6: One 3-Year Option
A7: 4949 C | B7: Circle Pizza | C7: 3620 | D7: NNN | E7: 45962 | F7: 47787 | G7: =IFERROR(I7/C7,0) -> 1.4088398 | H7: =IFERROR(IF(OR(J7="",K7=""),0,((K7/C7)/G7)^(12/MAX(1,DATEDIF(E7,J7,"M")))-1),0) -> 0.019607843 | I7: 5100 | J7: 46327 | K7: 5200 | L7: =IFERROR(K7/C7,"") -> 1.4364641
A8: 4949 D&E | B8: Silver Sake | C8: 1990 | D8: NNN | E8: MTM | F8: MTM | G8: =IFERROR(I8/C8,0) -> 1.5075377 | H8: =IFERROR(IF(OR(J8="",K8=""),0,((K8/C8)/G8)^(12/MAX(1,DATEDIF(E8,J8,"M")))-1),0) -> 0 | I8: 3000 | L8: =IFERROR(K8/C8,"") -> 0
A9: 4949 F | B9: Waiel Merza | C9: 810 | D9: NNN | E9: 46054 | F9: 47238 | G9: =IFERROR(I9/C9,0) -> 0.95061728 | H9: =IFERROR(IF(OR(J9="",K9=""),0,((K9/C9)/G9)^(12/MAX(1,DATEDIF(E9,J9,"M")))-1),0) -> 0.024858298 | I9: 770 | J9: 46508 | K9: 794 | L9: =IFERROR(K9/C9,"") -> 0.98024691 | M9: One 3-Year Option
A10: 4949 G | B10: Cigarettes & Gifts | C10: 810 | D10: NNN | E10: 44105 | F10: 45930 | G10: =IFERROR(I10/C10,0) -> 1.2506173 | H10: =IFERROR(IF(OR(J10="",K10=""),0,((K10/C10)/G10)^(12/MAX(1,DATEDIF(E10,J10,"M")))-1),0) -> 0 | I10: 1013 | L10: =IFERROR(K10/C10,"") -> 0
A11: 4949 H | B11: Brittany Hair & Nails | C11: 810 | D11: MG | E11: 43070 | F11: 46142 | G11: =IFERROR(I11/C11,0) -> 1.6975309 | H11: =IFERROR(IF(OR(J11="",K11=""),0,((K11/C11)/G11)^(12/MAX(1,DATEDIF(E11,J11,"M")))-1),0) -> 0 | I11: 1375 | L11: =IFERROR(K11/C11,"") -> 0 | M11: 2 Options
A12: 4949 I | B12: Madeville Hair Salon | C12: 810 | D12: NNN | E12: MTM | F12: MTM | G12: =IFERROR(I12/C12,0) -> 1.2197531 | H12: =IFERROR(IF(OR(J12="",K12=""),0,((K12/C12)/G12)^(12/MAX(1,DATEDIF(E12,J12,"M")))-1),0) -> 0 | I12: 988 | L12: =IFERROR(K12/C12,"") -> 0
A13: 4949 J | B13: VACANT | C13: 1350 | D13: NNN | G13: =IFERROR(I13/C13,0) -> 0 | H13: =IFERROR(IF(OR(J13="",K13=""),0,((K13/C13)/G13)^(12/MAX(1,DATEDIF(E13,J13,"M")))-1),0) -> 0 | I13: 0 | L13: =IFERROR(K13/C13,"") -> 0
A14: 4955 A | B14: Sharing & Caring | C14: 1350 | D14: MG | E14: MTM | F14: MTM | G14: =IFERROR(I14/C14,0) -> 1.0185185 | H14: =IFERROR(IF(OR(J14="",K14=""),0,((K14/C14)/G14)^(12/MAX(1,DATEDIF(E14,J14,"M")))-1),0) -> 0 | I14: 1375 | L14: =IFERROR(K14/C14,"") -> 0
A15: 4955 B | B15: Spoteless Cleaners | C15: 1310 | D15: NNN | E15: MTM | F15: MTM | G15: =IFERROR(I15/C15,0) -> 0.8259542 | H15: =IFERROR(IF(OR(J15="",K15=""),0,((K15/C15)/G15)^(12/MAX(1,DATEDIF(E15,J15,"M")))-1),0) -> 0 | I15: 1082 | L15: =IFERROR(K15/C15,"") -> 0
A16: 4955 C | B16: Dawn's Pet Palace | C16: 1880 | D16: NNN | E16: 45992 | F16: 47087 | G16: =IFERROR(I16/C16,0) -> 0.80106383 | H16: =IFERROR(IF(OR(J16="",K16=""),0,((K16/C16)/G16)^(12/MAX(1,DATEDIF(E16,J16,"M")))-1),0) -> 0.030736144 | I16: 1506 | J16: 46722 | K16: 1600 | L16: =IFERROR(K16/C16,"") -> 0.85106383
B18: TOTAL | C18: =SUM(C5:C16) -> 17880 | G18: =IFERROR(I18/C18,0) -> 1.0808725 | I18: =SUM(I5:I16) -> 19326
B20: TODO
A21: 1 | B21: make sure to go in and hard code the initial leaseup month for VACANT units and if wanted for MTM
A22: 2 | B22: make TI costs and LCs equal to new ones for those we think will be new lease for sure
A23: 3 | B23: make sure to set VACANT lease types to NNN
A24: 4
C25: =(C6 + C13 )/ C18 -> 0.12639821
C26: =1 - C25 -> 0.87360179

Sheet OM OpEx
B1: OM OPERATING EXPENSES — HISTORICAL & PROJECTED
B2: important note - right now, just the total opex number monthly number is being taken and use to start the month 1 of the cash flow, then then annual opex growth % is being applied for simplicity, in future we will line item these
B4: Line Item | C4: OM | D4: $/SF | E4: Growth % | F4: Yr 1 Projected | G4: Monthly
B5: Repairs & Maintenance | C5: 35760 | D5: =IFERROR(C5/NRA,0) -> 2 | E5: 0.03 | F5: =C5*(1+E5) -> 36832.8 | G5: =F5/12 -> 3069.4
B6: Janitorial | C6: 18590 | D6: =IFERROR(C6/NRA,0) -> 1.0397092 | E6: 0.02 | F6: =C6*(1+E6) -> 18961.8 | G6: =F6/12 -> 1580.15
B7: Landscaping / Grounds | C7: 21132 | D7: =IFERROR(C7/NRA,0) -> 1.1818792 | E7: 0.02 | F7: =C7*(1+E7) -> 21554.64 | G7: =F7/12 -> 1796.22
B8: Pest Control | C8: 1278 | D8: =IFERROR(C8/NRA,0) -> 0.07147651 | E8: 0.02 | F8: =C8*(1+E8) -> 1303.56 | G8: =F8/12 -> 108.63
B9: Security | C9: 30544 | D9: =IFERROR(C9/NRA,0) -> 1.7082774 | E9: 0.02 | F9: =C9*(1+E9) -> 31154.88 | G9: =F9/12 -> 2596.24
B10: Utilities — Electric (Common) | C10: 3220 | D10: =IFERROR(C10/NRA,0) -> 0.18008949 | E10: 0.03 | F10: =C10*(1+E10) -> 3316.6 | G10: =F10/12 -> 276.38333
B11: Utilities — Water/Sewer | C11: 31766 | D11: =IFERROR(C11/NRA,0) -> 1.7766219 | E11: 0.03 | F11: =C11*(1+E11) -> 32718.98 | G11: =F11/12 -> 2726.5817
B12: Utilities — Gas | C12: 0 | D12: =IFERROR(C12/NRA,0) -> 0 | E12: 0.03 | F12: =C12*(1+E12) -> 0 | G12: =F12/12 -> 0
B13: Trash & Recycling | C13: 0 | D13: =IFERROR(C13/NRA,0) -> 0 | E13: 0.02 | F13: =C13*(1+E13) -> 0 | G13: =F13/12 -> 0
B14: Fire/Life Safety | C14: 1687 | D14: =IFERROR(C14/NRA,0) -> 0.09435123 | E14: 0.02 | F14: =C14*(1+E14) -> 1720.74 | G14: =F14/12 -> 143.395
B15: HVAC Contracts | C15: 0 | D15: =IFERROR(C15/NRA,0) -> 0 | E15: 0.02 | F15: =C15*(1+E15) -> 0 | G15: =F15/12 -> 0
B16: Parking Lot Maintenance | C16: 0 | D16: =IFERROR(C16/NRA,0) -> 0 | E16: 0.02 | F16: =C16*(1+E16) -> 0 | G16: =F16/12 -> 0
B17: Property Taxes | C17: 24042 | D17: =IFERROR(C17/NRA,0) -> 1.3446309 | E17: 0.02 | F17: =Assessed_Value*Millage_Rate -> 23484 | G17: =F17/12 -> 1957 | H17: uses Mill rate to calculate
B18: Insurance | C18: 9777 | D18: =IFERROR(C18/NRA,0) -> 0.54681208 | E18: 0.03 | F18: =C18*(1+E18) -> 10070.31 | G18: =F18/12 -> 839.1925 | H18: need quote on rate
B19: Management Fee | C19: 16613 | D19: =IFERROR(C19/NRA,0) -> 0.9291387 | E19: 0 | F19: =0 -> 0 | G19: =F19/12 -> 0 | H19: Variable: Property Management Amount being calculated directly in cash flow
B20: Other / Misc | C20: 0 | D20: =IFERROR(C20/NRA,0) -> 0 | E20: 0.02 | F20: =C20*(1+E20) -> 0 | G20: =F20/12 -> 0
B21: TOTAL OPERATING EXPENSES | C21: =SUM(C5:C20) -> 194409 | D21: =IFERROR(C21/NRA,0) -> 10.872987 | F21: =SUM(F5:F18, F20) -> 181118.31 | G21: =SUM(G5:G18, G20) -> 15093.193
B25: Current Total Reimburesement Income
B26: 81816

Sheet Debt
A1: DEBT SCHEDULE
C2: 1 | D2: 2 | E2: 3 | F2: 4 | G2: 5 | H2: 6 | I2: 7 | J2: 8 | K2: 9 | L2: 10 | M2: 11 | N2: 12 | O2: 13 | P2: 14 | Q2: 15 | R2: 16 | S2: 17 | T2: 18 | U2: 19 | V2: 20 | W2: 21 | X2: 22 | Y2: 23 | Z2: 24 | AA2: 25 | AB2: 26 | AC2: 27 | AD2: 28 | AE2: 29 | AF2: 30 | AG2: 31 | AH2: 32 | AI2: 33 | AJ2: 34 | AK2: 35 | AL2: 36 | AM2: 37 | AN2: 38 | AO2: 39 | AP2: 40 | AQ2: 41 | AR2: 42 | AS2: 43 | AT2: 44 | AU2: 45 | AV2: 46 | AW2: 47 | AX2: 48 | AY2: 49 | AZ2: 50 | BA2: 51 | BB2: 52 | BC2: 53 | BD2: 54 | BE2: 55 | BF2: 56 | BG2: 57 | BH2: 58 | BI2: 59 | BJ2: 60
B3: LOAN 1 — ACQUISITION
B4: Beginning Balance | C4: =Loan1_Amount -> 1400000 | D4: =C9 -> 1400000 | E4: =D9 -> 1400000 | F4: =E9 -> 1400000 | G4: =F9 -> 1400000 | H4: =G9 -> 1400000 | I4: =H9 -> 1400000 | J4: =I9 -> 1400000 | K4: =J9 -> 1400000 | ... BJ4: =BI9 -> 0
B5: Interest Payment | C5: =C4*Rate1/12 -> 11666.667 | D5: =D4*Rate1/12 -> 11666.667 | E5: =E4*Rate1/12 -> 11666.667 | F5: =F4*Rate1/12 -> 11666.667 | G5: =G4*Rate1/12 -> 11666.667 | H5: =H4*Rate1/12 -> 11666.667 | I5: =I4*Rate1/12 -> 11666.667 | J5: =J4*Rate1/12 -> 11666.667 | ... BJ5: =BJ4*Rate1/12 -> 0
B6: Principal Payment | C6: =IF(C2<=IO1_Months,0,IF(C4=0,0,PPMT(Rate1/12,C2-IO1_Months,Amort1_Years*12,-Loan1_Amount))) -> 0 | D6: =IF(D2<=IO1_Months,0,IF(D4=0,0,PPMT(Rate1/12,D2-IO1_Months,Amort1_Years*12,-Loan1_Amount))) -> 0 | E6: =IF(E2<=IO1_Months,0,IF(E4=0,0,PPMT(Rate1/12,E2-IO1_Months,Amort1_Years*12,-Loan1_Amount))) -> 0 | F6: =IF(F2<=IO1_Months,0,IF(F4=0,0,PPMT(Rate1/12,F2-IO1_Months,Amort1_Years*12,-Loan1_Amount))) -> 0 | G6: =IF(G2<=IO1_Months,0,IF(G4=0,0,PPMT(Rate1/12,G2-IO1_Months,Amort1_Years*12,-Loan1_Amount))) -> 0 | H6: =IF(H2<=IO1_Months,0,IF(H4=0,0,PPMT(Rate1/12,H2-IO1_Months,Amort1_Years*12,-Loan1_Amount))) -> 0 | I6: =IF(I2<=IO1_Months,0,IF(I4=0,0,PPMT(Rate1/12,I2-IO1_Months,Amort1_Years*12,-Loan1_Amount))) -> 0 | J6: =IF(J2<=IO1_Months,0,IF(J4=0,0,PPMT(Rate1/12,J2-IO1_Months,Amort1_Years*12,-Loan1_Amount))) -> 0 | ... BJ6: =IF(BJ2<=IO1_Months,0,IF(BJ4=0,0,PPMT(Rate1/12,BJ2-IO1_Months,Amort1_Years*12,-Loan1_Amount))) -> 0
B7: Total Payment | C7: =C5+C6 -> 11666.667 | D7: =D5+D6 -> 11666.667 | E7: =E5+E6 -> 11666.667 | F7: =F5+F6 -> 11666.667 | G7: =G5+G6 -> 11666.667 | H7: =H5+H6 -> 11666.667 | I7: =I5+I6 -> 11666.667 | J7: =J5+J6 -> 11666.667 | ... BJ7: =BJ5+BJ6 -> 0
B8: Loan Payoff | C8: =IF(AND(Refi_Toggle="ON",C2=Refi_Month),C4-C6,IF(AND(Refi_Toggle<>"ON",C2=Exit_Month),C4-C6,0)) -> 0 | D8: =IF(AND(Refi_Toggle="ON",D2=Refi_Month),D4-D6,IF(AND(Refi_Toggle<>"ON",D2=Exit_Month),D4-D6,0)) -> 0 | E8: =IF(AND(Refi_Toggle="ON",E2=Refi_Month),E4-E6,IF(AND(Refi_Toggle<>"ON",E2=Exit_Month),E4-E6,0)) -> 0 | F8: =IF(AND(Refi_Toggle="ON",F2=Refi_Month),F4-F6,IF(AND(Refi_Toggle<>"ON",F2=Exit_Month),F4-F6,0)) -> 0 | G8: =IF(AND(Refi_Toggle="ON",G2=Refi_Month),G4-G6,IF(AND(Refi_Toggle<>"ON",G2=Exit_Month),G4-G6,0)) -> 0 | H8: =IF(AND(Refi_Toggle="ON",H2=Refi_Month),H4-H6,IF(AND(Refi_Toggle<>"ON",H2=Exit_Month),H4-H6,0)) -> 0 | I8: =IF(AND(Refi_Toggle="ON",I2=Refi_Month),I4-I6,IF(AND(Refi_Toggle<>"ON",I2=Exit_Month),I4-I6,0)) -> 0 | J8: =IF(AND(Refi_Toggle="ON",J2=Refi_Month),J4-J6,IF(AND(Refi_Toggle<>"ON",J2=Exit_Month),J4-J6,0)) -> 0 | ... BJ8: =IF(AND(Refi_Toggle="ON",BJ2=Refi_Month),BJ4-BJ6,IF(AND(Refi_Toggle<>"ON",BJ2=Exit_Month),BJ4-BJ6,0)) -> 0
B9: Ending Balance | C9: =C4-C6-C8 -> 1400000 | D9: =D4-D6-D8 -> 1400000 | E9: =E4-E6-E8 -> 1400000 | F9: =F4-F6-F8 -> 1400000 | G9: =G4-G6-G8 -> 1400000 | H9: =H4-H6-H8 -> 1400000 | I9: =I4-I6-I8 -> 1400000 | J9: =J4-J6-J8 -> 1400000 | ... BJ9: =BJ4-BJ6-BJ8 -> 0
B10: Origination Fee | C10: =IF(C2=1,Loan1_Amount*Orig_Fee1,0) -> 28000 | D10: =IF(D2=1,Loan1_Amount*Orig_Fee1,0) -> 0 | E10: =IF(E2=1,Loan1_Amount*Orig_Fee1,0) -> 0 | F10: =IF(F2=1,Loan1_Amount*Orig_Fee1,0) -> 0 | G10: =IF(G2=1,Loan1_Amount*Orig_Fee1,0) -> 0 | H10: =IF(H2=1,Loan1_Amount*Orig_Fee1,0) -> 0 | I10: =IF(I2=1,Loan1_Amount*Orig_Fee1,0) -> 0 | J10: =IF(J2=1,Loan1_Amount*Orig_Fee1,0) -> 0 | ... BJ10: =IF(BJ2=1,Loan1_Amount*Orig_Fee1,0) -> 0
B12: LOAN 2 — REFINANCE
B13: Refi Proceeds | C13: =IF(AND(Refi_Toggle="ON",C2=Refi_Month),Refi_Loan_Amt,0) -> 0 | D13: =IF(AND(Refi_Toggle="ON",D2=Refi_Month),Refi_Loan_Amt,0) -> 0 | E13: =IF(AND(Refi_Toggle="ON",E2=Refi_Month),Refi_Loan_Amt,0) -> 0 | F13: =IF(AND(Refi_Toggle="ON",F2=Refi_Month),Refi_Loan_Amt,0) -> 0 | G13: =IF(AND(Refi_Toggle="ON",G2=Refi_Month),Refi_Loan_Amt,0) -> 0 | H13: =IF(AND(Refi_Toggle="ON",H2=Refi_Month),Refi_Loan_Amt,0) -> 0 | I13: =IF(AND(Refi_Toggle="ON",I2=Refi_Month),Refi_Loan_Amt,0) -> 0 | J13: =IF(AND(Refi_Toggle="ON",J2=Refi_Month),Refi_Loan_Amt,0) -> 0 | ... BJ13: =IF(AND(Refi_Toggle="ON",BJ2=Refi_Month),Refi_Loan_Amt,0) -> 0
B14: Beginning Balance | C14: =C13 -> 0 | D14: =C19+D13 -> 0 | E14: =D19+E13 -> 0 | F14: =E19+F13 -> 0 | G14: =F19+G13 -> 0 | H14: =G19+H13 -> 0 | I14: =H19+I13 -> 0 | J14: =I19+J13 -> 0 | K14: =J19+K13 -> 0 | ... BJ14: =BI19+BJ13 -> 1900007.5
B15: Interest Payment | C15: =C14*Refi_Rate/12 -> 0 | D15: =D14*Refi_Rate/12 -> 0 | E15: =E14*Refi_Rate/12 -> 0 | F15: =F14*Refi_Rate/12 -> 0 | G15: =G14*Refi_Rate/12 -> 0 | H15: =H14*Refi_Rate/12 -> 0 | I15: =I14*Refi_Rate/12 -> 0 | J15: =J14*Refi_Rate/12 -> 0 | ... BJ15: =BJ14*Refi_Rate/12 -> 11479.212
B16: Principal Payment | C16: =IF(Refi_Toggle<>"ON",0,IF(C14=0,0,IF((C2-Refi_Month+1)<=Refi_IO,0,PPMT(Refi_Rate/12,(C2-Refi_Month+1)-Refi_IO,Refi_Amort*12,-Refi_Loan_Amt)))) -> 0 | D16: =IF(Refi_Toggle<>"ON",0,IF(D14=0,0,IF((D2-Refi_Month+1)<=Refi_IO,0,PPMT(Refi_Rate/12,(D2-Refi_Month+1)-Refi_IO,Refi_Amort*12,-Refi_Loan_Amt)))) -> 0 | E16: =IF(Refi_Toggle<>"ON",0,IF(E14=0,0,IF((E2-Refi_Month+1)<=Refi_IO,0,PPMT(Refi_Rate/12,(E2-Refi_Month+1)-Refi_IO,Refi_Amort*12,-Refi_Loan_Amt)))) -> 0 | F16: =IF(Refi_Toggle<>"ON",0,IF(F14=0,0,IF((F2-Refi_Month+1)<=Refi_IO,0,PPMT(Refi_Rate/12,(F2-Refi_Month+1)-Refi_IO,Refi_Amort*12,-Refi_Loan_Amt)))) -> 0 | G16: =IF(Refi_Toggle<>"ON",0,IF(G14=0,0,IF((G2-Refi_Month+1)<=Refi_IO,0,PPMT(Refi_Rate/12,(G2-Refi_Month+1)-Refi_IO,Refi_Amort*12,-Refi_Loan_Amt)))) -> 0 | H16: =IF(Refi_Toggle<>"ON",0,IF(H14=0,0,IF((H2-Refi_Month+1)<=Refi_IO,0,PPMT(Refi_Rate/12,(H2-Refi_Month+1)-Refi_IO,Refi_Amort*12,-Refi_Loan_Amt)))) -> 0 | I16: =IF(Refi_Toggle<>"ON",0,IF(I14=0,0,IF((I2-Refi_Month+1)<=Refi_IO,0,PPMT(Refi_Rate/12,(I2-Refi_Month+1)-Refi_IO,Refi_Amort*12,-Refi_Loan_Amt)))) -> 0 | J16: =IF(Refi_Toggle<>"ON",0,IF(J14=0,0,IF((J2-Refi_Month+1)<=Refi_IO,0,PPMT(Refi_Rate/12,(J2-Refi_Month+1)-Refi_IO,Refi_Amort*12,-Refi_Loan_Amt)))) -> 0 | ... BJ16: =IF(Refi_Toggle<>"ON",0,IF(BJ14=0,0,IF((BJ2-Refi_Month+1)<=Refi_IO,0,PPMT(Refi_Rate/12,(BJ2-Refi_Month+1)-Refi_IO,Refi_Amort*12,-Refi_Loan_Amt)))) -> 3222.0348
B17: Total Payment | C17: =C15+C16 -> 0 | D17: =D15+D16 -> 0 | E17: =E15+E16 -> 0 | F17: =F15+F16 -> 0 | G17: =G15+G16 -> 0 | H17: =H15+H16 -> 0 | I17: =I15+I16 -> 0 | J17: =J15+J16 -> 0 | ... BJ17: =BJ15+BJ16 -> 14701.247
B18: Loan Payoff | C18: =IF(AND(Refi_Toggle="ON",C2=Exit_Month),C14-C16,0) -> 0 | D18: =IF(AND(Refi_Toggle="ON",D2=Exit_Month),D14-D16,0) -> 0 | E18: =IF(AND(Refi_Toggle="ON",E2=Exit_Month),E14-E16,0) -> 0 | F18: =IF(AND(Refi_Toggle="ON",F2=Exit_Month),F14-F16,0) -> 0 | G18: =IF(AND(Refi_Toggle="ON",G2=Exit_Month),G14-G16,0) -> 0 | H18: =IF(AND(Refi_Toggle="ON",H2=Exit_Month),H14-H16,0) -> 0 | I18: =IF(AND(Refi_Toggle="ON",I2=Exit_Month),I14-I16,0) -> 0 | J18: =IF(AND(Refi_Toggle="ON",J2=Exit_Month),J14-J16,0) -> 0 | ... BJ18: =IF(AND(Refi_Toggle="ON",BJ2=Exit_Month),BJ14-BJ16,0) -> 1896785.5
B19: Ending Balance | C19: =C14-C16-C18 -> 0 | D19: =D14-D16-D18 -> 0 | E19: =E14-E16-E18 -> 0 | F19: =F14-F16-F18 -> 0 | G19: =G14-G16-G18 -> 0 | H19: =H14-H16-H18 -> 0 | I19: =I14-I16-I18 -> 0 | J19: =J14-J16-J18 -> 0 | ... BJ19: =BJ14-BJ16-BJ18 -> 0
B20: Origination Fee | C20: =IF(AND(Refi_Toggle="ON",C2=Refi_Month),Refi_Loan_Amt*Refi_Orig_Fee,0) -> 0 | D20: =IF(AND(Refi_Toggle="ON",D2=Refi_Month),Refi_Loan_Amt*Refi_Orig_Fee,0) -> 0 | E20: =IF(AND(Refi_Toggle="ON",E2=Refi_Month),Refi_Loan_Amt*Refi_Orig_Fee,0) -> 0 | F20: =IF(AND(Refi_Toggle="ON",F2=Refi_Month),Refi_Loan_Amt*Refi_Orig_Fee,0) -> 0 | G20: =IF(AND(Refi_Toggle="ON",G2=Refi_Month),Refi_Loan_Amt*Refi_Orig_Fee,0) -> 0 | H20: =IF(AND(Refi_Toggle="ON",H2=Refi_Month),Refi_Loan_Amt*Refi_Orig_Fee,0) -> 0 | I20: =IF(AND(Refi_Toggle="ON",I2=Refi_Month),Refi_Loan_Amt*Refi_Orig_Fee,0) -> 0 | J20: =IF(AND(Refi_Toggle="ON",J2=Refi_Month),Refi_Loan_Amt*Refi_Orig_Fee,0) -> 0 | ... BJ20: =IF(AND(Refi_Toggle="ON",BJ2=Refi_Month),Refi_Loan_Amt*Refi_Orig_Fee,0) -> 0
B22: COMBINED DEBT SUMMARY
B23: Total Debt Service | C23: =C7+C17 -> 11666.667 | D23: =D7+D17 -> 11666.667 | E23: =E7+E17 -> 11666.667 | F23: =F7+F17 -> 11666.667 | G23: =G7+G17 -> 11666.667 | H23: =H7+H17 -> 11666.667 | I23: =I7+I17 -> 11666.667 | J23: =J7+J17 -> 11666.667 | ... BJ23: =BJ7+BJ17 -> 14701.247
B24: Net Refi Cash | C24: =C13-C8-C20 -> 0 | D24: =D13-D8-D20 -> 0 | E24: =E13-E8-E20 -> 0 | F24: =F13-F8-F20 -> 0 | G24: =G13-G8-G20 -> 0 | H24: =H13-H8-H20 -> 0 | I24: =I13-I8-I20 -> 0 | J24: =J13-J8-J20 -> 0 | ... BJ24: =BJ13-BJ8-BJ20 -> 0
B25: Total Loan Payoff at Exit | C25: =IF(C2 = Exit_Month, C18 + C8, 0) -> 0 | D25: =IF(D2 = Exit_Month, D18 + D8, 0) -> 0 | E25: =IF(E2 = Exit_Month, E18 + E8, 0) -> 0 | F25: =IF(F2 = Exit_Month, F18 + F8, 0) -> 0 | G25: =IF(G2 = Exit_Month, G18 + G8, 0) -> 0 | H25: =IF(H2 = Exit_Month, H18 + H8, 0) -> 0 | I25: =IF(I2 = Exit_Month, I18 + I8, 0) -> 0 | J25: =IF(J2 = Exit_Month, J18 + J8, 0) -> 0 | ... BJ25: =IF(BJ2 = Exit_Month, BJ18 + BJ8, 0) -> 1896785.5

Sheet Annual CF
A1: ANNUAL CASH FLOW SUMMARY
C2: Year 1 | D2: Year 2 | E2: Year 3 | F2: Year 4 | G2: Year 5
B4: INCOME
B5: Total Collected Rent | C5: =SUM('Monthly CF'!C7:N7) -> 201013 | D5: =SUM('Monthly CF'!O7:Z7) -> 234054.36 | E5: =SUM('Monthly CF'!AA7:AL7) -> 239309.38 | F5: =SUM('Monthly CF'!AM7:AX7) -> 247089.78 | G5: =SUM('Monthly CF'!AY7:BJ7) -> 242565.54
B6: Reimbursement Income | C6: =SUM('Monthly CF'!C13:N13) -> 164518.2 | D6: =SUM('Monthly CF'!O13:Z13) -> 195949.64 | E6: =SUM('Monthly CF'!AA13:AL13) -> 197048.69 | F6: =SUM('Monthly CF'!AM13:AX13) -> 199830.57 | G6: =SUM('Monthly CF'!AY13:BJ13) -> 202424.27
B7: Additional Income | C7: =SUM('Monthly CF'!C8:N8) -> 16513 | D7: =SUM('Monthly CF'!O8:Z8) -> 16513 | E7: =SUM('Monthly CF'!AA8:AL8) -> 16513 | F7: =SUM('Monthly CF'!AM8:AX8) -> 16513 | G7: =SUM('Monthly CF'!AY8:BJ8) -> 16513
B8: Credit Loss | C8: =SUM('Monthly CF'!C10:N10) -> -10876.3 | D8: =SUM('Monthly CF'!O10:Z10) -> -12528.368 | E8: =SUM('Monthly CF'!AA10:AL10) -> -12791.119 | F8: =SUM('Monthly CF'!AM10:AX10) -> -13180.139 | G8: =SUM('Monthly CF'!AY10:BJ10) -> -12953.927
B9: Effective Gross Income | C9: =SUM('Monthly CF'!C11:N11) -> 206649.7 | D9: =SUM('Monthly CF'!O11:Z11) -> 238038.99 | E9: =SUM('Monthly CF'!AA11:AL11) -> 243031.26 | F9: =SUM('Monthly CF'!AM11:AX11) -> 250422.64 | G9: =SUM('Monthly CF'!AY11:BJ11) -> 246124.62
B11: OPERATING EXPENSES
B12: Total Operating Expenses | C12: =SUM('Monthly CF'!C18:N18) -> 182772.63 | D12: =SUM('Monthly CF'!O18:Z18) -> 186428.08 | E12: =SUM('Monthly CF'!AA18:AL18) -> 190156.64 | F12: =SUM('Monthly CF'!AM18:AX18) -> 193959.77 | G12: =SUM('Monthly CF'!AY18:BJ18) -> 197838.97
B13: Management Fee | C13: =SUM('Monthly CF'!C19:N19) -> 8265.988 | D13: =SUM('Monthly CF'!O19:Z19) -> 9521.5595 | E13: =SUM('Monthly CF'!AA19:AL19) -> 9721.2503 | F13: =SUM('Monthly CF'!AM19:AX19) -> 10016.906 | G13: =SUM('Monthly CF'!AY19:BJ19) -> 9844.9847
B14: Total Expenses | C14: =SUM('Monthly CF'!C20:N20) -> 191038.61 | D14: =SUM('Monthly CF'!O20:Z20) -> 195949.64 | E14: =SUM('Monthly CF'!AA20:AL20) -> 199877.89 | F14: =SUM('Monthly CF'!AM20:AX20) -> 203976.68 | G14: =SUM('Monthly CF'!AY20:BJ20) -> 207683.95
B16: NET OPERATING INCOME | C16: =SUM('Monthly CF'!C22:N22) -> 180129.29 | D16: =SUM('Monthly CF'!O22:Z22) -> 238038.99 | E16: =SUM('Monthly CF'!AA22:AL22) -> 240202.06 | F16: =SUM('Monthly CF'!AM22:AX22) -> 246276.53 | G16: =SUM('Monthly CF'!AY22:BJ22) -> 240864.93
B18: CapEx | C18: =SUM('Monthly CF'!C25:N25) -> -150000 | D18: =SUM('Monthly CF'!O25:Z25) -> 0 | E18: =SUM('Monthly CF'!AA25:AL25) -> 0 | F18: =SUM('Monthly CF'!AM25:AX25) -> 0 | G18: =SUM('Monthly CF'!AY25:BJ25) -> 0
B19: Tenant Improvements | C19: =SUM('Monthly CF'!C26:N26) -> -154600 | D19: =SUM('Monthly CF'!O26:Z26) -> 0 | E19: =SUM('Monthly CF'!AA26:AL26) -> 0 | F19: =SUM('Monthly CF'!AM26:AX26) -> -49200 | G19: =SUM('Monthly CF'!AY26:BJ26) -> -36200
B20: Leasing Commissions | C20: =SUM('Monthly CF'!C27:N27) -> -26523 | D20: =SUM('Monthly CF'!O27:Z27) -> 0 | E20: =SUM('Monthly CF'!AA27:AL27) -> 0 | F20: =SUM('Monthly CF'!AM27:AX27) -> -11299.89 | G20: =SUM('Monthly CF'!AY27:BJ27) -> -9167.2693
B21: CF Before Debt Service | C21: =SUM('Monthly CF'!C29:N29) -> -150993.71 | D21: =SUM('Monthly CF'!O29:Z29) -> 238038.99 | E21: =SUM('Monthly CF'!AA29:AL29) -> 240202.06 | F21: =SUM('Monthly CF'!AM29:AX29) -> 185776.64 | G21: =SUM('Monthly CF'!AY29:BJ29) -> 195497.66
B23: Total Debt Service | C23: =SUM('Monthly CF'!C32:N32) -> -154701.25 | D23: =SUM('Monthly CF'!O32:Z32) -> -176414.96 | E23: =SUM('Monthly CF'!AA32:AL32) -> -176414.96 | F23: =SUM('Monthly CF'!AM32:AX32) -> -176414.96 | G23: =SUM('Monthly CF'!AY32:BJ32) -> -176414.96
B24: Replacement Reserve | C24: =SUM('Monthly CF'!C33:N33) -> -8940 | D24: =SUM('Monthly CF'!O33:Z33) -> -8940 | E24: =SUM('Monthly CF'!AA33:AL33) -> -8940 | F24: =SUM('Monthly CF'!AM33:AX33) -> -8940 | G24: =SUM('Monthly CF'!AY33:BJ33) -> -8940
B25: Entity Expenses | C25: =SUM('Monthly CF'!C34:N34)+SUM('Monthly CF'!C35:N35)+SUM('Monthly CF'!C36:N36) -> -15880 | D25: =SUM('Monthly CF'!O34:Z34)+SUM('Monthly CF'!O35:Z35)+SUM('Monthly CF'!O36:Z36) -> -15880 | E25: =SUM('Monthly CF'!AA34:AL34)+SUM('Monthly CF'!AA35:AL35)+SUM('Monthly CF'!AA36:AL36) -> -15880 | F25: =SUM('Monthly CF'!AM34:AX34)+SUM('Monthly CF'!AM35:AX35)+SUM('Monthly CF'!AM36:AX36) -> -15880 | G25: =SUM('Monthly CF'!AY34:BJ34)+SUM('Monthly CF'!AY35:BJ35)+SUM('Monthly CF'!AY36:BJ36) -> -15880
B26: Cash Available for Distribution | C26: =SUM('Monthly CF'!C38:N38) -> -330514.96 | D26: =SUM('Monthly CF'!O38:Z38) -> 36804.024 | E26: =SUM('Monthly CF'!AA38:AL38) -> 38967.095 | F26: =SUM('Monthly CF'!AM38:AX38) -> -15458.325 | G26: =SUM('Monthly CF'!AY38:BJ38) -> -5737.3001
B28: Net Refi Proceeds | C28: =SUM('Monthly CF'!C40:N40) -> 593232.6 | D28: =SUM('Monthly CF'!O40:Z40) -> 0 | E28: =SUM('Monthly CF'!AA40:AL40) -> 0 | F28: =SUM('Monthly CF'!AM40:AX40) -> 0 | G28: =SUM('Monthly CF'!AY40:BJ40) -> 0
B29: Net Sale Proceeds | C29: =SUM('Monthly CF'!C47:N47) -> 0 | D29: =SUM('Monthly CF'!O47:Z47) -> 0 | E29: =SUM('Monthly CF'!AA47:AL47) -> 0 | F29: =SUM('Monthly CF'!AM47:AX47) -> 0 | G29: =SUM('Monthly CF'!AY47:BJ47) -> 1105714.8
B30: Net Cash Flow | C30: =SUM('Monthly CF'!C51:N51) -> -725282.36 | D30: =SUM('Monthly CF'!O51:Z51) -> 36804.024 | E30: =SUM('Monthly CF'!AA51:AL51) -> 38967.095 | F30: =SUM('Monthly CF'!AM51:AX51) -> -15458.325 | G30: =SUM('Monthly CF'!AY51:BJ51) -> 1099977.5
B33: ANNUAL METRICS
B34: NOI $/SF | C34: =IFERROR(C16/NRA,0) -> 10.074345 | D34: =IFERROR(D16/NRA,0) -> 13.313142 | E34: =IFERROR(E16/NRA,0) -> 13.43412 | F34: =IFERROR(F16/NRA,0) -> 13.773855 | G34: =IFERROR(G16/NRA,0) -> 13.471193
B35: Cash-on-Cash | C35: =IFERROR(C26/(Overview!I20-Overview!I6),0) -> -0.33452931 | D35: =IFERROR(D26/(Overview!I20-Overview!I6),0) -> 0.037251037 | E35: =IFERROR(E26/(Overview!I20-Overview!I6),0) -> 0.039440379 | F35: =IFERROR(F26/(Overview!I20-Overview!I6),0) -> -0.015646078 | G35: =IFERROR(G26/(Overview!I20-Overview!I6),0) -> -0.0058069839

Sheet Waterfall
A1: WATERFALL — TO BE BUILT
A3: GP/LP splits, preferred return, and promote tiers will be added in a future version.

Sheet Sensitivity
A1: SENSITIVITY ANALYSIS — TO BE BUILT
A3: IRR sensitivity matrices will be added in a future version.
